Workbook

Sheet Equipos
A1: EQUIPOS (EDITABLE)
A3: Codigo | B3: Tipo Equipo | C3: Marca | D3: Modelo | E3: Año | F3: Ubicacion | G3: Responsable | H3: Estado Base | I3: Control Base | J3: Frecuencia Base | K3: Promedio Diario
A4: CD-100 | B4: Camión Slurry | C4: Volkswagen | D4: 26220 | E4: 2008 | F4: San Carlos | G4: Carlos Aedo | H4: Operativo | I4: HORAS | J4: 250 | K4: 0
A5: CD-102 | B5: Camión Tolva | C5: Man | D5: TGS 50480 | E5: 2018 | F5: San Nicolas | G5: Nelson Cancino | H5: Operativo | I5: HORAS | J5: 500 | K5: 6.54
A6: CD-103 | B6: Camión Tolva | C6: Man | D6: TGS 50480 | E6: 2018 | F6: TALLER | G6: Felipe Figueroa | H6: Fuera de Servicio | I6: HORAS | J6: 500
A7: CD-104 | B7: Camión Tolva | C7: Man | D7: TGS 50480 | E7: 2019 | F7: Emergencias Curico | G7: Nelson Cancino Papá | H7: Operativo | I7: HORAS | J7: 250 | K7: 215.17
A8: CD-105 | B8: Camión Tolva | C8: Man | D8: TGS 50480 | E8: 2018 | F8: Palmucho | G8: Eugenio Hormazabal | H8: Operativo | I8: HORAS | J8: 500 | K8: 97.16
A9: CD-106 | B9: Camión Tolva | C9: Man | D9: TGS 50480 | E9: 2019 | F9: Emergencias Curico | G9: Felipe Figueroa | H9: Operativo | I9: HORAS | J9: 500 | K9: 120.58
A10: CD-107 | B10: Camión Tolva | C10: Man | D10: TGS 50480 | E10: 2019 | F10: Taller | G10: Cesar Vergara | H10: Operativo | I10: HORAS | J10: 500 | K10: 147.06
A11: CD-108 | B11: Camión Slurry | C11: International | D11: 7600 | E11: 2008 | F11: Palmucho | G11: Patricio Salas | H11: Operativo | I11: HORAS | J11: 250 | K11: 0
A12: CD-109 | B12: Camión Plano | C12: Hino | D12: XZU 6.5 DCAB | E12: 2012 | F12: Palmucho | G12: Washington Sanzana | H12: Operativo | I12: KM | J12: 10000 | K12: 102.86
A13: CD-110 | B13: Camión Plano | C13: Jac | D13: Urban HFC1050K | E13: 2015 | F13: Cobquecura | G13: Rodolfo Vera | H13: Operativo | I13: HORAS | J13: 250 | K13: 70.85
A14: CD-111 | B14: Camión Plano | C14: Mercedes Benz | D14: Atego 1315 48 | E14: 2007 | F14: TALLER | G14: Sin asignar | H14: Fuera de Servicio | I14: HORAS | J14: 250
A15: CD-112 | B15: Camión Pintura | C15: No hay info | D15: No hay info | E15: No hay info | F15: TALLER | G15: Sin asignar | H15: Fuera de Servicio | I15: HORAS | J15: 250
A16: CD-113 | B16: Camión Imprimador | C16: Volkswagen | D16: 17180M | E16: 2011 | F16: Quirihue | G16: Frank Yegres | H16: Operativo | I16: HORAS | J16: 250 | K16: 0
A17: CD-114 | B17: Camión Imprimador | C17: Freightliner | D17: M2 112 | E17: 1998 | F17: Palmucho | G17: Juan Espinoza | H17: Operativo | I17: HORAS | J17: 250 | K17: 2.71
A18: CD-115 | B18: Tracto Camión | C18: Mercedes Benz | D18: LS 1634 45 | E18: 2011 | F18: Taller ext | G18: Manuel Pacheco | H18: Taller | I18: KM | J18: 10000 | K18: 391.03
A19: CD-116 | B19: Camión Plano | C19: Wolkswagen | D19: 9150E | E19: 2012 | F19: Taller | G19: Nicolas Morales | H19: Operativo | I19: HORAS | J19: 250 | K19: 0
A20: CD-117 | B20: Camión Slurry | C20: No hay info | D20: No hay info | E20: No hay info | F20: Taller | G20: Sin asignar | H20: Fuera de Servicio | I20: HORAS | J20: 250 | K20: 0
A21: CD-118 | B21: Camión Plano | C21: Freightliner | D21: M2 106 | E21: 2010 | F21: Taller | G21: Carlos Vasquez | H21: Operativo | I21: HORAS | J21: 250 | K21: 292.62
A22: CD-119 | B22: Camión Combustible | C22: Hino | D22: GH8JMTA | E22: 2013 | F22: San Nicolas | G22: Nector Muñoz | H22: Operativo | I22: HORAS | J22: 250 | K22: 5.15
A23: CD-120 | B23: Camión Tolva | C23: Man | D23: TGS 40400 BB | E23: 2024 | F23: Cobquecura | G23: Pablo Torres | H23: Operativo | I23: HORAS | J23: 500 | K23: 121.61
A24: CD-121 | B24: Camión Tolva | C24: Man | D24: TGS 40400 BB | E24: 2024 | F24: Cobquecura | G24: Chandor Ruiz | H24: Operativo | I24: HORAS | J24: 500 | K24: 105.37
A25: CD-122 | B25: Camión Tolva | C25: Man | D25: TGS 40400 BB | E25: 2024 | F25: San Nicolas | G25: Renan Aguilera | H25: Operativo | I25: HORAS | J25: 500 | K25: 1.36
A26: CD-123 | B26: Camión Tolva | C26: Man | D26: TGS 40400 BB | E26: 2024 | F26: San Nicolas | G26: Wilson Salazar | H26: Operativo | I26: HORAS | J26: 500 | K26: 42.24
A27: CD-124 | B27: Camión Tolva | C27: Man | D27: TGS 40400 BB | E27: 2024 | H27: Fuera de Servicio | I27: HORAS | J27: 500 | K27: 0
A28: CD-125 | B28: Camión Maxus | C28: Maxus | D28: C35 2.0 | E28: 2023 | F28: Taller | G28: Patricio Mora | H28: Operativo | I28: HORAS | J28: 250 | K28: 259.61
A29: CD-126 | B29: Camión Maxus | C29: Maxus | D29: C35 2.0 | E29: 2023 | F29: Taller (Kauffman) | G29: Manuel Piñaleo | H29: Operativo | I29: HORAS | J29: 250
A30: CD-127 | B30: Camión Pluma | C30: International | D30: 4300 | E30: 2012 | F30: Taller | G30: Osvaldo Faundez | H30: Operativo | I30: HORAS | J30: 250 | K30: 127.61
A31: CD-128 | B31: Camión slurry | C31: Mack | D31: GU 813 | E31: 2012 | F31: Palmucho | G31: Marcelo Candelara | H31: Operativo | I31: HORAS | J31: 250 | K31: 24.84
A32: CD-129 | B32: Camión Aljibe | C32: Mack | D32: GU 813 | E32: 2012 | F32: TALLER | G32: Sin asignar | H32: Fuera de Servicio | I32: HORAS | J32: 250
A33: CD-130 | B33: Camión Tolva | C33: Renault | D33: K480 | E33: 2021 | F33: Taller | G33: Sin asignar | H33: Fuera de Servicio | I33: HORAS | J33: 500 | K33: 58.71
A34: CD-131 | B34: Camión Tolva | C34: Renault | D34: K480 | E34: 2021 | F34: Taller | G34: Sin asignar | H34: Fuera de Servicio | I34: HORAS | J34: 250 | K34: 275
A35: CD-132 | B35: Camión Tolva | C35: Renault | D35: K480 | E35: 2021 | F35: Palmucho | G35: Cesar Vergara | H35: Operativo | I35: HORAS | J35: 500 | K35: 168.21
A36: CD-133 | B36: Camión Plano | C36: International | D36: 7400 | E36: 2010 | F36: TALLER | G36: Sin asignar | H36: Fuera de Servicio | I36: HORAS | J36: 250
A37: CD-134 | B37: Camión Plano | C37: International | D37: 4300 | E37: 2012 | F37: TALLER | G37: Sin asignar | H37: Taller | I37: HORAS | J37: 250 | K37: 0
A38: CD-135 | B38: Camión Plano | C38: Mack | D38: GU 813 | E38: 2014 | F38: TALLER | G38: Sin asignar | H38: Fuera de Servicio | I38: HORAS | J38: 250
A39: CD-136 | B39: Camión Combustible | C39: Hino | D39: HZU | E39: 2015 | F39: Obras Varias | G39: Orlando Sanchez | H39: Operativo | I39: KM | J39: 10000 | K39: 81.79
A40: CD-137 | B40: Tracto Camión | C40: Mercedes Benz | D40: Axor 1936 | E40: 2014 | F40: Taller | G40: Manuel Pacheco | H40: Operativo | I40: HORAS | J40: 250 | K40: 139.79
A41: CD-138 | B41: Camion Imprimador | C41: Sterling | D41: L7500 | F41: San Carlos | G41: Duban Rio | H41: Operativo | I41: HORAS | J41: 250 | K41: 354.05
A42: CD-139 | B42: Camion Plano | C42: Mercedes Benz | D42: Atego 1015 | E42: 2011 | H42: Fuera de Servicio | I42: HORAS | J42: 250
A43: CD-140 | B43: Camion Plano | C43: Mercedes Benz | D43: 915 C 37 | E43: 2011 | F43: Palmucho | H43: Operativo | I43: KM | J43: 10000 | K43: 175.78
A44: CD-141 | B44: Camion Mixer | C44: Mack | D44: DM 690S | E44: 1997 | F44: Palmucho | H44: Operativo | I44: HORAS | J44: 250
A45: CD-142 | B45: Camion Mixer | C45: Freightliner | D45: FLD 112 | E45: 2006 | F45: Palmucho | H45: Operativo | I45: HORAS | J45: 250
A46: CD-51 | B46: Camión Combustible | C46: Hino | D46: XZU 8.0 | E46: 2011 | F46: Palmucho | G46: Salvador Castillo | H46: Operativo | I46: KM | J46: 10000 | K46: 42.8
A47: CD-57 | B47: Camión Plano | C47: Hino | D47: XZUDCAB | E47: 2012 | F47: SANTIAGO | G47: No aplica | H47: Fuera de Servicio | I47: HORAS | J47: 250
A48: CD-68 | B48: Camión Aljibe | C48: Mack | D48: GU 813 | E48: 2008 | F48: Cobquecura | G48: Froilan Campos | H48: Operativo | I48: HORAS | J48: 250 | K48: 24.17
A49: CD-69 | B49: Tracto Camión | C49: Scania | D49: P400A | E49: 2018 | F49: Taller | G49: Pedro Rojas | H49: Operativo | I49: Km | J49: 10000 | K49: 233.13
A50: CD-71 | B50: Camión Aljibe | C50: Mack | D50: GU 813 | E50: 2008 | F50: Palmucho | G50: Hernan Henriquez | H50: Operativo | I50: HORAS | J50: 250 | K50: 18.17
A51: CD-73 | B51: Camión Aljibe | C51: Mack | D51: GU 813 | E51: 2014 | F51: TALLER | G51: Sin asignar | H51: Operativo | I51: HORAS | J51: 250
A52: CD-74 | B52: Tracto Camión | C52: Renault | D52: Premium Lander | E52: 2011 | F52: TALLER | G52: Sin asignar | H52: Fuera de Servicio | I52: HORAS | J52: 250
A53: CD-80 | B53: Camión Pluma | C53: International | D53: 7600 | E53: 2012 | H53: Fuera de Servicio | I53: HORAS | J53: 250
A54: CD-86 | B54: Camión Aljibe | C54: Kenworth | D54: T800 | E54: 2010 | F54: Quirihue | G54: Francisco Pino | H54: Operativo | I54: HORAS | J54: 250 | K54: 0
A55: CD-87 | B55: Camión Tolva | C55: Man | D55: TGS 40400 BB | E55: 2020 | F55: Emergencias Curico | G55: Juan Aguilar | H55: Operativo | I55: HORAS | J55: 500 | K55: 64.91
A56: CD-88 | B56: Camión Tolva | C56: Man | D56: TGS 40400 BB | E56: 2020 | F56: Taller | G56: Jose Andaur | H56: Operativo | I56: HORAS | J56: 500 | K56: 167.3
A57: CD-89 | B57: Camión Tolva | C57: Man | D57: TGS 40400 BB | E57: 2020 | F57: Palmucho | G57: Gerardo Beltran | H57: Operativo | I57: HORAS | J57: 500 | K57: 45.47
A58: CD-90 | B58: Camión Tolva | C58: Man | D58: TGS 40400 BB | E58: 2020 | F58: Emergencias Curico | G58: Luis Sepulveda | H58: Operativo | I58: HORAS | J58: 500 | K58: 96.44
A59: CD-91 | B59: Camión Tolva | C59: Man | D59: TGS 40400 BB | E59: 2020 | F59: TALLER | G59: Sin asignar | H59: Fuera de Servicio | I59: HORAS | J59: 500 | K59: 164.84
A60: CD-92 | B60: Camión Combustible | C60: Hino | D60: XZU423L | E60: 2011 | H60: Fuera de Servicio | I60: HORAS | J60: 250 | K60: 0
A61: CD-93 | B61: Camión Plano | C61: Hino | D61: XZUDCAB | E61: 2013 | F61: Taller | G61: Jose Valenzuela | H61: Fuera de Servicio | I61: HORAS | J61: 250
A62: CD-94 | B62: Camión Tolva | C62: Man | D62: TGS 33400 | E62: 2018 | F62: Palmucho | G62: Nelson Garcia | H62: Operativo | I62: HORAS | J62: 500 | K62: 51.14
A63: CD-96 | B63: Camión Aljibe | C63: Mercedes Benz | D63: Atego 1315 48 | E63: 2007 | F63: Palmucho | G63: Miguel Pereira | H63: Operativo | I63: HORAS | J63: 250 | K63: 126.64
A64: CD-97 | B64: Tracto Camión | C64: Man | D64: TGS 33480 | E64: 2013 | F64: Taller | G64: Ramiro Solis | H64: Operativo | I64: HORAS | J64: 250 | K64: 99.67
A65: CD-98 | B65: Camión Plano | C65: Hino | D65: Xzu 6.5 | E65: 2014 | F65: Emergencias Curico | G65: Luis Flores | H65: Operativo | I65: KM | J65: 10000 | K65: 0
A66: CD-99 | B66: Camión Aljibe | C66: Freightliner | D66: M2 112 | E66: 2013 | F66: Taller ext | G66: Jaime Alonso Vargas Gangas | H66: Fuera de Servicio | I66: HORAS | J66: 250 | K66: 10.55
A67: ED-07 | B67: Soldadora | C67: Indura | D67: 400 | E67: 1990 | F67: TALLER | G67: No aplica | H67: Operativo | I67: HORAS | J67: 250
A68: ED-51 | B68: Gravilladora | C68: Etnyre | D68: K-5180 | E68: 2010 | F68: RETIRO | G68: No identificado | H68: Operativo | I68: HORAS | J68: 250 | K68: 0
A69: ED-52 | B69: Barredora | C69: Rosco | D69: Rb-48 | E69: 2000 | F69: Ninhue | G69: Jordano Villa | H69: Operativo | I69: HORAS | J69: 250 | K69: 13.28
A70: ED-61 | B70: Gravilladora | C70: Rosco | D70: 4wd | E70: 2001 | F70: TALLER | G70: Sebastian Nuñez | H70: Operativo | I70: HORAS | J70: 250 | K70: 0.49
A71: ED-63 | B71: Barredora | C71: Rosco | D71: K-5180 | E71: 2000 | F71: RETIRO | G71: Maximo Apablaza | H71: Operativo | I71: HORAS | J71: 250 | K71: 1.13
A72: ED-64 | B72: Perforadora Hidraulica | C72: Furukawua | D72: HCR1200-EDII | E72: 2017 | F72: TALLER | G72: No aplica | H72: Operativo | I72: HORAS | J72: 250
A73: ED-65 | B73: Compresor | C73: Atlas Copco | D73: EHR-700 | E73: 2020 | F73: TALLER | G73: No aplica | H73: Operativo | I73: HORAS | J73: 250
A74: ED-66 | B74: Planta Micropavimento | C74: Romanelli | D74: UHR700H | E74: 2021 | F74: TALLER | G74: No aplica | H74: Operativo | I74: HORAS | J74: 250
A75: ED-67 | B75: Imprimador | C75: Rayner | D75: Rayner | E75: 2020 | F75: TALLER | G75: No aplica | H75: Operativo | I75: HORAS | J75: 250
A76: ED-74 | B76: Gravilladora | C76: Rosco | D76: SPRHH | E76: 2007 | I76: HORAS | J76: 250 | K76: 3.11
A77: EQP-10 | B77: Planta aridos | C77: Sandvik | D77: QS331 | E77: 2016 | F77: Taller | G77: Roberto Tilleria | H77: Operativo | I77: HORAS | J77: 250
A78: EQP-11 | B78: Planta Aridos seleccionadora | C78: Terex | D78: 674 | E78: 2017 | F78: Palmucho | G78: Patriicio Rodriguez | H78: Operativo | I78: HORAS | J78: 250 | K78: 1.71
A79: EQP-13 | B79: Planta aridos | C79: Sandvik | D79: UH440I | E79: 2010 | F79: Taller | G79: No aplica | H79: Fuera de Servicio | I79: HORAS | J79: 250
A80: EQP-14 | B80: Planta aridos | C80: Kleemann | D80: Mc 110R | E80: 2014 | F80: Taller | G80: Rodrigo Fuentes | H80: Fuera de Servicio | I80: HORAS | J80: 250
A81: EQP-15 | B81: Planta Aridos seleccionadora | C81: Rubble Master | D81: HS 11000 M | E81: 2020 | F81: San Nicolas | G81: Jordan Andrades | H81: Fuera de Servicio | I81: HORAS | J81: 250 | K81: 0
A82: EQP-16 | B82: Planta aridos | C82: Sandvik | D82: UH440I | E82: 2010 | F82: Palmucho | G82: Sandro Quiroz | H82: Operativo | I82: HORAS | J82: 250 | K82: 2.74
A83: EQP-17 | B83: Planta Aridos seleccionadora | C83: Maximuss | D83: 512 | F83: San Nicolas | H83: Fuera de Servicio | I83: HORAS | J83: 250 | K83: 1.57
A84: EQP-18 | B84: Planta aridos | C84: Kleemann | D84: Mc 110Z | E84: 2019 | F84: Palmucho | G84: Jose Pereira | H84: Operativo | I84: HORAS | J84: 250 | K84: 1.99
A85: EQP-19 | B85: Planta aridos | C85: Iveco | D85: GeCursor 300ED | E85: 2008 | F85: Taller | G85: Roberto Tilleria | H85: Operativo | I85: HORAS | J85: 250
A86: EQP-7 | B86: Planta aridos | C86: Sandvik | D86: UH440I | E86: 2010 | F86: San Nicolas | G86: Rodrigo Fuentes | H86: Operativo | I86: HORAS | J86: 250 | K86: 4.38
A87: EQP-9 | B87: Planta aridos | C87: Sandvik | D87: QJ341 | E87: 2014 | F87: PALMUCHO | G87: Roberto Tilleria | H87: Fuera de Servicio | I87: HORAS | J87: 250
A88: MD-100 | B88: Excavadora | C88: Sany | D88: SY215CLC | E88: 2024 | F88: San Nicolas | G88: Sergio Gonzalez | H88: Operativo | I88: HORAS | J88: 250 | K88: 5.48
A89: MD-101 | B89: Motoniveladora | C89: Komatsu | D89: GD675 5 | E89: 2018 | F89: Palmucho | G89: Bernardo Escanilla | H89: Operativo | I89: HORAS | J89: 250 | K89: 3.52
A90: MD-102 | B90: Rodillo | C90: Bomag | D90: BW211 D40 | E90: 2014 | F90: Cobquecura | G90: Pedro Uribe | H90: Operativo | I90: HORAS | J90: 300 | K90: 3.58
A91: MD-103 | B91: Rodillo | C91: Bomag | D91: BW211 D5 | E91: 2019 | F91: Quirihue | G91: German Rojas | H91: Operativo | I91: HORAS | J91: 300 | K91: 2.86
A92: MD-104 | B92: Excavadora | C92: Sany | D92: SY215CLC | E92: 2024 | F92: Emergencias Curico | G92: Rodolfo Benavides | H92: Operativo | I92: HORAS | J92: 250 | K92: 4.11
A93: MD-105 | B93: Cargador Frontal | C93: Hyundai | D93: HL7709S | E93: 2019 | F93: Mantul | G93: No identificado | H93: Operativo | I93: HORAS | J93: 250 | K93: 2.06
A94: MD-106 | B94: Maquina Industrial | C94: Dieci | D94: L 3500 | E94: 2016 | H94: No operativo | I94: HORAS | J94: 250
A95: MD-107 | B95: Cargador Frontal | C95: Sany | D95: SW978K1 | E95: 2024 | F95: San Nicolas | G95: Francisco Barrueto | H95: Operativo | I95: HORAS | J95: 250 | K95: 6.21
A96: MD-108 | B96: Rodillo de Neumaticos | C96: Hamm | D96: GRW15 | E96: 2008 | F96: San Carlos | G96: Isaias Arriagada | H96: Operativo | I96: HORAS | J96: 250 | K96: 1.43
A97: MD-109 | B97: Motoniveladora | C97: Caterpillar | D97: 12M | E97: 2019 | F97: Palmucho | G97: Luis Cortes | H97: Operativo | I97: HORAS | J97: 250 | K97: 2.96
A98: MD-110 | B98: Motoniveladora | C98: Caterpillar | D98: 12M | E98: 2019 | F98: Cobquecura | G98: Claudio Caceres | H98: Operativo | I98: HORAS | J98: 250 | K98: 4.07
A99: MD-25 | B99: Motoniveladora | C99: John Deere | D99: 772 D | E99: 2010 | F99: San Carlos | G99: Felipe Ortiz | H99: Operativo | I99: HORAS | J99: 250 | K99: 1.87
A100: MD-26 | B100: Motoniveladora | C100: John Deere | D100: 772 D | E100: 2010 | F100: Cobquecura | G100: Hector Reyes | H100: Operativo | I100: HORAS | J100: 250 | K100: 2.88
A101: MD-28 | B101: Excavadora | C101: Doosan | D101: Dx225lca | E101: 2011 | F101: Villaseca | G101: Rodrigo Contreras | H101: Operativo | I101: HORAS | J101: 250 | K101: 1.39
...

Sheet Lecturas
A1: LECTURAS (EDITABLE)
A3: Fecha | B3: Codigo | C3: Horometro | D3: Kilometraje | E3: Obra / Ubicacion | F3: Responsable | G3: Observacion
A4: 46065 | B4: CD-100 | C4: 2852
A5: 44607 | B5: CD-100 | C5: 1937
A6: 44553 | B6: CD-100 | C6: 1683
A7: 44329 | B7: CD-100 | C7: 985
A8: 46132 | B8: CD-102 | C8: 10496 | E8: SAN NICOLAS
A9: 46115 | B9: CD-102 | C9: 10378 | D9: 260271 | E9: Quirihue
A10: 46101 | B10: CD-102 | C10: 10368 | D10: 262575 | E10: Quirihue
A11: 46099 | B11: CD-102 | C11: 10361 | D11: 262326 | E11: Quirihue
A12: 45056 | B12: CD-103 | C12: 5327 | D12: 126893
A13: 46114 | B13: CD-104 | D13: 261250 | E13: Curicó
A14: 46113 | B14: CD-104 | D14: 260933 | E14: Curicó
A15: 46108 | B15: CD-104 | E15: Curicó | F15: Nelson Omar Cancino Arellano | G15: Carga combustible importada 2026-04-01
A16: 46083 | B16: CD-104 | C16: 8820 | D16: 258456
A17: 46107 | B17: CD-105 | C17: 10623 | D17: 257067 | E17: Palmucho
A18: 46107 | B18: CD-105 | C18: 10611 | D18: 256570 | E18: Palmucho
A19: 46105 | B19: CD-105 | C19: 10599 | D19: 256409 | E19: Palmucho
A20: 46105 | B20: CD-105 | C20: 10590 | D20: 256246 | E20: Palmucho
A21: 46105 | B21: CD-106 | C21: 8345 | E21: Taller
A22: 46070 | B22: CD-106 | D22: 250115
A23: 46052 | B23: CD-106 | C23: 8328 | D23: 168556
A24: 46049 | B24: CD-106 | C24: 8221 | D24: 168332
A25: 46092 | B25: CD-107 | C25: 10923 | E25: San Nicolas
A26: 46087 | B26: CD-107 | C26: 10837
A27: 46086 | B27: CD-107 | C27: 10820
A28: 46065 | B28: CD-107 | C28: 10863
A29: 46107 | B29: CD-108 | D29: 48763 | E29: Palmucho
A30: 46077 | B30: CD-108 | D30: 98639
A31: 46077 | B31: CD-108 | D31: 98639
A32: 46062 | B32: CD-108 | D32: 98550
A33: 46106 | B33: CD-109 | D33: 190409 | E33: Palmucho
A34: 46101 | B34: CD-109 | D34: 190215 | E34: Palmucho
A35: 46098 | B35: CD-109 | D35: 190022 | E35: Palmucho
A36: 46080 | B36: CD-109 | D36: 189344
A37: 46111 | B37: CD-110 | D37: 275886 | E37: Cobquecura
A38: 46101 | B38: CD-110 | D38: 275095 | E38: Cobquecura
A39: 46098 | B39: CD-110 | D39: 274769 | E39: Cobquecura
A40: 46078 | B40: CD-110 | D40: 274320
A41: 46050 | B41: CD-113 | D41: 121065
A42: 46043 | B42: CD-113 | D42: 802320
A43: 46036 | B43: CD-113 | D43: 802920
A44: 45994 | B44: CD-113 | D44: 802920
A45: 46107 | B45: CD-114 | C45: 3882 | E45: Palmucho
A46: 46107 | B46: CD-114 | C46: 3887 | E46: Palmucho
A47: 46106 | B47: CD-114 | C47: 3877 | E47: Palmucho
A48: 46099 | B48: CD-114 | C48: 3868 | E48: Palmucho
A49: 46064 | B49: CD-115 | D49: 333912 | E49: Taller
A50: 46058 | B50: CD-115 | D50: 330885
A51: 46050 | B51: CD-115 | D51: 330286
A52: 46043 | B52: CD-115 | D52: 329180
A53: 46100 | B53: CD-116 | E53: Villaseca | F53: Nicolas Antonio Rivera Astudillo | G53: Carga combustible importada 2026-04-01
A54: 46094 | B54: CD-116 | E54: Villaseca | F54: Nicolas Antonio Rivera Astudillo | G54: Carga combustible importada 2026-04-01
A55: 46044 | B55: CD-116 | D55: 329583
A56: 46034 | B56: CD-117 | D56: 114148
A57: 46099 | B57: CD-118 | D57: 917261 | E57: Quirihue
A58: 46086 | B58: CD-118 | D58: 512848
A59: 46085 | B59: CD-118 | D59: 516492
A60: 46083 | B60: CD-118 | D60: 514492
A61: 46115 | B61: CD-119 | D61: 194120 | E61: Quirihue
A62: 46104 | B62: CD-119 | C62: 2841 | E62: San Carlos
A63: 46101 | B63: CD-119 | C63: 2832 | D63: 195800 | E63: San Carlos
A64: 46101 | B64: CD-119 | D64: 195800 | E64: San Carlos | F64: Nector Aldo Muñoz Rivera | G64: Carga combustible importada 2026-04-01
A65: 46070 | B65: CD-120 | C65: 3360
A66: 46060 | B66: CD-120 | C66: 3340
A67: 46056 | B67: CD-120 | C67: 3324
A68: 46111 | B68: CD-121 | C68: 3552 | D68: 89291 | E68: Cobquecura
A69: 46098 | B69: CD-121 | C69: 3502 | D69: 88762 | E69: Cobquecura
A70: 46077 | B70: CD-121 | C70: 3440 | D70: 88032
A71: 46072 | B71: CD-121 | C71: 3431 | D71: 87953
A72: 46106 | B72: CD-122 | C72: 3774 | D72: 97492 | E72: San Carlos
A73: 46100 | B73: CD-122 | C73: 3759 | D73: 97224 | E73: Quirihue
A74: 46098 | B74: CD-122 | C74: 3751 | D74: 97036 | E74: Quirihue
A75: 46093 | B75: CD-122 | C75: 3694
A76: 46101 | B76: CD-123 | C76: 3720 | E76: Ninhue
A77: 46087 | B77: CD-123 | D77: 99818
A78: 46076 | B78: CD-123 | D78: 99221
A79: 46072 | B79: CD-123 | D79: 98782
A80: 46048 | B80: CD-124 | D80: 48160
A81: 46100 | B81: CD-125 | D81: 79301 | E81: Cobquecura
A82: 46100 | B82: CD-125 | D82: 79301 | E82: Oficina Central | F82: Patricio Alfredo Mora Mora | G82: Carga combustible importada 2026-04-01
A83: 46072 | B83: CD-125 | C83: 1471 | D83: 75372
A84: 46070 | B84: CD-125 | D84: 74376
A85: 46114 | B85: CD-127 | D85: 126821 | E85: Oficina Central
A86: 46107 | B86: CD-127 | D86: 125252 | E86: Palmucho
A87: 46106 | B87: CD-127 | D87: 125001 | E87: Palmucho
A88: 46100 | B88: CD-127 | D88: 123978 | E88: Oficina Central
A89: 46105 | B89: CD-128 | D89: 141791 | E89: Palmucho
A90: 46090 | B90: CD-128 | D90: 141196 | E90: Retiro | F90: Marco Calderara | G90: Carga combustible importada 2026-04-01
A91: 46086 | B91: CD-128 | D91: 140968
A92: 46078 | B92: CD-128 | D92: 140754
A93: 46020 | B93: CD-130 | D93: 80732
A94: 45996 | B94: CD-130 | D94: 79323
A95: 46003 | B95: CD-131 | D95: 80500
A96: 46000 | B96: CD-131 | D96: 79675
A97: 46115 | B97: CD-132 | C97: 7602 | D97: 193220 | E97: Quirihue
A98: 46104 | B98: CD-132 | C98: 7962 | D98: 195464 | E98: Palmucho
A99: 46100 | B99: CD-132 | C99: 7678 | D99: 195090 | E99: Palmucho
A100: 46099 | B100: CD-132 | C100: 7674 | D100: 195002 | E100: Palmucho
A101: 46050 | B101: CD-134 | D101: 121065
...

Sheet Mantenciones
A3: Fecha | B3: Codigo | C3: Tipo Mantencion | D3: Lectura | E3: EsPM | F3: Folio | G3: Lugar | H3: Mecanico | I3: Costo Mantencion CLP | J3: Estado
A4: 45967 | B4: MD-57 | C4: Mantencion PM2 | D4: 13469 | E4: Sí | F4: 15910 | J4: Finalizada
A5: 45954 | B5: MD-83 | C5: Mantencion PM2 | D5: 7636 | E5: Sí | F5: 15906 | J5: Finalizada
A6: 45967 | B6: MD-68 | C6: Mantencion PM2 | D6: 3240 | E6: Sí | F6: 15908 | J6: Finalizada
A7: 46042 | B7: MD-83 | C7: Mantencion PM2 | D7: 8046 | E7: Sí | J7: Finalizada
A8: 45972 | B8: CD-88 | C8: Mantencion PM2 | D8: 1453 | E8: Sí | F8: 15913 | J8: Finalizada
A9: 45980 | B9: CD-102 | C9: Mantencion PM2 | D9: 9695 | E9: Sí | F9: 15914 | J9: Finalizada
A10: 45982 | B10: MD-95 | C10: Mantencion PM2 | D10: 1413 | E10: Sí | F10: 15178 | J10: Finalizada
A11: 45985 | B11: MD-88 | C11: Mantencion PM2 | D11: 6327 | E11: Sí | F11: 15179 | J11: Finalizada
A12: 45993 | B12: MD-102 | C12: Mantencion PM2 | D12: 5321 | E12: Sí | F12: 15184 | J12: Finalizada
A13: 45995 | B13: MD-94 | C13: Mantencion PM2 | D13: 2060 | E13: Sí | F13: 15186 | J13: Finalizada
A14: 46008 | B14: VD-78 | C14: Mantencion PM1 | D14: 128090 | E14: Sí | F14: SN | J14: Finalizada
A15: 46009 | B15: VD-77 | C15: Mantencion PM1 | D15: 128838 | E15: Sí | F15: SN | J15: Finalizada
A16: 46014 | B16: CD-97 | C16: Mantencion PM1 | D16: 530211 | E16: Sí | F16: SN | J16: Finalizada
A17: 46015 | B17: CD-69 | C17: Mantencion PM2 | D17: 461588 | E17: Sí | F17: 389 | J17: Finalizada
A18: 46028 | B18: MD-73 | C18: Mantencion PM1 | D18: 17076 | E18: Sí | F18: 389 | J18: Finalizada
A19: 46028 | B19: CD-142 | C19: Mantencion PM1 | D19: 331891 | E19: Sí | F19: 389 | J19: Finalizada
A20: 45971 | B20: MD-96 | C20: Mantencion PM1 | D20: 1496 | E20: Sí | F20: 15912 | J20: Finalizada
A21: 46031 | B21: MD-109 | C21: Mantencion PM1 | D21: 87661 | E21: Sí | F21: 389 | J21: Finalizada
A22: 46034 | B22: VD-119 | C22: Mantencion PM1 | E22: Sí | F22: 389 | J22: Finalizada
A23: 46034 | B23: VD-84 | C23: Mantencion PM1 | D23: 118530 | E23: Sí | F23: SN | J23: Finalizada
A24: 46034 | B24: ED-73 | C24: Mantencion PM1 | D24: 681 | E24: Sí | J24: Finalizada
A25: 45908 | B25: MD-107 | C25: Mantencion PM2 | D25: 393 | E25: Sí | F25: 15911 | J25: Finalizada
A26: 46035 | B26: VD-91 | C26: Mantencion PM1 | D26: 105667 | E26: Sí | F26: 389 | J26: Finalizada
A27: 46036 | B27: VD-76 | C27: Mantencion PM1 | D27: 157018 | E27: Sí | F27: 389 | J27: Finalizada
A28: 45967 | B28: MD-107 | C28: Mantencion PM2 | D28: 748 | E28: Sí | F28: 15911 | J28: Finalizada
A29: 46037 | B29: VD-95 | C29: Mantencion PM1 | D29: 136208 | E29: Sí | F29: 389 | J29: Finalizada
A30: 45967 | B30: MD-100 | C30: Mantencion PM2 | D30: 2000 | E30: Sí | F30: 15909 | J30: Finalizada
A31: 46028 | B31: MD-100 | C31: Mantencion PM2 | D31: 2600 | E31: Sí | F31: 15920 | J31: Finalizada
A32: 46035 | B32: MD-107 | C32: Mantencion PM2 | D32: 1112 | E32: Sí | F32: 15921 | J32: Finalizada
A33: 46044 | B33: CD-132 | C33: Mantencion PM1 | D33: 189042 | E33: Sí | J33: Finalizada
A34: 46044 | B34: CD-106 | C34: Mantencion PM1 | D34: 8319 | E34: Sí | J34: Finalizada
A35: 46049 | B35: MD-75 | C35: Mantencion PM2 | E35: Sí | F35: 15440 | J35: Finalizada
A36: 46050 | B36: MD-101 | C36: Mantencion PM1 | D36: 9814 | E36: Sí | J36: Finalizada
A37: 46050 | B37: VD-111 | C37: Mantencion PM1 | D37: 54500 | E37: Sí | J37: Finalizada
A38: 46057 | B38: MD-56 | C38: Mantencion PM1 | D38: 15554 | E38: Sí | J38: Finalizada
A39: 46065 | B39: VD-78 | C39: Mantencion PM1 | D39: 138841 | E39: Sí | J39: Finalizada
A40: 46066 | B40: CD-87 | C40: Mantencion PM1 | D40: 9302 | E40: Sí | J40: Finalizada
A41: 46072 | B41: VD-122 | C41: Mantencion PM1 | D41: 39996 | E41: Sí | F41: 16152 | J41: Finalizada
A42: 46073 | B42: VD-125 | C42: Mantencion PM1 | D42: 58306 | E42: Sí | F42: Ext | J42: Finalizada
A43: 46073 | B43: CD-69 | C43: Mantencion PM2 | D43: 486500 | E43: Sí | F43: 15104 | J43: Finalizada
A44: 46074 | B44: VD-116 | C44: Mantencion PM1 | D44: 61948 | E44: Sí | F44: 15101 | J44: Finalizada
A45: 45965 | B45: VD-112 | C45: Mantencion PM1 | D45: 81949 | E45: Sí | F45: 389 | J45: Finalizada
A46: 45859 | B46: VD-78 | C46: Mantencion PM1 | D46: 110210 | E46: Sí | J46: Finalizada
A47: 46066 | B47: MD-100 | C47: Mantencion PM2 | D47: 2610 | E47: Sí | F47: 15961 | J47: Finalizada
A48: 46055 | B48: VD-110 | C48: Mantencion PM1 | D48: 79968 | E48: Sí | F48: 15956 | J48: Finalizada
A49: 46062 | B49: CD-102 | C49: Mantencion PM2 | D49: 10370 | E49: Sí | F49: 15959 | J49: Finalizada
A50: 46060 | B50: CD-104 | C50: Mantencion PM2 | D50: 8700 | E50: Sí | F50: nn | J50: Finalizada
A51: 46078 | B51: VD-29 | C51: Mantencion PM1 | E51: Sí | F51: nn | J51: Finalizada
B52: VD-100 | C52: Mantencion PM1 | D52: 89665 | E52: Sí | J52: Finalizada
A53: 46086 | B53: MD-26 | C53: Mantencion PM2 | D53: 16953 | E53: Sí | J53: Finalizada
A54: 46086 | B54: CD-120 | C54: Mantencion PM2 | D54: 3406 | E54: Sí | J54: Finalizada
A55: 46085 | B55: CD-121 | C55: Mantencion PM2 | D55: 3468 | E55: Sí | J55: Finalizada
A56: 46086 | B56: CD-140 | C56: Mantencion PM1 | D56: 295000 | E56: Sí | J56: Finalizada
A57: 46084 | B57: CD-122 | C57: Mantencion PM2 | D57: 3654 | E57: Sí | J57: Finalizada
A58: 46083 | B58: CD-88 | C58: Mantencion PM2 | D58: 1978 | E58: Sí | J58: Finalizada
A59: 46086 | B59: VD-107 | C59: Mantencion PM1 | D59: 75400 | E59: Sí | G59: Rosselot | I59: 425505 | J59: Finalizada
A60: 46071 | B60: VD-112 | C60: Mantencion PM1 | D60: 107335 | E60: Sí | J60: Finalizada
A61: 46087 | B61: VD-102 | C61: Mantencion PM1 | D61: 105962 | E61: Sí | F61: 105962 | J61: Finalizada
A62: 46093 | B62: VD-88 | C62: Mantencion PM1 | D62: 123772 | E62: Sí | G62: Palmucho | J62: Finalizada
A63: 46093 | B63: CD-109 | C63: Mantencion PM1 | D63: 189849 | E63: Sí | G63: Q-61 | J63: Finalizada
A64: 46092 | B64: MD-67 | C64: Mantencion PM2 | D64: 3745 | E64: Sí | G64: Q-61 | H64: COM. PUENTES DE MAULE LTDA. | I64: 177476 | J64: Finalizada
A65: 46097 | B65: EQP-7 | C65: Mantencion PM2 | D65: 15727 | E65: Sí | G65: San Nicolas | I65: 866929 | J65: Finalizada
A66: 46094 | B66: VD-109 | C66: Mantencion PM1 | D66: 107210 | E66: Sí | G66: Rosselot | I66: 405817 | J66: Finalizada
A67: 46094 | B67: MD-70 | C67: Mantencion PM2 | D67: 13040 | E67: Sí | F67: 17151 | G67: Pelluhue | H67: SOCIEDAD COMERCIAL SOCOFIL LIMITADA | I67: 89099.98 | J67: Finalizada
A68: 46098 | B68: MD-73 | C68: Mantencion PM2 | D68: 17296 | E68: Sí | F68: 17155 | G68: Curico | H68: COM. PUENTES DE MAULE LTDA. | I68: 289773.33 | J68: Finalizada
A69: 46094 | B69: MD-62 | C69: Mantencion PM2 | D69: 17152 | E69: Sí | F69: 17152 | G69: Curico | H69: H.V.O. COMERCIAL Y TRANSPORTES SPA | I69: 277000 | J69: Finalizada
A70: 46094 | B70: MD-57 | C70: Mantencion PM2 | D70: 13650 | E70: Sí | F70: 17153 | G70: Curico | H70: HD HYUNDAI INFRACORE CHILE S.A | I70: 125352 | J70: Finalizada
A71: 46057 | B71: MD-68 | C71: Mantencion PM2 | D71: 3472 | E71: Sí | H71: COM. PUENTES DE MAULE LTDA. | I71: 177476 | J71: Finalizada
A72: 46098 | B72: MD-102 | C72: Mantencion PM2 | D72: 5648 | E72: Sí | F72: 15994 | G72: Cobquecura | H72: COM. PUENTES DE MAULE LTDA. | I72: 177476 | J72: Finalizada
A73: 46093 | B73: MD-75 | C73: Mantencion PM2 | D73: 1713 | E73: Sí | G73: Quirihue | H73: COM. PUENTES DE MAULE LTDA. | I73: 133882.14 | J73: Finalizada
A74: 46086 | B74: VD-138 | C74: Mantencion PM1 | D74: 14872 | E74: Sí | G74: Kaufmann | H74: KAUFMANN S A VEHICULOS MOTORIZADOS | I74: 252383 | J74: Finalizada
A75: 46099 | B75: VD-140 | C75: Mantencion PM1 | D75: 22254 | E75: Sí | G75: Kaufmann | H75: KAUFMANN S A VEHICULOS MOTORIZADOS | I75: 310988 | J75: Finalizada
A76: 46099 | B76: VD-130 | C76: Mantencion PM1 | D76: 78670 | E76: Sí | G76: Kaufmann | H76: KAUFMANN S A VEHICULOS MOTORIZADOS | I76: 487719 | J76: Finalizada
A77: 46099 | B77: VD-97 | C77: Mantencion PM1 | D77: 110602 | E77: Sí | G77: Kaufmann | H77: KAUFMANN S A VEHICULOS MOTORIZADOS | I77: 276888 | J77: Finalizada
A78: 46099 | B78: VD-123 | C78: Mantencion PM1 | D78: 78795 | E78: Sí | F78: 15106 | G78: Taller | H78: SOCIEDAD COMERCIAL SOCOFIL LIMITADA | I78: 32014 | J78: Finalizada
A79: 46092 | B79: CD-107 | C79: Mantencion PM2 | D79: 10923 | E79: Sí | F79: 15107 | G79: Taller | J79: Finalizada
A80: 46093 | B80: MD-95 | C80: Mantencion PM2 | D80: 1713 | E80: Sí | F80: 15991 | G80: Quirihue | H80: COM. PUENTES DE MAULE LTDA. | I80: 133882.14 | J80: Finalizada
A81: 46086 | B81: MD-107 | C81: Mantencion PM2 | D81: 1462 | E81: Sí | G81: Kaufmann | H81: KAUFMANN S A VEHICULOS MOTORIZADOS | I81: 249078 | J81: Finalizada
A82: 46100 | B82: CD-90 | C82: Mantencion PM2 | D82: 9317 | E82: Sí | G82: Taller | J82: Finalizada
A83: 46099 | B83: CD-119 | C83: Mantencion PM1 | D83: 195600 | E83: Sí | H83: AUTOMOTORA ALAMEDA SPA | I83: 143221 | J83: Finalizada
A84: 46100 | B84: MD-87 | C84: Mantencion PM2 | D84: 6683 | E84: Sí | F84: 17156 | G84: Colbun | J84: Finalizada
A85: 46058 | B85: MD-110 | C85: Mantencion PM2 | D85: 8547 | E85: Sí | G85: Quirihue | J85: Finalizada
A86: 46072 | B86: VD-120 | C86: Mantencion PM1 | D86: 61470 | E86: Sí | G86: Quirihue | J86: Finalizada
A87: 45974 | B87: MD-28 | C87: Mantencion PM2 | D87: 21210 | E87: Sí | G87: Villa Seca | J87: Finalizada
A88: 46087 | B88: VD-121 | C88: Mantencion PM1 | D88: 71838 | E88: Sí | F88: 16205 | G88: San Carlos | J88: Finalizada
A89: 46085 | B89: MD-39 | C89: Mantencion PM2 | D89: 8980 | E89: Sí | F89: 16202 | J89: Finalizada
A90: 46031 | B90: VD-139 | C90: Mantencion PM1 | D90: 11406 | E90: Sí | G90: Kaufmann | H90: KAUFMANN S A VEHICULOS MOTORIZADOS | I90: 254792 | J90: Finalizada
A91: 46020 | B91: VD-129 | C91: Mantencion PM1 | D91: 65636 | E91: Sí | G91: Kaufmann | H91: KAUFMANN S A VEHICULOS MOTORIZADOS | I91: 573317 | J91: Finalizada
A92: 46027 | B92: VD-125 | C92: Mantencion PM1 | D92: 30210 | E92: Sí | J92: Finalizada
A93: 46029 | B93: VD-131 | C93: Mantencion PM1 | D93: 85271 | E93: Sí | G93: Kaufmann | H93: KAUFMANN S A VEHICULOS MOTORIZADOS | I93: 725040 | J93: Finalizada
A94: 46105 | B94: VD-128 | C94: Mantencion PM1 | D94: 86820 | E94: Sí | G94: Kaufmann | H94: KAUFMANN S A VEHICULOS MOTORIZADOS | I94: 698466 | J94: Finalizada
A95: 46101 | B95: VD-94 | C95: Mantencion PM1 | D95: 92994 | E95: Sí | J95: Finalizada
A96: 46077 | B96: VD-115 | C96: Mantencion PM1 | D96: 90248 | E96: Sí | J96: Finalizada
A97: 46105 | B97: CD-110 | C97: Mantencion PM1 | D97: 275548 | E97: Sí | G97: Cobquecura | J97: Finalizada
A98: 46099 | B98: VD-110 | C98: Mantencion PM1 | D98: 90000 | E98: Sí | J98: Finalizada
A99: 46099 | B99: CD-119 | C99: Mantencion PM1 | D99: 195600 | E99: Sí | G99: San Nicolas | H99: AUTOMOTORA ALAMEDA SPA | I99: 170432.99 | J99: Finalizada
B100: VD-90 | C100: Mantencion PM1 | D100: 118530 | E100: Sí | J100: Finalizada
A101: 46105 | B101: CD-132 | C101: Mantencion PM2 | D101: 7682 | E101: Sí | G101: Palmucho | J101: Finalizada
A102: 46107 | B102: EQP-11 | C102: Mantencion PM2 | D102: 2050 | E102: Sí | G102: Palmucho | J102: Finalizada
...

Sheet Repuestos
A1: Repuestos Bodega Demotron
A3: Codigo OEM | B3: Nombre | C3: Categoria | D3: Stock | E3: Precio | F3: Ubicacion
A4: KIT-MAX-T60 2.0 | B4: Kit Filtro Maxus 2.0 | C4: KIT COMPLETO FILTROS | D4: 2 | E4: 23799.9
A5: KIT-MAX-T60 2.8 | B5: Kit Filtro Maxus 2.8 | C5: KIT COMPLETO FILTROS | D5: 7 | E5: 24499
A6: KIT-PEU-PART | B6: Kit Filtros Peugeot Patner | C6: KIT COMPLETO FILTROS | D6: 1 | E6: 24600
A7: KIT-ZXAUTO-T | B7: Kit Filtro Zx Terralord | C7: KIT COMPLETO FILTROS | D7: 2 | E7: 35301.29
A8: KIT-HINO-300 | B8: Kit Filtro HINO 300 | C8: KIT COMPLETO FILTROS | D8: 3 | E8: 143221.43
A9: KIT-HINO-500 | B9: Kit Filtros CD-109 | C9: KIT COMPLETO FILTROS | D9: 0 | E9: 147685.2
A10: KIT-MAH-2.2 | B10: Kit Filtro Maxindra | C10: KIT COMPLETO FILTROS | D10: 1 | E10: 23899.89
A11: KIT-SSanyong | B11: Kit Filtros Ssangyong | C11: KIT COMPLETO FILTROS | D11: 2 | E11: 30899.98
A12: KIT-MAN-TT | B12: Kit Filtros Man Tolva | C12: KIT COMPLETO FILTROS | D12: 2 | E12: 190541
A13: KIT-DOO-225la | B13: Kit Filtros Doosan DX225la | C13: KIT COMPLETO FILTROS | D13: 4 | E13: 200572
A14: KIT-DOO-300la | B14: Kit Filtros Doosan DX300la | C14: KIT COMPLETO FILTROS | D14: 1 | E14: 312122
A15: KIT-STERL-7500 | B15: Kit Filtros Sterling 7500 | C15: KIT COMPLETO FILTROS | D15: 1 | E15: 229300
... A20: KIT-INTER-4300 | B20: KIt Filtros International 4300 | C20: KIT COMPLETO FILTROS | D20: 1 | E20: 136602
A21: KIT-FREI-112 | B21: KIt Filtros Freightliner M2 112 | C21: KIT COMPLETO FILTROS | D21: 1
A22: KIT-FREI-106 | B22: KIt Filtros Freightliner M2 106 | C22: KIT COMPLETO FILTROS | D22: 1
A23: KIT-MACK-GU | B23: Kit Filtros Mack GU 813 | C23: KIT COMPLETO FILTROS | D23: 1
A24: KIT-Bomag-D40 | B24: Kit Filtros Bomag BW211 D40 | C24: KIT COMPLETO FILTROS | D24: 1
A25: KIT-554K-JD | B25: Kit Filtros John Deree 554K | C25: KIT COMPLETO FILTROS | D25: 1
A26: KIT-MB-1634 | B26: Kit Filtros Mercedes Benz LS1634 | C26: KIT COMPLETO FILTROS | D26: 1
A27: KIT-CASE-580M | B27: Kit Filtros CASE 580M | C27: KIT COMPLETO FILTROS | D27: 2
A28: KIT-KEN-T800 | B28: Kit Filtros Kenworth T801 | C28: KIT COMPLETO FILTROS | D28: 1
A29: KIT-HAMM | B29: Kit Filtros Hamm GRW16 | C29: KIT COMPLETO FILTROS | D29: 3
A30: KIT-VOLK-26 | B30: Kit Filtros Volkswagen 26220 | C30: KIT COMPLETO FILTROS | D30: 1
A31: KIT-SANY-BHL | B31: Kit Filtros Sany BHL75A | C31: KIT COMPLETO FILTROS | D31: 1 | E31: 227618
A32: KIT-CAT-416 | B32: Kit Filtros CAT 416 E | C32: KIT COMPLETO FILTROS | D32: 1 | E32: 213063
A33: LF3345 | B33: LF3345 | C33: FILTRO DE ACEITE | D33: 1
A34: PA3761 | B34: PA3761 | C34: FILTRO DE AIRE MOTOR | D34: 1
A35: LF3827 | B35: LF3827 | C35: FILTRO DE ACEITE | D35: 1
A36: FF5380 | B36: FF5380 | C36: FILTRO DE COMBUSTIBLE | D36: 1
A37: FS19914 | B37: FS19914 | C37: FILTRO DECANTADOR | D37: 1
A38: FS1212 | B38: FS1212 | C38: FILTRO DECANTADOR | D38: 1
A39: PSC75 | B39: PSC75 | C39: FILTRO DE COMBUSTIBLE | D39: 1
A40: KIT-724K-JD | B40: Kit Filtros John Deree 724K | C40: KIT COMPLETO FILTROS | D40: 1 | E40: 800603
A41: KIT-CAT-390 | B41: Kit Filtros CAT 390 | C41: KIT COMPLETO FILTROS | D41: 1 | E41: 212500
A42: KIT-REN-K480 | B42: Kit Filtros Renault K480 | C42: KIT COMPLETO FILTROS | D42: 2 | E42: 380600
A43: KIT-MAXUS-C35 | B43: Kit Filtros Maxus C35 | C43: KIT COMPLETO FILTROS | D43: 1
A44: KIT-Bomag-212 | B44: Kit Filtros Bomag BW212 D40 | C44: KIT COMPLETO FILTROS | D44: 1
A45: KIT-HYN-HL7709S | B45: Kit Filtros Hyundai HL7709S | C45: KIT COMPLETO FILTROS | D45: 2

Sheet Recetas_Kits
A1: KIT de Repuestos
A3: Modelo Equipo | B3: SKU Repuesto | C3: Cantidad
A4: 12M | C4: 1
A5: 160H | C5: 1
A6: 17180M | C6: 1
A7: 210 LC | C7: 1
A8: 210 Lc | C8: 1
A9: 26220 | B9: KIT-VOLK-26 | C9: 1
A10: 330D | C10: 1
A11: 350GLC | C11: 1
A12: 3CX 4X4 | C12: 1
A13: 416 E | B13: KIT-CAT-416 | C13: 1
A14: 4300 | B14: KIT-INTER-4300 | C14: 1
A15: 467 Zx | C15: 1
A16: 4x2 6MT | C16: 1
A17: 512 | C17: 1
A18: 554K | B18: KIT-554K-JD | C18: 1
A19: 580M | B19: KIT-CASE-580M | C19: 1
A20: 624K | C20: 1
A21: 670G | C21: 1
A22: 674 | C22: 1
A23: 724K | C23: 1
A24: 7400 | C24: 1
A25: 7600 | C25: 1
A26: 770G | C26: 1
A27: 772 D | B27: KIT-772D-JD | C27: 1
A28: 772G | C28: 1
A29: 915 C 37 | C29: 1
A30: 9150 EOD | C30: 1
A31: 9150E | C31: 1
A32: 966H | B32: KIT-CAT-966H | C32: 1
A33: Atego 1015 | C33: 1
A34: Atego 1315 48 | C34: 1
A35: Axor 1936 | C35: 1
A36: B90B 4X4 | C36: 1
A37: BERLINGO B9 C HDI 1.6 | C37: 1
A38: BHL75A | B38: KIT-SANY-BHL | C38: 1
A39: BW211 D40 | B39: KIT-Bomag-D40 | C39: 1
A40: BW211 D5 | C40: 1
A41: Berlingo C Electric | C41: 1
A42: Bw212 D40 | B42: KIT-Bomag-212 | C42: 1
A43: C35 2.0 | B43: KIT-MAXUS-C35 | C43: 1
A44: CC 422 | C44: 1
A45: CP 271 | C45: 1
A46: DM 690S | C46: 1
A47: DOKKER III 1.5 | C47: 1
A48: Dx225lca | B48: KIT-DOO-225la | C48: 1
A49: Dx300lca | B49: KIT-DOO-300la | C49: 1
A50: Dx340lca | C50: 1
A51: EC330BLC | C51: 1
A52: EXPERT HDI 2.0 | C52: 1
A53: FLD 112 | C53: 1
A54: G930 | C54: 1
A55: G940 | C55: 1
A56: GD675 5 | C56: 1
A57: GH8JMTA | B57: KIT-HINO-500 | C57: 1
A58: GRW15 | C58: 1
A59: GT-3600 | C59: 1
A60: GU 813 | B60: KIT-MACK-GU | C60: 1
A61: GeCursor 300ED | C61: 1
A62: H940C | C62: 1
A63: HL7709S | B63: KIT-HYN-HL7709S | C63: 1
A64: HS 11000 M | C64: 1
A65: HUNTER 1.9 MT 4X4 COMFORT | C65: 1
A66: HZU | B66: KIT-HINO-300 | C66: 1
A67: K480 | B67: KIT-REN-K480 | C67: 1
A68: KANGOO 1.5 | C68: 1
A69: L150G | C69: 1
A70: L7500 | B70: KIT-STERL-7500 | C70: 1
A71: LS 1634 45 | B71: KIT-MB-1634 | C71: 1
A72: M2 106 | B72: KIT-FREI-106 | C72: 1
A73: M2 112 | B73: KIT-FREI-112 | C73: 1
A74: Mc 110R | C74: 1
A75: Mc 110Z | C75: 1
A76: Musso Grand 4x2 | B76: KIT-SSanyong | C76: 1
A77: P400A | C77: 1
A78: PC300LC | C78: 1
A79: PC450 7E0 | C79: 1
A80: Partner 1.5D L1 | B80: KIT-PEU-PART | C80: 1
A81: Pik up CRDE 4X2 2.2 | B81: KIT-MAH-2.2 | C81: 1
A82: Premium Lander | C82: 1
A83: QJ341 | C83: 1
A84: QS331 | C84: 1
A85: S210W v | C85: 1
A86: SAVEIRO CABINA SIMPLE 1.6 MT POWER PLUS | C86: 1
A87: SPRINTER 313 CDI | C87: 1
A88: SPRINTER 415 CDI | C88: 1
A89: SPRINTER 415 CDI 2.1 | C89: 1
A90: SW978K1 | C90: 1
A91: SY215CLC | C91: 1
A92: T60 2.0 | B92: KIT-MAX-T60 2.0 | C92: 1
A93: T60 4x4 | B93: KIT-MAX-T60 2.0 | C93: 1
A94: T60 2.8 | B94: KIT-MAX-T60 2.8 | C94: 1
A95: T800 | B95: KIT-KEN-T800 | C95: 1
A96: TERRALORD DCAB 2.5 | B96: KIT-ZXAUTO-T | C96: 1
A97: TGS 33400 | B97: KIT-MAN-TT | C97: 1
A98: TGS 33480 | B98: KIT-MAN-TT | C98: 1
A99: TGS 40400 BB | B99: KIT-MAN-TT | C99: 1
A100: TGS 50480 | B100: KIT-MAN-TT | C100: 1
A101: Titan 323 | C101: 1
...

Sheet Compras PM
A1: COMPRAS PM (EDITABLE)
A3: Fecha | B3: OC | C3: Codigo | D3: Descripcion | E3: Proveedor | F3: Costo PM CLP | G3: Regla | H3: Estado OC
A4: 46065.519 | B4: DEMO-02-7633 | C4: VD-115 | D4: SC-2-6076 KIT FILTROS PEUGEOT | E4: SOCIEDAD COMERCIAL SOCOFIL LIMITADA | F4: 32201.4 | G4: Directo Equipo | H4: OC Aprobada
A5: 46065.519 | B5: DEMO-02-7633 | C5: VD-116 | D5: SC-2-6076 KIT FILTROS PEUGEOT | E5: SOCIEDAD COMERCIAL SOCOFIL LIMITADA | F5: 32201.4 | G5: Directo Equipo | H5: OC Aprobada
A6: 46065.519 | B6: DEMO-02-7633 | C6: VD-117 | D6: SC-2-6076 KIT FILTROS PEUGEOT | E6: SOCIEDAD COMERCIAL SOCOFIL LIMITADA | F6: 32201.4 | G6: Directo Equipo | H6: OC Aprobada
A7: 46065.519 | B7: DEMO-02-7633 | C7: VD-118 | D7: SC-2-6076 KIT FILTROS PEUGEOT | E7: SOCIEDAD COMERCIAL SOCOFIL LIMITADA | F7: 32201.4 | G7: Directo Equipo | H7: OC Aprobada
A8: 46065.519 | B8: DEMO-02-7633 | C8: VD-119 | D8: SC-2-6076 KIT FILTROS PEUGEOT | E8: SOCIEDAD COMERCIAL SOCOFIL LIMITADA | F8: 32201.4 | G8: Directo Equipo | H8: OC Aprobada
A9: 46065.519 | B9: DEMO-02-7633 | C9: VD-120 | D9: SC-2-6076 KIT FILTROS PEUGEOT | E9: SOCIEDAD COMERCIAL SOCOFIL LIMITADA | F9: 32201.4 | G9: Directo Equipo | H9: OC Aprobada
A10: 46065.519 | B10: DEMO-02-7633 | C10: VD-121 | D10: SC-2-6076 KIT FILTROS PEUGEOT | E10: SOCIEDAD COMERCIAL SOCOFIL LIMITADA | F10: 32201.4 | G10: Directo Equipo | H10: OC Aprobada
A11: 46065.519 | B11: DEMO-02-7633 | C11: VD-122 | D11: SC-2-6076 KIT FILTROS PEUGEOT | E11: SOCIEDAD COMERCIAL SOCOFIL LIMITADA | F11: 32201.4 | G11: Directo Equipo | H11: OC Aprobada
A12: 46065.519 | B12: DEMO-02-7633 | C12: VD-123 | D12: SC-2-6076 KIT FILTROS PEUGEOT | E12: SOCIEDAD COMERCIAL SOCOFIL LIMITADA | F12: 32201.4 | G12: Directo Equipo | H12: OC Aprobada
A13: 46065.519 | B13: DEMO-02-7633 | C13: VD-124 | D13: SC-2-6076 KIT FILTROS PEUGEOT | E13: SOCIEDAD COMERCIAL SOCOFIL LIMITADA | F13: 32201.4 | G13: Directo Equipo | H13: OC Aprobada
A14: 46069.447 | B14: DEMO-02-7643 | C14: CD-87 | D14: SC-02-6085 KIT DE FILTROS MANTENCIO | E14: SOCIEDAD COMERCIAL SOCOFIL LIMITADA | F14: 5764.6988 | G14: Prorrateo MAN | H14: OC Aprobada
A15: 46069.447 | B15: DEMO-02-7643 | C15: CD-88 | D15: SC-02-6085 KIT DE FILTROS MANTENCIO | E15: SOCIEDAD COMERCIAL SOCOFIL LIMITADA | F15: 5764.6988 | G15: Prorrateo MAN | H15: OC Aprobada
... A30: 46069.447 | B30: DEMO-02-7643 | C30: CD-89 | D30: SC-02-6085 KIT DE FILTROS MANTENCIO | E30: SOCIEDAD COMERCIAL SOCOFIL LIMITADA | F30: 5764.6988 | G30: Prorrateo MAN | H30: OC Aprobada
A31: 46069.64 | B31: DEMO-02-7652 | C31: =_xlfn.TEXTAFTER(TRIM(tblComprasPM[[#This Row],[Descripcion]]), " ", -1) -> CD-69 | D31: SC-02 KIT DE FILTROS SCANIA CD-69 | E31: COM. PUENTES DE MAULE LTDA. | F31: 162393.35 | G31: Directo Equipo | H31: OC Aprobada
A32: 46070.75 | B32: DEMO-02-7664 | C32: =_xlfn.TEXTAFTER(TRIM(tblComprasPM[[#This Row],[Descripcion]]), " ", -1) -> CD-45 | D32: SC-02-FILTROS CD-45 | E32: COM. PUENTES DE MAULE LTDA. | F32: 108651.76 | G32: Directo Equipo | H32: OC Aprobada
A33: 46071.353 | B33: DEMO-02-7663 | C33: =_xlfn.TEXTAFTER(TRIM(tblComprasPM[[#This Row],[Descripcion]]), " ", -1) -> CD-45 | D33: SC-02-FILTROS CD-45 | E33: SALINAS Y FABRES | F33: 59673.74 | G33: Directo Equipo | H33: OC Enviada a Proveedor
A34: 46071.627 | B34: DEMO-02-7668 | C34: =_xlfn.TEXTAFTER(TRIM(tblComprasPM[[#This Row],[Descripcion]]), " ", -1) -> CD-119 | D34: SC-02-6089 KIT DE FILTROS CD-119 | E34: AUTOMOTORA ALAMEDA SPA | F34: 201663.35 | G34: Directo Equipo | H34: OC Aprobada
A35: 46072.422 | B35: DEMO-02-7672 | C35: =_xlfn.TEXTAFTER(TRIM(tblComprasPM[[#This Row],[Descripcion]]), " ", -1) -> CD-88 | D35: SC-02-6090 FILTROS CD-88 | E35: AUTOMOTORA ALAMEDA SPA | F35: 402316.39 | G35: Directo Equipo | H35: OC Aprobada
A36: 46072.697 | B36: DEMO-02-7676 | C36: =_xlfn.TEXTAFTER(TRIM(tblComprasPM[[#This Row],[Descripcion]]), " ", -1) -> MD-84 | D36: SC-02-6093 KIT FILTROS MD-84 | E36: SALINAS Y FABRES | F36: 456581.58 | G36: Directo Equipo | H36: OC Enviada a Proveedor
A37: 46073.411 | B37: DEMO-02-7682 | C37: CD-102 | D37: SC-02-FILTROS CAMIONES MAN (STOCK T | E37: AUTOMOTORA ALAMEDA SPA | F37: 13095.53 | G37: Prorrateo MAN | H37: OC Aprobada
A38: 46073.411 | B38: DEMO-02-7682 | C38: CD-104 | D38: SC-02-FILTROS CAMIONES MAN (STOCK T | E38: AUTOMOTORA ALAMEDA SPA | F38: 13095.53 | G38: Prorrateo MAN | H38: OC Aprobada
A39: 46073.411 | B39: DEMO-02-7682 | C39: CD-105 | D39: SC-02-FILTROS CAMIONES MAN (STOCK T | E39: AUTOMOTORA ALAMEDA SPA | F39: 13095.53 | G39: Prorrateo MAN | H39: OC Aprobada
A40: 46073.411 | B40: DEMO-02-7682 | C40: CD-106 | D40: SC-02-FILTROS CAMIONES MAN (STOCK T | E40: AUTOMOTORA ALAMEDA SPA | F40: 13095.53 | G40: Prorrateo MAN | H40: OC Aprobada
A41: 46073.411 | B41: DEMO-02-7682 | C41: CD-107 | D41: SC-02-FILTROS CAMIONES MAN (STOCK T | E41: AUTOMOTORA ALAMEDA SPA | F41: 13095.53 | G41: Prorrateo MAN | H41: OC Aprobada
A42: 46073.411 | B42: DEMO-02-7682 | C42: CD-120 | D42: SC-02-FILTROS CAMIONES MAN (STOCK T | E42: AUTOMOTORA ALAMEDA SPA | F42: 13095.53 | G42: Prorrateo MAN | H42: OC Aprobada
A43: 46073.411 | B43: DEMO-02-7682 | C43: CD-121 | D43: SC-02-FILTROS CAMIONES MAN (STOCK T | E43: AUTOMOTORA ALAMEDA SPA | F43: 13095.53 | G43: Prorrateo MAN | H43: OC Aprobada
A44: 46073.411 | B44: DEMO-02-7682 | C44: CD-122 | D44: SC-02-FILTROS CAMIONES MAN (STOCK T | E44: AUTOMOTORA ALAMEDA SPA | F44: 13095.53 | G44: Prorrateo MAN | H44: OC Aprobada
A45: 46073.411 | B45: DEMO-02-7682 | C45: CD-123 | D45: SC-02-FILTROS CAMIONES MAN (STOCK T | E45: AUTOMOTORA ALAMEDA SPA | F45: 13095.53 | G45: Prorrateo MAN | H45: OC Aprobada
A46: 46073.411 | B46: DEMO-02-7682 | C46: CD-87 | D46: SC-02-FILTROS CAMIONES MAN (STOCK T | E46: AUTOMOTORA ALAMEDA SPA | F46: 13095.53 | G46: Prorrateo MAN | H46: OC Aprobada
A47: 46073.411 | B47: DEMO-02-7682 | C47: CD-88 | D47: SC-02-FILTROS CAMIONES MAN (STOCK T | E47: AUTOMOTORA ALAMEDA SPA | F47: 13095.53 | G47: Prorrateo MAN | H47: OC Aprobada
A48: 46073.411 | B48: DEMO-02-7682 | C48: CD-89 | D48: SC-02-FILTROS CAMIONES MAN (STOCK T | E48: AUTOMOTORA ALAMEDA SPA | F48: 13095.53 | G48: Prorrateo MAN | H48: OC Aprobada
... A53: 46073.411 | B53: DEMO-02-7682 | C53: CD-90 | D53: SC-02-FILTROS CAMIONES MAN (STOCK T | E53: AUTOMOTORA ALAMEDA SPA | F53: 13095.53 | G53: Prorrateo MAN | H53: OC Aprobada
A54: 46073.524 | B54: DEMO-02-7686 | C54: =_xlfn.TEXTAFTER(TRIM(tblComprasPM[[#This Row],[Descripcion]]), " ", -1) -> VD-29 | D54: SC-02-6095 KIR FILTROS VD-29 | E54: KAUFMANN S A VEHICULOS MOTORIZADOS | F54: 61356.4 | G54: Directo Equipo | H54: OC Aprobada
A55: 46073.541 | B55: DEMO-02-7688 | C55: CD-106 | D55: FILTROS BOTELLA MAN | E55: FORTI SPA | F55: 7700 | G55: Prorrateo MAN | H55: OC Aprobada
A56: 46073.541 | B56: DEMO-02-7688 | C56: CD-107 | D56: FILTROS BOTELLA MAN | E56: FORTI SPA | F56: 7700 | G56: Prorrateo MAN | H56: OC Aprobada
A57: 46073.541 | B57: DEMO-02-7688 | C57: CD-120 | D57: FILTROS BOTELLA MAN | E57: FORTI SPA | F57: 7700 | G57: Prorrateo MAN | H57: OC Aprobada
A58: 46073.541 | B58: DEMO-02-7688 | C58: CD-121 | D58: FILTROS BOTELLA MAN | E58: FORTI SPA | F58: 7700 | G58: Prorrateo MAN | H58: OC Aprobada
A59: 46073.541 | B59: DEMO-02-7688 | C59: CD-122 | D59: FILTROS BOTELLA MAN | E59: FORTI SPA | F59: 7700 | G59: Prorrateo MAN | H59: OC Aprobada
A60: 46073.541 | B60: DEMO-02-7688 | C60: CD-123 | D60: FILTROS BOTELLA MAN | E60: FORTI SPA | F60: 7700 | G60: Prorrateo MAN | H60: OC Aprobada
A61: 46073.541 | B61: DEMO-02-7688 | C61: CD-87 | D61: FILTROS BOTELLA MAN | E61: FORTI SPA | F61: 7700 | G61: Prorrateo MAN | H61: OC Aprobada
A62: 46073.541 | B62: DEMO-02-7688 | C62: CD-88 | D62: FILTROS BOTELLA MAN | E62: FORTI SPA | F62: 7700 | G62: Prorrateo MAN | H62: OC Aprobada
A63: 46073.541 | B63: DEMO-02-7688 | C63: CD-89 | D63: FILTROS BOTELLA MAN | E63: FORTI SPA | F63: 7700 | G63: Prorrateo MAN | H63: OC Aprobada
A64: 46073.541 | B64: DEMO-02-7688 | C64: CD-90 | D64: FILTROS BOTELLA MAN | E64: FORTI SPA | F64: 7700 | G64: Prorrateo MAN | H64: OC Aprobada
A65: 46073.541 | B65: DEMO-02-7688 | C65: CD-94 | D65: FILTROS BOTELLA MAN | E65: FORTI SPA | F65: 7700 | G65: Prorrateo MAN | H65: OC Aprobada
A66: 46073.541 | B66: DEMO-02-7688 | C66: CD-102 | D66: FILTROS BOTELLA MAN | E66: FORTI SPA | F66: 7700 | G66: Prorrateo MAN | H66: OC Aprobada
... A71: 46073.541 | B71: DEMO-02-7688 | C71: CD-120 | D71: FILTROS BOTELLA MAN | E71: FORTI SPA | F71: 7700 | G71: Prorrateo MAN | H71: OC Aprobada
A72: 46073.686 | B72: DEMO-02-7690 | C72: =_xlfn.TEXTAFTER(TRIM(tblComprasPM[[#This Row],[Descripcion]]), " ", -1) -> VD-125 | D72: MANTENCION VD-125 | E72: KAUFMANN S A VEHICULOS MOTORIZADOS | F72: 426593.58 | G72: Directo Equipo | H72: OC Aprobada
A73: 46076.364 | B73: DEMO-02-7692 | C73: =_xlfn.TEXTAFTER(TRIM(tblComprasPM[[#This Row],[Descripcion]]), " ", -1) -> CD-110 | D73: SC-02-6096 KIT FILTROS CD-110 | E73: SOCIEDAD COMERCIAL SOCOFIL LIMITADA | F73: 21301 | G73: Directo Equipo | H73: OC Aprobada
A74: 46076.407 | B74: DEMO-02-7696 | C74: =_xlfn.TEXTAFTER(TRIM(tblComprasPM[[#This Row],[Descripcion]]), " ", -1) -> CD-98 | D74: SC-02-6097 KIT FILTROS CD-98 | E74: AUTOMOTORA ALAMEDA SPA | F74: 271270.02 | G74: Directo Equipo | H74: OC Aprobada
A75: 46076.468 | B75: DEMO-02-7699 | C75: =_xlfn.TEXTAFTER(TRIM(tblComprasPM[[#This Row],[Descripcion]]), " ", -1) -> CD-69 | D75: SC-02 FILTRO AIRE PRIM Y SEC. CD-69 | E75: SOCIEDAD COMERCIAL SOCOFIL LIMITADA | F75: 76299.825 | G75: Directo Equipo | H75: OC Aprobada
A76: 46076.484 | B76: DEMO-02-7706 | C76: =_xlfn.TEXTAFTER(TRIM(tblComprasPM[[#This Row],[Descripcion]]), " ", -1) -> CD-86 | D76: SC-02-KIT FILTROS CD-86 | E76: SOCIEDAD COMERCIAL SOCOFIL LIMITADA | F76: 288199.96 | G76: Directo Equipo | H76: OC Aprobada
A77: 46076.553 | B77: DEMO-02-7707 | C77: =_xlfn.TEXTAFTER(TRIM(tblComprasPM[[#This Row],[Descripcion]]), " ", -1) -> O | D77: SC-02-6119 REG. MANTENCION VD-108 O | E77: ROSSELOT Y FIGUEROA LIMITADA | F77: 387603.23 | G77: Directo Equipo | H77: OC Aprobada
A78: 46078.358 | B78: DEMO-02-7732 | C78: =_xlfn.TEXTAFTER(TRIM(tblComprasPM[[#This Row],[Descripcion]]), " ", -1) -> CD-116 | D78: SC-02-6105 KIT FILTROS CD-116 | E78: SOCIEDAD COMERCIAL SOCOFIL LIMITADA | F78: 94000.004 | G78: Directo Equipo | H78: OC Aprobada
A79: 46078.425 | B79: DEMO-02-7736 | C79: =_xlfn.TEXTAFTER(TRIM(tblComprasPM[[#This Row],[Descripcion]]), " ", -1) -> MD-75 | D79: SC-02-6101 FILTROS MD-75 | E79: COM. PUENTES DE MAULE LTDA. | F79: 357653.31 | G79: Directo Equipo | H79: OC Aprobada
A80: 46078.648 | B80: DEMO-02-7737 | C80: =_xlfn.TEXTAFTER(TRIM(tblComprasPM[[#This Row],[Descripcion]]), " ", -1) -> MD-96 | D80: SC-02-6103 KIT DE FILTROS MD-96 | E80: KAUFMANN S A VEHICULOS MOTORIZADOS | F80: 258526.31 | G80: Directo Equipo | H80: OC Aprobada
A81: 46078.661 | B81: DEMO-02-7738 | C81: =_xlfn.TEXTAFTER(TRIM(tblComprasPM[[#This Row],[Descripcion]]), " ", -1) -> CD-71 | D81: SC-02-6104 FILTROS MANTENCION CD-71 | E81: COM. PUENTES DE MAULE LTDA. | F81: 393830.5 | G81: Directo Equipo | H81: OC Aprobada
A82: 46079.431 | B82: DEMO-02-7745 | C82: =_xlfn.TEXTAFTER(TRIM(tblComprasPM[[#This Row],[Descripcion]]), " ", -1) -> CD-93 | D82: SC-02-KIT FILTROS CD-93 | E82: AUTOMOTORA ALAMEDA SPA | F82: 170432.99 | G82: Directo Equipo | H82: OC Aprobada
A83: 46079.432 | B83: DEMO-02-7746 | C83: =_xlfn.TEXTAFTER(TRIM(tblComprasPM[[#This Row],[Descripcion]]), " ", -1) -> CD-51 | D83: SC-02- KIT DE FILTROS CD-51 | E83: AUTOMOTORA ALAMEDA SPA | F83: 131994.8 | G83: Directo Equipo | H83: OC Aprobada
... A89: 46083.5 | B89: DEMO-02-7786 | C89: =_xlfn.TEXTAFTER(TRIM(tblComprasPM[[#This Row],[Descripcion]]), " ", -1) -> MD-39 | D89: SC-02-6111 FILTROS MD-39 | E89: COM. PUENTES DE MAULE LTDA. | F89: 237325.27 | G89: Directo Equipo | H89: OC Aprobada
A90: 46083.515 | B90: DEMO-02-7788 | C90: CD-102 | D90: SC-02-6112 FILTROS CD-123/122/91 | E90: UNIÓN TÉCNICA AUTOMOTRIZ LTDA. | F90: 264548.75 | G90: Directo Equipo | H90: OC Aprobada
A91: 46083.515 | B91: DEMO-02-7788 | C91: CD-104 | D91: SC-02-6112 FILTROS CD-123/122/91 | E91: UNIÓN TÉCNICA AUTOMOTRIZ LTDA. | F91: 264548.75 | G91: Directo Equipo | H91: OC Aprobada
A92: 46083.515 | B92: DEMO-02-7788 | C92: CD-87 | D92: SC-02-6112 FILTROS CD-123/122/91 | E92: UNIÓN TÉCNICA AUTOMOTRIZ LTDA. | F92: 264548.75 | G92: Directo Equipo | H92: OC Aprobada
A93: 46083.515 | B93: DEMO-02-7788 | C93: CD-88 | D93: SC-02-6112 FILTROS CD-123/122/91 | E93: UNIÓN TÉCNICA AUTOMOTRIZ LTDA. | F93: 264548.75 | G93: Directo Equipo | H93: OC Aprobada
A94: 46083.515 | B94: DEMO-02-7788 | C94: CD-89 | D94: SC-02-6112 FILTROS CD-123/122/91 | E94: UNIÓN TÉCNICA AUTOMOTRIZ LTDA. | F94: 264548.75 | G94: Directo Equipo | H94: OC Aprobada
A95: 46083.515 | B95: DEMO-02-7788 | C95: CD-90 | D95: SC-02-6112 FILTROS CD-123/122/91 | E95: UNIÓN TÉCNICA AUTOMOTRIZ LTDA. | F95: 264548.75 | G95: Directo Equipo | H95: OC Aprobada
A96: 46083.515 | B96: DEMO-02-7788 | C96: CD-94 | D96: SC-02-6112 FILTROS CD-123/122/91 | E96: UNIÓN TÉCNICA AUTOMOTRIZ LTDA. | F96: 264548.75 | G96: Directo Equipo | H96: OC Aprobada
A97: 46083.515 | B97: DEMO-02-7788 | C97: CD-97 | D97: SC-02-6112 FILTROS CD-123/122/91 | E97: UNIÓN TÉCNICA AUTOMOTRIZ LTDA. | F97: 264548.75 | G97: Directo Equipo | H97: OC Aprobada
A98: 46083.551 | B98: DEMO-02-7789 | C98: =_xlfn.TEXTAFTER(TRIM(tblComprasPM[[#This Row],[Descripcion]]), " ", -1) -> CD-122/123/ | D98: SC-02-FILTRO HIDRAULICO CD-122/123/ | E98: SOCIEDAD COMERCIAL SOCOFIL LIMITADA | F98: 26999.91 | G98: Directo Equipo | H98: OC Aprobada
A99: 46083.616 | B99: DEMO-02-7790 | C99: =_xlfn.TEXTAFTER(TRIM(tblComprasPM[[#This Row],[Descripcion]]), " ", -1) -> CD-94 | D99: SC-02-6118 FILTROS CD-94 | E99: UNIÓN TÉCNICA AUTOMOTRIZ LTDA. | F99: 458830.68 | G99: Directo Equipo | H99: OC Aprobada
A100: 46083.67 | B100: DEMO-02-7792 | C100: =_xlfn.TEXTAFTER(TRIM(tblComprasPM[[#This Row],[Descripcion]]), " ", -1) -> VD-89 | D100: SC-02 MANTENCION VD-89 | E100: KAUFMANN S A VEHICULOS MOTORIZADOS | F100: 312029.9 | G100: Directo Equipo | H100: OC Aprobada
A101: 46084.554 | B101: DEMO-02-7801 | C101: =_xlfn.TEXTAFTER(TRIM(tblComprasPM[[#This Row],[Descripcion]]), " ", -1) -> MD-89 | D101: SC-02-6113 FILTROS MD-89 | E101: COM. PUENTES DE MAULE LTDA. | F101: 237325.27 | G101: Directo Equipo | H101: OC Aprobada
A102: 46084.661 | B102: DEMO-02-7802 | C102: =_xlfn.TEXTAFTER(TRIM(tblComprasPM[[#This Row],[Descripcion]]), " ", -1) -> MD-28 | D102: SC-02-6150 FILTROS MD-61 MD-28 | E102: COM. PUENTES DE MAULE LTDA. | F102: 115923.85 | G102: Directo Equipo | H102: OC Aprobada
A103: 46084.661 | B103: DEMO-02-7802 | C103: =_xlfn.TEXTAFTER(TRIM(tblComprasPM[[#This Row],[Descripcion]]), " ", -1) -> MD-28 | D103: SC-02-6150 FILTROS MD-61 MD-28 | E103: COM. PUENTES DE MAULE LTDA. | F103: 115923.85 | G103: Directo Equipo | H103: OC Aprobada
A104: 46084.686 | B104: DEMO-02-7803 | C104: =_xlfn.TEXTAFTER(TRIM(tblComprasPM[[#This Row],[Descripcion]]), " ", -1) -> CD-14 | D104: SC-02-6114 FILTROS MANTENCION CD-14 | E104: COM. PUENTES DE MAULE LTDA. | F104: 63816.13 | G104: Directo Equipo | H104: OC Aprobada
A105: 46084.693 | B105: DEMO-02-7804 | C105: =_xlfn.TEXTAFTER(TRIM(tblComprasPM[[#This Row],[Descripcion]]), " ", -1) -> MD-49 | D105: SC-02-6116 FILTROS MANTENCION MD-49 | E105: COM. PUENTES DE MAULE LTDA. | F105: 204885.87 | G105: Directo Equipo | H105: OC Aprobada
A106: 46085.465 | B106: DEMO-02-7809 | C106: =_xlfn.TEXTAFTER(TRIM(tblComprasPM[[#This Row],[Descripcion]]), " ", -1) -> MD-107 | D106: SC-02-6137 FILTROS MD-107 | E106: KAUFMANN S A VEHICULOS MOTORIZADOS | F106: 211515.36 | G106: Directo Equipo | H106: OC Aprobada
A107: 46085.498 | B107: DEMO-02-7811 | C107: =_xlfn.TEXTAFTER(TRIM(tblComprasPM[[#This Row],[Descripcion]]), " ", -1) -> MD-87 | D107: SC-02-6151 KIT FILTROS MD-87 | E107: COM. PUENTES DE MAULE LTDA. | F107: 450580.41 | G107: Directo Equipo | H107: OC Aprobada
A108: 46085.547 | B108: DEMO-02-7817 | C108: =_xlfn.TEXTAFTER(TRIM(tblComprasPM[[#This Row],[Descripcion]]), " ", -1) -> MD-26 | D108: SC-02-6121 FILTROS MD-26 | E108: COM. PUENTES DE MAULE LTDA. | F108: 496871.41 | G108: Directo Equipo | H108: OC Aprobada
A109: 46085.56 | B109: DEMO-02-7818 | C109: =_xlfn.TEXTAFTER(TRIM(tblComprasPM[[#This Row],[Descripcion]]), " ", -1) -> MD-73 | D109: SC-02-6117 FILTROS MD-73 | E109: COM. PUENTES DE MAULE LTDA. | F109: 289773.33 | G109: Directo Equipo | H109: OC Aprobada
... A111: 46085.665 | B111: DEMO-02-7820 | C111: =_xlfn.TEXTAFTER(TRIM(tblComprasPM[[#This Row],[Descripcion]]), " ", -1) -> MD-100 | D111: SC-02-6127 FILTROS MD-100 | E111: KAUFMANN S A VEHICULOS MOTORIZADOS | F111: 360956.75 | G111: Directo Equipo | H111: OC Aprobada
A112: 46086.416 | B112: DEMO-02-7825 | C112: VD-77 | D112: SC-02-6122 FILTROS ZXAUTOS | E112: SOCIEDAD COMERCIAL SOCOFIL LIMITADA | F112: 18800.036 | G112: Directo Equipo | H112: OC Aprobada
A113: 46086.422 | B113: DEMO-02-7826 | C113: MD-25 | D113: SC-02 FILTRO MD-25 MD-107 | E113: SOCIEDAD COMERCIAL SOCOFIL LIMITADA | F113: 26999.91 | G113: Directo Equipo | H113: OC Aprobada
A114: 46086.422 | B114: DEMO-02-7826 | C114: =_xlfn.TEXTAFTER(TRIM(tblComprasPM[[#This Row],[Descripcion]]), " ", -1) -> MD-107 | D114: SC-02 FILTRO MD-25 MD-107 | E114: SOCIEDAD COMERCIAL SOCOFIL LIMITADA | F114: 26999.91 | G114: Directo Equipo | H114: OC Aprobada
A115: 46086.517 | B115: DEMO-02-7830 | C115: =_xlfn.TEXTAFTER(TRIM(tblComprasPM[[#This Row],[Descripcion]]), " ", -1) -> VD-138 | D115: SC-02 MANTENCION EXTERNA VD-138 | E115: KAUFMANN S A VEHICULOS MOTORIZADOS | F115: 300335.77 | G115: Directo Equipo | H115: OC Aprobada
A116: 46086.626 | B116: DEMO-02-7833 | C116: =_xlfn.TEXTAFTER(TRIM(tblComprasPM[[#This Row],[Descripcion]]), " ", -1) -> VD-38 | D116: SC-02-6115 FILTROS VD-38 | E116: SOCIEDAD COMERCIAL SOCOFIL LIMITADA | F116: 40499.972 | G116: Directo Equipo | H116: OC Aprobada
A117: 46086.684 | B117: DEMO-02-7835 | C117: =_xlfn.TEXTAFTER(TRIM(tblComprasPM[[#This Row],[Descripcion]]), " ", -1) -> MD-82 | D117: SC-02-6138 FILTROS MD-82 | E117: COM. PUENTES DE MAULE LTDA. | F117: 321247.64 | G117: Directo Equipo | H117: OC Aprobada
A118: 46086.697 | B118: DEMO-02-7836 | C118: =_xlfn.TEXTAFTER(TRIM(tblComprasPM[[#This Row],[Descripcion]]), " ", -1) -> MD-105 | D118: SC-02-6135 FILTROS MD-105 | E118: COM. PUENTES DE MAULE LTDA. | F118: 255083.64 | G118: Directo Equipo | H118: OC Aprobada
A119: 46086.701 | B119: DEMO-02-7837 | C119: =_xlfn.TEXTAFTER(TRIM(tblComprasPM[[#This Row],[Descripcion]]), " ", -1) -> MD-76 | D119: SC-02-6136 FILTROS MD-76 | E119: COM. PUENTES DE MAULE LTDA. | F119: 283936.38 | G119: Directo Equipo | H119: OC Aprobada
A120: 46086.706 | B120: DEMO-02-7838 | C120: =_xlfn.TEXTAFTER(TRIM(tblComprasPM[[#This Row],[Descripcion]]), " ", -1) -> CD-127 | D120: SC-02-6140 FILTROS CD-127 | E120: COM. PUENTES DE MAULE LTDA. | F120: 222792.99 | G120: Directo Equipo | H120: OC Aprobada
A121: 46086.71 | B121: DEMO-02-7839 | C121: =_xlfn.TEXTAFTER(TRIM(tblComprasPM[[#This Row],[Descripcion]]), " ", -1) -> MD-95 | D121: SC-02-6132 FILTROS MD-95 | E121: COM. PUENTES DE MAULE LTDA. | F121: 133882.14 | G121: Directo Equipo | H121: OC Aprobada
A122: 46086.75 | B122: DEMO-02-7841 | C122: =_xlfn.TEXTAFTER(TRIM(tblComprasPM[[#This Row],[Descripcion]]), " ", -1) -> MD-85 | D122: SC-02-6123 FILTROS MD-85 | E122: COM. PUENTES DE MAULE LTDA. | F122: 206424.54 | G122: Directo Equipo | H122: OC Aprobada
A123: 46087.498 | B123: DEMO-02-7847 | C123: VD-107 | D123: SC-02-6163 MANTENCION EXTERNA VD-107 | E123: ROSSELOT Y FIGUEROA LIMITADA | F123: 506350.95 | G123: Directo Equipo | H123: OC Aprobada
A124: 46091.371 | B124: DEMO-02-7866 | C124: =_xlfn.TEXTAFTER(TRIM(tblComprasPM[[#This Row],[Descripcion]]), " ", -1) -> EQP-7 | D124: SC-02-6157 FILTROS EQP-7 | E124: COM. PUENTES DE MAULE LTDA. | F124: 111593.44 | G124: Directo Equipo | H124: OC Aprobada
A125: 46091.475 | B125: DEMO-02-7873 | C125: =_xlfn.TEXTAFTER(TRIM(tblComprasPM[[#This Row],[Descripcion]]), " ", -1) -> ED-61 | D125: SC-02-6171 FILTROS ED-61 | E125: SOCIEDAD COMERCIAL SOCOFIL LIMITADA | F125: 31799.977 | G125: Directo Equipo | H125: OC Aprobada
A126: 46092.556 | B126: DEMO-02-7891 | C126: =_xlfn.TEXTAFTER(TRIM(tblComprasPM[[#This Row],[Descripcion]]), " ", -1) -> EQP-7 | D126: SC-02-6156 FILTROS EQP-7 | E126: COM. PUENTES DE MAULE LTDA. | F126: 119511.7 | G126: Directo Equipo | H126: OC Aprobada
A127: 46093.365 | B127: DEMO-02-7897 | C127: =_xlfn.TEXTAFTER(TRIM(tblComprasPM[[#This Row],[Descripcion]]), " ", -1) -> CD-119 | D127: SC-02-6178 KIT FILTROS CD-119 | E127: AUTOMOTORA ALAMEDA SPA | F127: 170432.99 | G127: Directo Equipo | H127: OC Aprobada
A128: 46093.447 | B128: DEMO-02-7900 | C128: CD-121 | D128: SC-02-6177 FILTROS HID. MAN | E128: SOCIEDAD COMERCIAL SOCOFIL LIMITADA | F128: 6023.528 | G128: Prorrateo MAN | H128: OC Aprobada
A129: 46093.447 | B129: DEMO-02-7900 | C129: CD-122 | D129: SC-02-6177 FILTROS HID. MAN | E129: SOCIEDAD COMERCIAL SOCOFIL LIMITADA | F129: 6023.528 | G129: Prorrateo MAN | H129: OC Aprobada
...

Sheet Bodega
A1: BODEGA (EDITABLE)
A3: Folio | B3: Fecha | C3: Equipo | D3: Envio | E3: Persona que retiro | F3: Destino | G3: Comentario | H3: Codigo
B4: 46057 | C4: MD-56 | D4: Filtros Completos | F4: Taller | H4: MD-56
B5: 46058 | C5: MD-110 | D5: Filtros Completos | F5: Taller | H5: MD-110
B6: 46060 | C6: CD-104 | D6: Filtros Completos | F6: Taller | H6: CD-104
A7: 18005 | B7: 46062 | C7: CD-115 | D7: Filtros Incompletos | E7: JC Celedon | F7: Taller | G7: Filtro Secador de Aire | H7: CD-115
A8: 18053 | B8: 46065 | C8: MD-68 | D8: Filtros Completos | E8: Osvaldo Faundez | F8: San Nicolas | H8: MD-68
A9: 18039 | B9: 46071 | C9: VD-112 | D9: Filtro Completros | E9: Luis Valenzuela | F9: Taller | H9: VD-112
A10: 18043 | B10: 46072 | C10: VD-120 | D10: Filtro Completros | E10: Daniel Andrade | F10: Taller | H10: VD-120
A11: 18093 | B11: 46072 | C11: VD-120 | D11: Filtros Completos | E11: Marcos Soto | F11: Taller | H11: VD-120
A12: 18093 | B12: 46072 | C12: VD-122 | D12: Filtros Completos | E12: Marcos Soto | F12: Taller | H12: VD-122
A13: 18206 | B13: 46073 | C13: VD-60 | D13: Filtro Completros | E13: Carlos Verdugo | F13: Q-61 | H13: VD-60
A14: 18207 | B14: 46073 | C14: MD-41 | D14: Filtro Completros | E14: Carlos Verdugo | F14: Q-61 | H14: MD-41
A15: 18208 | B15: 46073 | C15: MD-45 | D15: Filtros Incompletos | E15: Carlos Verdugo | F15: Q-61 | H15: MD-45
A16: 18049 | B16: 46073 | C16: VD-115 | D16: Filtro Completros | E16: Daniel Andrade | F16: Taller | H16: VD-115
A17: 18253 | B17: 46073 | C17: CD-69 | D17: Filtros Completros | E17: Daniel Andrade | F17: Taller | G17: Se cambiaron y se compraron de nuevo el kit de aire motor | H17: CD-69
A18: 18225 | B18: 46077 | C18: CD-87 | D18: Filtro Secador | E18: Carlos Verdugo | F18: Palmucho | H18: CD-87
A19: 18226 | B19: 46077 | C19: VD-29 | D19: Filtros Completos | E19: Manuel Ortiz | F19: Cobquecura | H19: VD-29
A20: 18230 | B20: 46077 | C20: MD-84 | D20: Filtros Completos | F20: Quirihue | H20: MD-84
A21: 18236 | B21: 46078 | C21: MD-55 | D21: Filtro Completros | E21: Bernardo Salinas | F21: Palmucho | H21: MD-55
A22: 18236 | B22: 46078 | C22: MD-67 | D22: Filtro Completros | E22: Bernardo Salinas | F22: Palmucho | H22: MD-67
A23: 18264 | B23: 46078 | C23: VD-118 | D23: Filtro Completros | E23: Daniel Andrade | F23: Taller | H23: VD-118
A24: 18246 | B24: 46079 | C24: MD-62 | D24: Filtro Completros | E24: Marcos Soto | F24: Curico | H24: MD-62
A25: 18302 | B25: 46080 | C25: CD-123 | D25: Filtros Completos | E25: Marcos Soto | F25: Quirihue | H25: CD-123
A26: 18304 | B26: 46080 | C26: CD-121 | D26: Filtros Completos | F26: Cobquecura | H26: CD-121
A27: 18304 | B27: 46080 | C27: CD-120 | D27: Filtros Completos | F27: Cobquecura | H27: CD-120
A28: 18305 | B28: 46080 | C28: MD-94 | D28: Filtros Completos | F28: Cobquecura | H28: MD-94
A29: 18306 | B29: 46080 | C29: CD-140 | D29: Filtros Completos | F29: Cobquecura | H29: CD-140
A30: 18307 | B30: 46080 | C30: MD-26 | D30: Filtros Completos | F30: Cobquecura | H30: MD-26
A31: 18308 | B31: 46080 | C31: MD-95 | D31: Filtros Incompletos | F31: Quirihue | G31: Filtro decantador / Filtro Combustible / Filtro Aceite | H31: MD-95
A32: 18310 | B32: 46080 | C32: VD-124 | D32: Filtros Completos | F32: Cobquecura | H32: VD-124
A33: 18276 | B33: 46080 | C33: CD-125 | D33: Filtros Incompletos | E33: Patricio Novoa | G33: Filtro de combustible / Filtro de Aceite | H33: CD-125
A34: 18280 | B34: 46083 | C34: MD-51 | D34: Filtro Completros | F34: Palmucho | H34: MD-51
A35: 18284 | B35: 46083 | C35: MD-96 | D35: Filtros Completos | E35: Juan Roco | F35: San Carlos | H35: MD-96
A36: 18288 | B36: 46083 | C36: MD-94 | D36: Filtro Completros | F36: Palmucho | H36: MD-94
A37: 18289 | B37: 46083 | C37: MD-98 | D37: Filtros Completros | E37: Roberto Ventura | F37: Q-61 | H37: MD-98
B38: 46083 | C38: VD-88 | D38: Filtros Completos | F38: Palmucho | H38: VD-88
A39: 18322 | B39: 46084 | C39: CD-107 | D39: Filtros Incompletos | E39: Daniel Andrade | F39: Taller | G39: Filtro decantador / Filtro Combustible | H39: CD-107
A40: 18332 | B40: 46085 | C40: CD-86 | D40: Filtros Completos | E40: Marcos Soto | F40: Quirihue | H40: CD-86
A41: 18332 | B41: 46085 | C41: VD-113 | D41: Filtros Completos | E41: Marcos Soto | F41: Quirihue | H41: VD-113
A42: 18337 | B42: 46085 | C42: MD-39 | D42: Filtro Completros | E42: Alejandro Poblete | F42: Colbun | H42: MD-39
A43: 18341 | B43: 46085 | C43: MD-25 | D43: Filtros Completos | F43: San Carlos | H43: MD-25
A44: 18265 | B44: 46086 | C44: CD-88 | D44: Filtros Completos | E44: Carlos Vasquez | F44: Quirihue | H44: CD-88
B45: 46086 | C45: VD-38 | D45: Filtros Completos | F45: Taller | H45: VD-38
B46: 46086 | C46: MD-107 | D46: Filtros Completos | F46: Taller | H46: MD-107
A47: 18360 | B47: 46087 | C47: MD-25 | D47: Aceite 15w40 | E47: Alejandro Poblete | F47: San Carlos | H47: MD-25
A48: 18360 | B48: 46087 | C48: VD-121 | D48: Filtros Completos | E48: Alejandro Poblete | F48: San Carlos | H48: VD-121
A49: 18361 | B49: 46087 | C49: VD-102 | D49: Filtros Completos | E49: Luis Valenzuela | H49: VD-102
A50: 18408 | B50: 46087 | C50: CD-71 | D50: Filtros Completos | E50: Carlos Verdugo | F50: Palmucho | H50: CD-71
A51: 18409 | B51: 46087 | C51: MD-61 | D51: Filtros Completos | E51: Carlos Verdugo | F51: Palmucho | H51: MD-61
A52: 18409 | B52: 46087 | C52: VD-114 | D52: Filtros Completos | E52: Carlos Verdugo | F52: Palmucho | H52: VD-114
A53: 18410 | B53: 46087 | C53: MD-109 | D53: Filtros Completos | E53: Carlos Verdugo | F53: Palmucho | H53: MD-109
A54: 18411 | B54: 46087 | C54: CD-132 | D54: Filtros Completos | E54: Carlos Verdugo | F54: Palmucho | H54: CD-132
A55: 18418 | B55: 46090 | C55: CD-140 | D55: Filtros Incompletos | E55: Juan San Martin | F55: Cobquecura | G55: Filtro de combustible | H55: CD-140
A56: 18430 | B56: 46090 | C56: MD-75 | D56: Filtros Incompletos | E56: Francisco Parra | F56: Retiro | G56: Filtros de Aire 1 y 2 | H56: MD-75
A57: 18438 | B57: 46090 | C57: MD-76 | D57: Filtros Completos | E57: Daniel Andrade | F57: Q-61 | H57: MD-76
B58: 46091 | C58: CD-109 | D58: Filtros Completos | H58: CD-109
A59: 18457 | B59: 46093 | C59: MD-89 | D59: Filtros Completos | E59: Marcos Soto | F59: Quirihue | H59: MD-89
A60: 18458 | B60: 46093 | C60: MD-103 | D60: Filtros Completos | E60: Marcos Soto | F60: Quirihue | H60: MD-103
A61: 18466 | B61: 46093 | C61: EQP-7 | D61: Filtros Completos | E61: Roberto Tilleria | F61: San Nicolas | H61: EQP-07
B62: 46093 | C62: ED-73 | D62: Filtros Completos | F62: San Carlos | H62: ED-73
B63: 46093 | C63: VD-97 | D63: Filtros Completos | F63: Taller | H63: VD-97
B64: 46084 | C64: CD-122 | D64: Filtros Completos | F64: Taller | H64: CD-122
A65: 18384 | B65: 46094 | C65: MD-57 | D65: Filtros Completos | E65: Juan Celedon | F65: San Carlos | H65: MD-57
B66: 46094 | C66: MD-70 | D66: Filtros Completos | F66: Taller | H66: MD-70
A67: 18390 | B67: 46097 | C67: CD-90 | D67: Filtros Completos | E67: Jonathan Care | F67: Palmucho | H67: CD-90
A68: 18390 | B68: 46097 | C68: CD-94 | D68: Filtros Completos | E68: Jonathan Care | F68: Palmucho | H68: CD-94
A69: 18389 | B69: 46097 | C69: CD-98 | D69: Filtros Completos | E69: Jonathan Care | F69: Palmucho | H69: CD-98
A70: 18389 | B70: 46097 | C70: CD-96 | D70: Filtros Completos | E70: Jonathan Care | F70: Palmucho | H70: CD-96
A71: 18387 | B71: 46097 | C71: MD-82 | D71: Filtros Completos | E71: Jonathan Care | F71: Palmucho | H71: MD-82
A72: 18386 | B72: 46097 | C72: MD-67 | D72: Filtros Completos | E72: Jonathan Care | F72: Palmucho | H72: MD-67
B73: 46098 | C73: MD-73 | D73: Filtros Completos | F73: Taller | H73: MD-73
A74: 18398 | B74: 46099 | C74: VD-119 | D74: Filtros Completos | E74: Alejandro Poblete | F74: Taller | H74: VD-119
A75: 18397 | B75: 46099 | C75: VD-123 | D75: Filtros Completos | E75: Carlos Ramirez | F75: Taller | H75: VD-123
B76: 46099 | C76: CD-119 | D76: Filtros Completos | F76: Taller | H76: CD-119
B77: 46100 | C77: MD-79 | D77: Filtros Completos | F77: Taller | H77: MD-79
B78: 46101 | C78: CD-110 | D78: Filtros Completos | F78: Taller | H78: CD-110
B79: 46101 | C79: MD-87 | D79: Filtros Completos | F79: Taller | H79: MD-87
B80: 46101 | C80: MD-80 | D80: Filtros Completos | F80: Palmucho | H80: MD-80
B81: 46101 | C81: VD-94 | D81: Filtros Completos | H81: VD-94
A82: 18400 | B82: 46104 | C82: VD-28 | D82: Filtros Completos | E82: Alejandro Poblete | F82: Taller | H82: VD-28
B83: 46104 | C83: ED-61 | D83: Filtros Completos | E83: Roberto Ventura | F83: Palmucho | H83: ED-61
B84: 46104 | C84: MD-83 | D84: Filtros Completos | F84: Taller | H84: MD-83
B85: 46105 | C85: MD-28 | D85: Filtros Completos | E85: Juan Villalobos | F85: Villa Seca | H85: MD-28
B86: 46105 | C86: MD-49 | D86: Filtros Completos | E86: Juan Villalobos | F86: San Carlos | H86: MD-49
B87: 46105 | C87: MD-37 | D87: Filtros Completos | E87: Juan Villalobos | F87: Colbun | H87: MD-37
B88: 46105 | C88: EQP-11 | D88: Filtros Completos | E88: Osvaldo Faundez | F88: Palmucho | H88: EQP-11
B89: 46105 | C89: EQP-18 | D89: Filtros Completos | E89: Osvaldo Faundez | F89: Palmucho | H89: EQP-18
B90: 46105 | C90: CD-105 | D90: Filtros Completos | E90: Osvaldo Faundez | F90: Palmucho | H90: CD-105
B91: 46105 | C91: CD-89 | D91: Filtros Completos | E91: Osvaldo Faundez | F91: Palmucho | H91: CD-89
A92: 18560 | B92: 46106 | C92: VD-39 | D92: Filtros Completos | F92: Taller | H92: VD-39
A93: 18561 | B93: 46106 | C93: MD-71 | D93: Filtros Completos | F93: Taler | H93: MD-71
A94: 18570 | B94: 46111 | C94: MD-72 | D94: Filtros Completos | E94: Juan Celedon | F94: Taler | H94: MD-72
B95: 46111 | C95: MD-100 | D95: Filtros Completos | F95: Taller | H95: MD-100
B96: 46113 | C96: CD-100 | D96: Filtros Completos | F96: Taller | H96: CD-100
B97: 46118 | C97: VD-103 | D97: Filtros Completos | F97: Taller | H97: VD-103
B98: 46118 | C98: VD-63 | D98: Filtros Completos | F98: Taller | H98: VD-63
B99: 46118 | C99: VD-79 | D99: Filtros Completos | F99: Taller | H99: VD-79
B100: 46118 | C100: VD-117 | D100: Filtros Completos | F100: Taller | H100: VD-117
B101: 46118 | C101: VD-92 | D101: Filtros Completos | F101: Taller | H101: VD-92
...

Sheet Maestro_Equipos
A1: Maestro de Equipos
A3: Codigo | B3: Tipo Equipo | C3: Familia | D3: Marca | E3: Modelo | F3: Año | G3: Ubicacion | H3: Responsable | I3: Control Base | J3: Frecuencia Base | K3: Promedio Diario | L3: Ultima Fecha Lectura | M3: Ultimo Horometro | N3: Ultimo Kilometraje | O3: Lectura Actual | P3: Ultima Fecha PM | Q3: Ultima PM | R3: Ultima Lectura PM | S3: Costo Mantenciones CLP | T3: Costo Compras PM CLP | U3: Costo Total PM CLP | V3: Estado Operacional | W3: Estado CMMS | X3: Dias a Proxima Mantencion | Y3: Fecha Est. Proxima Mantencion | Z3: Fecha Compra PM | AA3: Fecha Salida Bodega | AB3: Tiempo Compra → Mantención | AC3: Tiempo Bodega → Mantención | AD3: Estado Bodega → Mantención | AE3: Estado Operativo Real | AF3: Prioridad Taller | AG3: Acción Sugerida | AH3: _CompraRequerida | AI3: _OrdenCompra | AJ3: Criticidad
A4: CD-100 | B4: Camión Slurry | C4: Camiones de Ruta | D4: Volkswagen | E4: 26220 | F4: 2008 | G4: =IFERROR(_xlfn.XLOOKUP($A4,tblEquipos[Codigo],tblEquipos[Ubicacion],""),"") -> San Carlos | H4: Juan Espinoza | I4: =IFERROR(VLOOKUP(A4, Equipos!A:J, 9, FALSE), "") -> HORAS | J4: =IFERROR(VLOOKUP(A4, Equipos!A:J, 10, FALSE), "") -> 250 | K4: =IFERROR(IF($I4="KM",ROUND((_xlfn.MAXIFS(tblLecturas[Kilometraje],tblLecturas[Codigo],$A4)-_xlfn.MINIFS(tblLecturas[Kilometraje],tblLecturas[Codigo],$A4))/(MAX(1,_xlfn.MAXIFS(tblLecturas[Fecha],tblLecturas[Codigo],$A4)-_xlfn.MINIFS(tblLecturas[Fecha],tblLecturas[Codigo],$A4))),1),ROUND((_xlfn.MAXIFS(tblLecturas[Horometro],tblLecturas[Codigo],$A4)-_xlfn.MINIFS(tblLecturas[Horometro],tblLecturas[Codigo],$A4))/(MAX(1,_xlfn.MAXIFS(tblLecturas[Fecha],tblLecturas[Codigo],$A4)-_xlfn.MINIFS(tblLecturas[Fecha],tblLecturas[Codigo],$A4))),1)),"") -> 1 | L4: =IFERROR(_xlfn.MAXIFS(tblLecturas[Fecha],tblLecturas[Codigo],$A4),"") -> 46155 | M4: =IFERROR(_xlfn.MAXIFS(Lecturas!$C:$C,Lecturas!$B:$B,$A4,Lecturas!$C:$C,">0"),"") -> 2852 | N4: =IFERROR(_xlfn.MAXIFS(tblLecturas[Kilometraje],tblLecturas[Codigo],$A4,tblLecturas[Kilometraje],">0"),"") -> 158684 | O4: {=IFERROR(IF($I4="KM",LOOKUP(2,1/(Lecturas!$B:$B=$A4)/(Lecturas!$D:$D>0),Lecturas!$D:$D),LOOKUP(2,1/(Lecturas!$B:$B=$A4)/(Lecturas!$C:$C>0),Lecturas!$C:$C)),"")} -> 985 | P4: =IFERROR(_xlfn.MAXIFS(tblMantenciones[Fecha],tblMantenciones[Codigo],tblMaestroEquipos[[#This Row],[Codigo]],tblMantenciones[EsPM],"Sí"),"") -> 46113 | Q4: =IF(_xlfn.MAXIFS(Mantenciones!$D:$D,Mantenciones!$B:$B,A4)=0,"Sin datos de mantención registrado",_xlfn.MAXIFS(Mantenciones!$D:$D,Mantenciones!$B:$B,A4)) -> 2882 | R4: =IFERROR(IF(_xlfn.MAXIFS(Mantenciones!$D:$D,Mantenciones!$B:$B,$A4,Mantenciones!$E:$E,"Sí",Mantenciones!$D:$D,">0")=0,"Sin datos de mantención registrado",_xlfn.MAXIFS(Mantenciones!$D:$D,Mantenciones!$B:$B,$A4,Mantenciones!$E:$E,"Sí",Mantenciones!$D:$D,">0")),"Sin datos de mantención registrado") -> 2882 | S4: =IFERROR(SUMIFS(tblMantenciones[Costo Mantencion CLP],tblMantenciones[Codigo],A4),0) -> 0 | T4: =IFERROR(SUMIFS(tblComprasPM[Costo PM CLP],tblComprasPM[Codigo],tblMaestroEquipos[[#This Row],[Codigo]]),0) -> 199255.98 | U4: =IFERROR(tblMaestroEquipos[[#This Row],[Costo Mantenciones CLP]]+tblMaestroEquipos[[#This Row],[Costo Compras PM CLP]],0) -> 199255.98 | V4: =IFERROR(_xlfn.XLOOKUP(tblMaestroEquipos[[#This Row],[Codigo]],tblEquipos[Codigo],tblEquipos[Estado Base]),"") -> Operativo | W4: =IF(OR(TRIM($V4)="Fuera de Servicio",TRIM($V4)="Fuera de servicio"),"FUERA DE SERVICIO",IF(OR(TRIM($V4)="Taller",TRIM($V4)="En taller",TRIM($V4)="EN TALLER"),"EN TALLER",IF($AD4="PENDIENTE","POR RECIBIR",IF(AND($Z4<>"",$AA4=""),"EN PROCESO",IF(AND(ISNUMBER($X4),$X4<0),"ATRASADA",IF(AND(ISNUMBER($X4),$X4<=30),"PRÓXIMA","AL DÍA")))))) -> AL DÍA | X4: =IF(OR(NOT(ISNUMBER(R4)),NOT(ISNUMBER(J4)),NOT(ISNUMBER(O4))),"", (R4+J4)-O4) -> 2147 | Y4: =IFERROR(IF(OR(tblMaestroEquipos[[#This Row],[Estado Operacional]]="FUERA DE SERVICIO",tblMaestroEquipos[[#This Row],[Ultima Fecha Lectura]]="",tblMaestroEquipos[[#This Row],[Dias a Proxima Mantencion]]=""),"",tblMaestroEquipos[[#This Row],[Ultima Fecha Lectura]]+tblMaestroEquipos[[#This Row],[Dias a Proxima Mantencion]]),"") -> 48302 | Z4: =IFERROR(IF(_xlfn.MINIFS(tblComprasPM[Fecha],tblComprasPM[Codigo],tblMaestroEquipos[[#This Row],[Codigo]])=0,"",_xlfn.MINIFS(tblComprasPM[Fecha],tblComprasPM[Codigo],tblMaestroEquipos[[#This Row],[Codigo]])),"") -> 46085.627 | AA4: =IFERROR(IF(_xlfn.MAXIFS(tblBodega[Fecha],tblBodega[Codigo],tblMaestroEquipos[[#This Row],[Codigo]])=0,"",_xlfn.MAXIFS(tblBodega[Fecha],tblBodega[Codigo],tblMaestroEquipos[[#This Row],[Codigo]])),"") -> 46113 | AB4: =IFERROR(IF(OR(tblMaestroEquipos[[#This Row],[Fecha Compra PM]]="",tblMaestroEquipos[[#This Row],[Fecha Compra PM]]=0),"",IF(OR(tblMaestroEquipos[[#This Row],[Ultima Fecha PM]]="",tblMaestroEquipos[[#This Row],[Ultima Fecha PM]]=0),MAX(0,INT(TODAY())-INT(tblMaestroEquipos[[#This Row],[Fecha Compra PM]])),MAX(0,INT(tblMaestroEquipos[[#This Row],[Ultima Fecha PM]])-INT(tblMaestroEquipos[[#This Row],[Fecha Compra PM]])))),"") -> 28 | AC4: =IFERROR(IF(OR(tblMaestroEquipos[[#This Row],[Fecha Salida Bodega]]="",tblMaestroEquipos[[#This Row],[Fecha Salida Bodega]]=0),"",IF(OR(tblMaestroEquipos[[#This Row],[Ultima Fecha PM]]="",tblMaestroEquipos[[#This Row],[Ultima Fecha PM]]=0),MAX(0,INT(TODAY())-INT(tblMaestroEquipos[[#This Row],[Fecha Salida Bodega]])),MAX(0,INT(tblMaestroEquipos[[#This Row],[Ultima Fecha PM]])-INT(tblMaestroEquipos[[#This Row],[Fecha Salida Bodega]])))),"") -> 0 | AD4: =IF(tblMaestroEquipos[[#This Row],[Fecha Salida Bodega]]="","SIN SALIDA BODEGA",IF(OR(tblMaestroEquipos[[#This Row],[Ultima Fecha PM]]="",tblMaestroEquipos[[#This Row],[Ultima Fecha PM]]<tblMaestroEquipos[[#This Row],[Fecha Salida Bodega]]),"PENDIENTE","CERRADO")) -> CERRADO | AE4: =IF(TRIM(V4)="Fuera de servicio","FUERA DE SERVICIO", IF(OR(TRIM(V4)="Taller",TRIM(V4)="En taller"),"EN TALLER", IF(W4="ATRASADO","ATRASADO", IF(W4="EN PROCESO","EN PROCESO", IF(W4="PRÓXIMO","PRÓXIMO", "OPERATIVO"))))) -> OPERATIVO | AF4: =IF($AE4="ATRASADA",IF($X4<=-15,"CRÍTICA","ALTA"),IF($AE4="PRÓXIMA","MEDIA",IF(OR($AE4="EN PROCESO",$AE4="POR RECIBIR"),"SEGUIMIENTO",IF($AE4="FUERA DE SERVICIO","NO APLICA","BAJA")))) -> BAJA | AG4: =IF($AE4="FUERA DE SERVICIO","No programar compra",IF($AE4="CERRADO","Cerrar ciclo y preparar siguiente PM",IF($AE4="EN PROCESO","Hacer seguimiento al taller y cerrar report",IF($AE4="POR RECIBIR","Acelerar recepción de repuestos",IF($AE4="ATRASADA","Comprar kit PM y coordinar ejecución",IF($AE4="PRÓXIMA","Planificar compra preventiva","Monitorear próximo vencimiento")))))) -> Monitorear próximo vencimiento | AH4: =IF(AND(OR($AE4="ATRASADA",$AE4="PRÓXIMA"),$Z4="",$AA4=""),1,0) -> 0 | AI4: =IF(OR($AH4=0,$Y4=""),"",SUMPRODUCT(($AH$4:$AH$242=1)*(($Y$4:$Y$242<$Y4)+(($Y$4:$Y$242=$Y4)*(ROW($Y$4:$Y$242)<=ROW()))))) | AJ4: =IF(W4="ATRASADA",1,IF(W4="EN PROCESO",2,IF(W4="POR RECIBIR",3,99))) -> 99
A5: CD-102 | B5: Camión Tolva | C5: Camiones de Ruta | D5: Man | E5: TGS 50480 | F5: 2018 | G5: =IFERROR(_xlfn.XLOOKUP($A5,tblEquipos[Codigo],tblEquipos[Ubicacion],""),"") -> San Nicolas | H5: Nelson Garcia | I5: =IFERROR(VLOOKUP(A5, Equipos!A:J, 9, FALSE), "") -> HORAS | J5: =IFERROR(VLOOKUP(A5, Equipos!A:J, 10, FALSE), "") -> 500 | K5: =IFERROR(IF($I5="KM",ROUND((_xlfn.MAXIFS(tblLecturas[Kilometraje],tblLecturas[Codigo],$A5)-_xlfn.MINIFS(tblLecturas[Kilometraje],tblLecturas[Codigo],$A5))/(MAX(1,_xlfn.MAXIFS(tblLecturas[Fecha],tblLecturas[Codigo],$A5)-_xlfn.MINIFS(tblLecturas[Fecha],tblLecturas[Codigo],$A5))),1),ROUND((_xlfn.MAXIFS(tblLecturas[Horometro],tblLecturas[Codigo],$A5)-_xlfn.MINIFS(tblLecturas[Horometro],tblLecturas[Codigo],$A5))/(MAX(1,_xlfn.MAXIFS(tblLecturas[Fecha],tblLecturas[Codigo],$A5)-_xlfn.MINIFS(tblLecturas[Fecha],tblLecturas[Codigo],$A5))),1)),"") -> 4.5 | L5: =IFERROR(_xlfn.MAXIFS(tblLecturas[Fecha],tblLecturas[Codigo],$A5),"") -> 46160 | M5: =IFERROR(_xlfn.MAXIFS(Lecturas!$C:$C,Lecturas!$B:$B,$A5,Lecturas!$C:$C,">0"),"") -> 10633 | N5: =IFERROR(_xlfn.MAXIFS(tblLecturas[Kilometraje],tblLecturas[Codigo],$A5,tblLecturas[Kilometraje],">0"),"") -> 262575 | O5: {=IFERROR(IF($I5="KM",LOOKUP(2,1/(Lecturas!$B:$B=$A5)/(Lecturas!$D:$D>0),Lecturas!$D:$D),LOOKUP(2,1/(Lecturas!$B:$B=$A5)/(Lecturas!$C:$C>0),Lecturas!$C:$C)),"")} -> 10633 | P5: =IFERROR(_xlfn.MAXIFS(tblMantenciones[Fecha],tblMantenciones[Codigo],tblMaestroEquipos[[#This Row],[Codigo]],tblMantenciones[EsPM],"Sí"),"") -> 46197 | Q5: =IF(_xlfn.MAXIFS(Mantenciones!$D:$D,Mantenciones!$B:$B,A5)=0,"Sin datos de mantención registrado",_xlfn.MAXIFS(Mantenciones!$D:$D,Mantenciones!$B:$B,A5)) -> 11042 | R5: =IFERROR(IF(_xlfn.MAXIFS(Mantenciones!$D:$D,Mantenciones!$B:$B,$A5,Mantenciones!$E:$E,"Sí",Mantenciones!$D:$D,">0")=0,"Sin datos de mantención registrado",_xlfn.MAXIFS(Mantenciones!$D:$D,Mantenciones!$B:$B,$A5,Mantenciones!$E:$E,"Sí",Mantenciones!$D:$D,">0")),"Sin datos de mantención registrado") -> 11042 | S5: =IFERROR(SUMIFS(tblMantenciones[Costo Mantencion CLP],tblMantenciones[Codigo],A5),0) -> 0 | T5: =IFERROR(SUMIFS(tblComprasPM[Costo PM CLP],tblComprasPM[Codigo],tblMaestroEquipos[[#This Row],[Codigo]]),0) -> 314826.62 | U5: =IFERROR(tblMaestroEquipos[[#This Row],[Costo Mantenciones CLP]]+tblMaestroEquipos[[#This Row],[Costo Compras PM CLP]],0) -> 314826.62 | V5: =IFERROR(_xlfn.XLOOKUP(tblMaestroEquipos[[#This Row],[Codigo]],tblEquipos[Codigo],tblEquipos[Estado Base]),"") -> Operativo | W5: =IF(OR(TRIM($V5)="Fuera de Servicio",TRIM($V5)="Fuera de servicio"),"FUERA DE SERVICIO",IF(OR(TRIM($V5)="Taller",TRIM($V5)="En taller",TRIM($V5)="EN TALLER"),"EN TALLER",IF($AD5="PENDIENTE","POR RECIBIR",IF(AND($Z5<>"",$AA5=""),"EN PROCESO",IF(AND(ISNUMBER($X5),$X5<0),"ATRASADA",IF(AND(ISNUMBER($X5),$X5<=30),"PRÓXIMA","AL DÍA")))))) -> AL DÍA | X5: =IF(OR(NOT(ISNUMBER(R5)),NOT(ISNUMBER(J5)),NOT(ISNUMBER(O5))),"", (R5+J5)-O5) -> 909 | Y5: =IFERROR(IF(OR(tblMaestroEquipos[[#This Row],[Estado Operacional]]="FUERA DE SERVICIO",tblMaestroEquipos[[#This Row],[Ultima Fecha Lectura]]="",tblMaestroEquipos[[#This Row],[Dias a Proxima Mantencion]]=""),"",tblMaestroEquipos[[#This Row],[Ultima Fecha Lectura]]+tblMaestroEquipos[[#This Row],[Dias a Proxima Mantencion]]),"") -> 47069 | Z5: =IFERROR(IF(_xlfn.MINIFS(tblComprasPM[Fecha],tblComprasPM[Codigo],tblMaestroEquipos[[#This Row],[Codigo]])=0,"",_xlfn.MINIFS(tblComprasPM[Fecha],tblComprasPM[Codigo],tblMaestroEquipos[[#This Row],[Codigo]])),"") -> 46069.447 | AA5: =IFERROR(IF(_xlfn.MAXIFS(tblBodega[Fecha],tblBodega[Codigo],tblMaestroEquipos[[#This Row],[Codigo]])=0,"",_xlfn.MAXIFS(tblBodega[Fecha],tblBodega[Codigo],tblMaestroEquipos[[#This Row],[Codigo]])),"") -> 46174 | AB5: =IFERROR(IF(OR(tblMaestroEquipos[[#This Row],[Fecha Compra PM]]="",tblMaestroEquipos[[#This Row],[Fecha Compra PM]]=0),"",IF(OR(tblMaestroEquipos[[#This Row],[Ultima Fecha PM]]="",tblMaestroEquipos[[#This Row],[Ultima Fecha PM]]=0),MAX(0,INT(TODAY())-INT(tblMaestroEquipos[[#This Row],[Fecha Compra PM]])),MAX(0,INT(tblMaestroEquipos[[#This Row],[Ultima Fecha PM]])-INT(tblMaestroEquipos[[#This Row],[Fecha Compra PM]])))),"") -> 128 | AC5: =IFERROR(IF(OR(tblMaestroEquipos[[#This Row],[Fecha Salida Bodega]]="",tblMaestroEquipos[[#This Row],[Fecha Salida Bodega]]=0),"",IF(OR(tblMaestroEquipos[[#This Row],[Ultima Fecha PM]]="",tblMaestroEquipos[[#This Row],[Ultima Fecha PM]]=0),MAX(0,INT(TODAY())-INT(tblMaestroEquipos[[#This Row],[Fecha Salida Bodega]])),MAX(0,INT(tblMaestroEquipos[[#This Row],[Ultima Fecha PM]])-INT(tblMaestroEquipos[[#This Row],[Fecha Salida Bodega]])))),"") -> 23 | AD5: =IF(tblMaestroEquipos[[#This Row],[Fecha Salida Bodega]]="","SIN SALIDA BODEGA",IF(OR(tblMaestroEquipos[[#This Row],[Ultima Fecha PM]]="",tblMaestroEquipos[[#This Row],[Ultima Fecha PM]]<tblMaestroEquipos[[#This Row],[Fecha Salida Bodega]]),"PENDIENTE","CERRADO")) -> CERRADO | AE5: =IF(TRIM(V5)="Fuera de servicio","FUERA DE SERVICIO", IF(OR(TRIM(V5)="Taller",TRIM(V5)="En taller"),"EN TALLER", IF(W5="ATRASADO","ATRASADO", IF(W5="EN PROCESO","EN PROCESO", IF(W5="PRÓXIMO","PRÓXIMO", "OPERATIVO"))))) -> OPERATIVO | AF5: =IF($AE5="ATRASADA",IF($X5<=-15,"CRÍTICA","ALTA"),IF($AE5="PRÓXIMA","MEDIA",IF(OR($AE5="EN PROCESO",$AE5="POR RECIBIR"),"SEGUIMIENTO",IF($AE5="FUERA DE SERVICIO","NO APLICA","BAJA")))) -> BAJA | AG5: =IF($AE5="FUERA DE SERVICIO","No programar compra",IF($AE5="CERRADO","Cerrar ciclo y preparar siguiente PM",IF($AE5="EN PROCESO","Hacer seguimiento al taller y cerrar report",IF($AE5="POR RECIBIR","Acelerar recepción de repuestos",IF($AE5="ATRASADA","Comprar kit PM y coordinar ejecución",IF($AE5="PRÓXIMA","Planificar compra preventiva","Monitorear próximo vencimiento")))))) -> Monitorear próximo vencimiento | AH5: =IF(AND(OR($AE5="ATRASADA",$AE5="PRÓXIMA"),$Z5="",$AA5=""),1,0) -> 0 | AI5: =IF(OR($AH5=0,$Y5=""),"",SUMPRODUCT(($AH$4:$AH$242=1)*(($Y$4:$Y$242<$Y5)+(($Y$4:$Y$242=$Y5)*(ROW($Y$4:$Y$242)<=ROW()))))) | AJ5: =IF(W5="ATRASADA",1,IF(W5="EN PROCESO",2,IF(W5="POR RECIBIR",3,99))) -> 99
A6: CD-103 | B6: Camión Tolva | C6: Camiones de Ruta | D6: Man | E6: TGS 50480 | F6: 2018 | G6: =IFERROR(_xlfn.XLOOKUP($A6,tblEquipos[Codigo],tblEquipos[Ubicacion],""),"") -> TALLER | H6: Felipe Figueroa | I6: =IFERROR(VLOOKUP(A6, Equipos!A:J, 9, FALSE), "") -> HORAS | J6: =IFERROR(VLOOKUP(A6, Equipos!A:J, 10, FALSE), "") -> 500 | K6: =IFERROR(IF($I6="KM",ROUND((_xlfn.MAXIFS(tblLecturas[Kilometraje],tblLecturas[Codigo],$A6)-_xlfn.MINIFS(tblLecturas[Kilometraje],tblLecturas[Codigo],$A6))/(MAX(1,_xlfn.MAXIFS(tblLecturas[Fecha],tblLecturas[Codigo],$A6)-_xlfn.MINIFS(tblLecturas[Fecha],tblLecturas[Codigo],$A6))),1),ROUND((_xlfn.MAXIFS(tblLecturas[Horometro],tblLecturas[Codigo],$A6)-_xlfn.MINIFS(tblLecturas[Horometro],tblLecturas[Codigo],$A6))/(MAX(1,_xlfn.MAXIFS(tblLecturas[Fecha],tblLecturas[Codigo],$A6)-_xlfn.MINIFS(tblLecturas[Fecha],tblLecturas[Codigo],$A6))),1)),"") -> 0 | L6: =IFERROR(_xlfn.MAXIFS(tblLecturas[Fecha],tblLecturas[Codigo],$A6),"") -> 45056 | M6: =IFERROR(_xlfn.MAXIFS(Lecturas!$C:$C,Lecturas!$B:$B,$A6,Lecturas!$C:$C,">0"),"") -> 5327 | N6: =IFERROR(_xlfn.MAXIFS(tblLecturas[Kilometraje],tblLecturas[Codigo],$A6,tblLecturas[Kilometraje],">0"),"") -> 126893 | O6: {=IFERROR(IF($I6="KM",LOOKUP(2,1/(Lecturas!$B:$B=$A6)/(Lecturas!$D:$D>0),Lecturas!$D:$D),LOOKUP(2,1/(Lecturas!$B:$B=$A6)/(Lecturas!$C:$C>0),Lecturas!$C:$C)),"")} -> 5327 | P6: =IFERROR(_xlfn.MAXIFS(tblMantenciones[Fecha],tblMantenciones[Codigo],tblMaestroEquipos[[#This Row],[Codigo]],tblMantenciones[EsPM],"Sí"),"") -> 45234 | Q6: =IF(_xlfn.MAXIFS(Mantenciones!$D:$D,Mantenciones!$B:$B,A6)=0,"Sin datos de mantención registrado",_xlfn.MAXIFS(Mantenciones!$D:$D,Mantenciones!$B:$B,A6)) -> 5942 | R6: =IFERROR(IF(_xlfn.MAXIFS(Mantenciones!$D:$D,Mantenciones!$B:$B,$A6,Mantenciones!$E:$E,"Sí",Mantenciones!$D:$D,">0")=0,"Sin datos de mantención registrado",_xlfn.MAXIFS(Mantenciones!$D:$D,Mantenciones!$B:$B,$A6,Mantenciones!$E:$E,"Sí",Mantenciones!$D:$D,">0")),"Sin datos de mantención registrado") -> 5942 | S6: =IFERROR(SUMIFS(tblMantenciones[Costo Mantencion CLP],tblMantenciones[Codigo],A6),0) -> 0 | T6: =IFERROR(SUMIFS(tblComprasPM[Costo PM CLP],tblComprasPM[Codigo],tblMaestroEquipos[[#This Row],[Codigo]]),0) -> 0 | U6: =IFERROR(tblMaestroEquipos[[#This Row],[Costo Mantenciones CLP]]+tblMaestroEquipos[[#This Row],[Costo Compras PM CLP]],0) -> 0 | V6: =IFERROR(_xlfn.XLOOKUP(tblMaestroEquipos[[#This Row],[Codigo]],tblEquipos[Codigo],tblEquipos[Estado Base]),"") -> Fuera de Servicio | W6: =IF(OR(TRIM($V6)="Fuera de Servicio",TRIM($V6)="Fuera de servicio"),"FUERA DE SERVICIO",IF(OR(TRIM($V6)="Taller",TRIM($V6)="En taller",TRIM($V6)="EN TALLER"),"EN TALLER",IF($AD6="PENDIENTE","POR RECIBIR",IF(AND($Z6<>"",$AA6=""),"EN PROCESO",IF(AND(ISNUMBER($X6),$X6<0),"ATRASADA",IF(AND(ISNUMBER($X6),$X6<=30),"PRÓXIMA","AL DÍA")))))) -> FUERA DE SERVICIO | X6: =IF(OR(NOT(ISNUMBER(R6)),NOT(ISNUMBER(J6)),NOT(ISNUMBER(O6))),"", (R6+J6)-O6) -> 1115 | Y6: =IFERROR(IF(OR(tblMaestroEquipos[[#This Row],[Estado Operacional]]="FUERA DE SERVICIO",tblMaestroEquipos[[#This Row],[Ultima Fecha Lectura]]="",tblMaestroEquipos[[#This Row],[Dias a Proxima Mantencion]]=""),"",tblMaestroEquipos[[#This Row],[Ultima Fecha Lectura]]+tblMaestroEquipos[[#This Row],[Dias a Proxima Mantencion]]),"") | Z6: =IFERROR(IF(_xlfn.MINIFS(tblComprasPM[Fecha],tblComprasPM[Codigo],tblMaestroEquipos[[#This Row],[Codigo]])=0,"",_xlfn.MINIFS(tblComprasPM[Fecha],tblComprasPM[Codigo],tblMaestroEquipos[[#This Row],[Codigo]])),"") | AA6: =IFERROR(IF(_xlfn.MAXIFS(tblBodega[Fecha],tblBodega[Codigo],tblMaestroEquipos[[#This Row],[Codigo]])=0,"",_xlfn.MAXIFS(tblBodega[Fecha],tblBodega[Codigo],tblMaestroEquipos[[#This Row],[Codigo]])),"") | AB6: =IFERROR(IF(OR(tblMaestroEquipos[[#This Row],[Fecha Compra PM]]="",tblMaestroEquipos[[#This Row],[Fecha Compra PM]]=0),"",IF(OR(tblMaestroEquipos[[#This Row],[Ultima Fecha PM]]="",tblMaestroEquipos[[#This Row],[Ultima Fecha PM]]=0),MAX(0,INT(TODAY())-INT(tblMaestroEquipos[[#This Row],[Fecha Compra PM]])),MAX(0,INT(tblMaestroEquipos[[#This Row],[Ultima Fecha PM]])-INT(tblMaestroEquipos[[#This Row],[Fecha Compra PM]])))),"") | AC6: =IFERROR(IF(OR(tblMaestroEquipos[[#This Row],[Fecha Salida Bodega]]="",tblMaestroEquipos[[#This Row],[Fecha Salida Bodega]]=0),"",IF(OR(tblMaestroEquipos[[#This Row],[Ultima Fecha PM]]="",tblMaestroEquipos[[#This Row],[Ultima Fecha PM]]=0),MAX(0,INT(TODAY())-INT(tblMaestroEquipos[[#This Row],[Fecha Salida Bodega]])),MAX(0,INT(tblMaestroEquipos[[#This Row],[Ultima Fecha PM]])-INT(tblMaestroEquipos[[#This Row],[Fecha Salida Bodega]])))),"") | AD6: =IF(tblMaestroEquipos[[#This Row],[Fecha Salida Bodega]]="","SIN SALIDA BODEGA",IF(OR(tblMaestroEquipos[[#This Row],[Ultima Fecha PM]]="",tblMaestroEquipos[[#This Row],[Ultima Fecha PM]]<tblMaestroEquipos[[#This Row],[Fecha Salida Bodega]]),"PENDIENTE","CERRADO")) -> SIN SALIDA BODEGA | AE6: =IF(TRIM(V6)="Fuera de servicio","FUERA DE SERVICIO", IF(OR(TRIM(V6)="Taller",TRIM(V6)="En taller"),"EN TALLER", IF(W6="ATRASADO","ATRASADO", IF(W6="EN PROCESO","EN PROCESO", IF(W6="PRÓXIMO","PRÓXIMO", "OPERATIVO"))))) -> FUERA DE SERVICIO | AF6: =IF($AE6="ATRASADA",IF($X6<=-15,"CRÍTICA","ALTA"),IF($AE6="PRÓXIMA","MEDIA",IF(OR($AE6="EN PROCESO",$AE6="POR RECIBIR"),"SEGUIMIENTO",IF($AE6="FUERA DE SERVICIO","NO APLICA","BAJA")))) -> NO APLICA | AG6: =IF($AE6="FUERA DE SERVICIO","No programar compra",IF($AE6="CERRADO","Cerrar ciclo y preparar siguiente PM",IF($AE6="EN PROCESO","Hacer seguimiento al taller y cerrar report",IF($AE6="POR RECIBIR","Acelerar recepción de repuestos",IF($AE6="ATRASADA","Comprar kit PM y coordinar ejecución",IF($AE6="PRÓXIMA","Planificar compra preventiva","Monitorear próximo vencimiento")))))) -> No programar compra | AH6: =IF(AND(OR($AE6="ATRASADA",$AE6="PRÓXIMA"),$Z6="",$AA6=""),1,0) -> 0 | AI6: =IF(OR($AH6=0,$Y6=""),"",SUMPRODUCT(($AH$4:$AH$242=1)*(($Y$4:$Y$242<$Y6)+(($Y$4:$Y$242=$Y6)*(ROW($Y$4:$Y$242)<=ROW()))))) | AJ6: =IF(W6="ATRASADA",1,IF(W6="EN PROCESO",2,IF(W6="POR RECIBIR",3,99))) -> 99
A7: CD-104 | B7: Camión Tolva | C7: Camiones de Ruta | D7: Man | E7: TGS 50480 | F7: 2019 | G7: =IFERROR(_xlfn.XLOOKUP($A7,tblEquipos[Codigo],tblEquipos[Ubicacion],""),"") -> Emergencias Curico | H7: Nelson Cancino | I7: =IFERROR(VLOOKUP(A7, Equipos!A:J, 9, FALSE), "") -> HORAS | J7: =IFERROR(VLOOKUP(A7, Equipos!A:J, 10, FALSE), "") -> 250 | K7: =IFERROR(IF($I7="KM",ROUND((_xlfn.MAXIFS(tblLecturas[Kilometraje],tblLecturas[Codigo],$A7)-_xlfn.MINIFS(tblLecturas[Kilometraje],tblLecturas[Codigo],$A7))/(MAX(1,_xlfn.MAXIFS(tblLecturas[Fecha],tblLecturas[Codigo],$A7)-_xlfn.MINIFS(tblLecturas[Fecha],tblLecturas[Codigo],$A7))),1),ROUND((_xlfn.MAXIFS(tblLecturas[Horometro],tblLecturas[Codigo],$A7)-_xlfn.MINIFS(tblLecturas[Horometro],tblLecturas[Codigo],$A7))/(MAX(1,_xlfn.MAXIFS(tblLecturas[Fecha],tblLecturas[Codigo],$A7)-_xlfn.MINIFS(tblLecturas[Fecha],tblLecturas[Codigo],$A7))),1)),"") -> 0 | L7: =IFERROR(_xlfn.MAXIFS(tblLecturas[Fecha],tblLecturas[Codigo],$A7),"") -> 46114 | M7: =IFERROR(_xlfn.MAXIFS(Lecturas!$C:$C,Lecturas!$B:$B,$A7,Lecturas!$C:$C,">0"),"") -> 8820 | N7: =IFERROR(_xlfn.MAXIFS(tblLecturas[Kilometraje],tblLecturas[Codigo],$A7,tblLecturas[Kilometraje],">0"),"") -> 261250 | O7: {=IFERROR(IF($I7="KM",LOOKUP(2,1/(Lecturas!$B:$B=$A7)/(Lecturas!$D:$D>0),Lecturas!$D:$D),LOOKUP(2,1/(Lecturas!$B:$B=$A7)/(Lecturas!$C:$C>0),Lecturas!$C:$C)),"")} -> 8820 | P7: =IFERROR(_xlfn.MAXIFS(tblMantenciones[Fecha],tblMantenciones[Codigo],tblMaestroEquipos[[#This Row],[Codigo]],tblMantenciones[EsPM],"Sí"),"") -> 46175 | Q7: =IF(_xlfn.MAXIFS(Mantenciones!$D:$D,Mantenciones!$B:$B,A7)=0,"Sin datos de mantención registrado",_xlfn.MAXIFS(Mantenciones!$D:$D,Mantenciones!$B:$B,A7)) -> 9025 | R7: =IFERROR(IF(_xlfn.MAXIFS(Mantenciones!$D:$D,Mantenciones!$B:$B,$A7,Mantenciones!$E:$E,"Sí",Mantenciones!$D:$D,">0")=0,"Sin datos de mantención registrado",_xlfn.MAXIFS(Mantenciones!$D:$D,Mantenciones!$B:$B,$A7,Mantenciones!$E:$E,"Sí",Mantenciones!$D:$D,">0")),"Sin datos de mantención registrado") -> 9025 | S7: =IFERROR(SUMIFS(tblMantenciones[Costo Mantencion CLP],tblMantenciones[Codigo],A7),0) -> 0 | T7: =IFERROR(SUMIFS(tblComprasPM[Costo PM CLP],tblComprasPM[Codigo],tblMaestroEquipos[[#This Row],[Codigo]]),0) -> 314826.62 | U7: =IFERROR(tblMaestroEquipos[[#This Row],[Costo Mantenciones CLP]]+tblMaestroEquipos[[#This Row],[Costo Compras PM CLP]],0) -> 314826.62 | V7: =IFERROR(_xlfn.XLOOKUP(tblMaestroEquipos[[#This Row],[Codigo]],tblEquipos[Codigo],tblEquipos[Estado Base]),"") -> Operativo | W7: =IF(OR(TRIM($V7)="Fuera de Servicio",TRIM($V7)="Fuera de servicio"),"FUERA DE SERVICIO",IF(OR(TRIM($V7)="Taller",TRIM($V7)="En taller",TRIM($V7)="EN TALLER"),"EN TALLER",IF($AD7="PENDIENTE","POR RECIBIR",IF(AND($Z7<>"",$AA7=""),"EN PROCESO",IF(AND(ISNUMBER($X7),$X7<0),"ATRASADA",IF(AND(ISNUMBER($X7),$X7<=30),"PRÓXIMA","AL DÍA")))))) -> AL DÍA | X7: =IF(OR(NOT(ISNUMBER(R7)),NOT(ISNUMBER(J7)),NOT(ISNUMBER(O7))),"", (R7+J7)-O7) -> 455 | Y7: =IFERROR(IF(OR(tblMaestroEquipos[[#This Row],[Estado Operacional]]="FUERA DE SERVICIO",tblMaestroEquipos[[#This Row],[Ultima Fecha Lectura]]="",tblMaestroEquipos[[#This Row],[Dias a Proxima Mantencion]]=""),"",tblMaestroEquipos[[#This Row],[Ultima Fecha Lectura]]+tblMaestroEquipos[[#This Row],[Dias a Proxima Mantencion]]),"") -> 46569 | Z7: =IFERROR(IF(_xlfn.MINIFS(tblComprasPM[Fecha],tblComprasPM[Codigo],tblMaestroEquipos[[#This Row],[Codigo]])=0,"",_xlfn.MINIFS(tblComprasPM[Fecha],tblComprasPM[Codigo],tblMaestroEquipos[[#This Row],[Codigo]])),"") -> 46069.447 | AA7: =IFERROR(IF(_xlfn.MAXIFS(tblBodega[Fecha],tblBodega[Codigo],tblMaestroEquipos[[#This Row],[Codigo]])=0,"",_xlfn.MAXIFS(tblBodega[Fecha],tblBodega[Codigo],tblMaestroEquipos[[#This Row],[Codigo]])),"") -> 46168 | AB7: =IFERROR(IF(OR(tblMaestroEquipos[[#This Row],[Fecha Compra PM]]="",tblMaestroEquipos[[#This Row],[Fecha Compra PM]]=0),"",IF(OR(tblMaestroEquipos[[#This Row],[Ultima Fecha PM]]="",tblMaestroEquipos[[#This Row],[Ultima Fecha PM]]=0),MAX(0,INT(TODAY())-INT(tblMaestroEquipos[[#This Row],[Fecha Compra PM]])),MAX(0,INT(tblMaestroEquipos[[#This Row],[Ultima Fecha PM]])-INT(tblMaestroEquipos[[#This Row],[Fecha Compra PM]])))),"") -> 106 | AC7: =IFERROR(IF(OR(tblMaestroEquipos[[#This Row],[Fecha Salida Bodega]]="",tblMaestroEquipos[[#This Row],[Fecha Salida Bodega]]=0),"",IF(OR(tblMaestroEquipos[[#This Row],[Ultima Fecha PM]]="",tblMaestroEquipos[[#This Row],[Ultima Fecha PM]]=0),MAX(0,INT(TODAY())-INT(tblMaestroEquipos[[#This Row],[Fecha Salida Bodega]])),MAX(0,INT(tblMaestroEquipos[[#This Row],[Ultima Fecha PM]])-INT(tblMaestroEquipos[[#This Row],[Fecha Salida Bodega]])))),"") -> 7 | AD7: =IF(tblMaestroEquipos[[#This Row],[Fecha Salida Bodega]]="","SIN SALIDA BODEGA",IF(OR(tblMaestroEquipos[[#This Row],[Ultima Fecha PM]]="",tblMaestroEquipos[[#This Row],[Ultima Fecha PM]]<tblMaestroEquipos[[#This Row],[Fecha Salida Bodega]]),"PENDIENTE","CERRADO")) -> CERRADO | AE7: =IF(TRIM(V7)="Fuera de servicio","FUERA DE SERVICIO", IF(OR(TRIM(V7)="Taller",TRIM(V7)="En taller"),"EN TALLER", IF(W7="ATRASADO","ATRASADO", IF(W7="EN PROCESO","EN PROCESO", IF(W7="PRÓXIMO","PRÓXIMO", "OPERATIVO"))))) -> OPERATIVO | AF7: =IF($AE7="ATRASADA",IF($X7<=-15,"CRÍTICA","ALTA"),IF($AE7="PRÓXIMA","MEDIA",IF(OR($AE7="EN PROCESO",$AE7="POR RECIBIR"),"SEGUIMIENTO",IF($AE7="FUERA DE SERVICIO","NO APLICA","BAJA")))) -> BAJA | AG7: =IF($AE7="FUERA DE SERVICIO","No programar compra",IF($AE7="CERRADO","Cerrar ciclo y preparar siguiente PM",IF($AE7="EN PROCESO","Hacer seguimiento al taller y cerrar report",IF($AE7="POR RECIBIR","Acelerar recepción de repuestos",IF($AE7="ATRASADA","Comprar kit PM y coordinar ejecución",IF($AE7="PRÓXIMA","Planificar compra preventiva","Monitorear próximo vencimiento")))))) -> Monitorear próximo vencimiento | AH7: =IF(AND(OR($AE7="ATRASADA",$AE7="PRÓXIMA"),$Z7="",$AA7=""),1,0) -> 0 | AI7: =IF(OR($AH7=0,$Y7=""),"",SUMPRODUCT(($AH$4:$AH$242=1)*(($Y$4:$Y$242<$Y7)+(($Y$4:$Y$242=$Y7)*(ROW($Y$4:$Y$242)<=ROW()))))) | AJ7: =IF(W7="ATRASADA",1,IF(W7="EN PROCESO",2,IF(W7="POR RECIBIR",3,99))) -> 99
A8: CD-105 | B8: Camión Tolva | C8: Camiones de Ruta | D8: Man | E8: TGS 50480 | F8: 2018 | G8: =IFERROR(_xlfn.XLOOKUP($A8,tblEquipos[Codigo],tblEquipos[Ubicacion],""),"") -> Palmucho | H8: Jose Andaur | I8: =IFERROR(VLOOKUP(A8, Equipos!A:J, 9, FALSE), "") -> HORAS | J8: =IFERROR(VLOOKUP(A8, Equipos!A:J, 10, FALSE), "") -> 500 | K8: =IFERROR(IF($I8="KM",ROUND((_xlfn.MAXIFS(tblLecturas[Kilometraje],tblLecturas[Codigo],$A8)-_xlfn.MINIFS(tblLecturas[Kilometraje],tblLecturas[Codigo],$A8))/(MAX(1,_xlfn.MAXIFS(tblLecturas[Fecha],tblLecturas[Codigo],$A8)-_xlfn.MINIFS(tblLecturas[Fecha],tblLecturas[Codigo],$A8))),1),ROUND((_xlfn.MAXIFS(tblLecturas[Horometro],tblLecturas[Codigo],$A8)-_xlfn.MINIFS(tblLecturas[Horometro],tblLecturas[Codigo],$A8))/(MAX(1,_xlfn.MAXIFS(tblLecturas[Fecha],tblLecturas[Codigo],$A8)-_xlfn.MINIFS(tblLecturas[Fecha],tblLecturas[Codigo],$A8))),1)),"") -> 6.2 | L8: =IFERROR(_xlfn.MAXIFS(tblLecturas[Fecha],tblLecturas[Codigo],$A8),"") -> 46142 | M8: =IFERROR(_xlfn.MAXIFS(Lecturas!$C:$C,Lecturas!$B:$B,$A8,Lecturas!$C:$C,">0"),"") -> 10821 | N8: =IFERROR(_xlfn.MAXIFS(tblLecturas[Kilometraje],tblLecturas[Codigo],$A8,tblLecturas[Kilometraje],">0"),"") -> 262956 | O8: {=IFERROR(IF($I8="KM",LOOKUP(2,1/(Lecturas!$B:$B=$A8)/(Lecturas!$D:$D>0),Lecturas!$D:$D),LOOKUP(2,1/(Lecturas!$B:$B=$A8)/(Lecturas!$C:$C>0),Lecturas!$C:$C)),"")} -> 10821 | P8: =IFERROR(_xlfn.MAXIFS(tblMantenciones[Fecha],tblMantenciones[Codigo],tblMaestroEquipos[[#This Row],[Codigo]],tblMantenciones[EsPM],"Sí"),"") -> 46127 | Q8: =IF(_xlfn.MAXIFS(Mantenciones!$D:$D,Mantenciones!$B:$B,A8)=0,"Sin datos de mantención registrado",_xlfn.MAXIFS(Mantenciones!$D:$D,Mantenciones!$B:$B,A8)) -> 10738 | R8: =IFERROR(IF(_xlfn.MAXIFS(Mantenciones!$D:$D,Mantenciones!$B:$B,$A8,Mantenciones!$E:$E,"Sí",Mantenciones!$D:$D,">0")=0,"Sin datos de mantención registrado",_xlfn.MAXIFS(Mantenciones!$D:$D,Mantenciones!$B:$B,$A8,Mantenciones!$E:$E,"Sí",Mantenciones!$D:$D,">0")),"Sin datos de mantención registrado") -> 10738 | S8: =IFERROR(SUMIFS(tblMantenciones[Costo Mantencion CLP],tblMantenciones[Codigo],A8),0) -> 0 | T8: =IFERROR(SUMIFS(tblComprasPM[Costo PM CLP],tblComprasPM[Codigo],tblMaestroEquipos[[#This Row],[Codigo]]),0) -> 50277.864 | U8: =IFERROR(tblMaestroEquipos[[#This Row],[Costo Mantenciones CLP]]+tblMaestroEquipos[[#This Row],[Costo Compras PM CLP]],0) -> 50277.864 | V8: =IFERROR(_xlfn.XLOOKUP(tblMaestroEquipos[[#This Row],[Codigo]],tblEquipos[Codigo],tblEquipos[Estado Base]),"") -> Operativo | W8: =IF(OR(TRIM($V8)="Fuera de Servicio",TRIM($V8)="Fuera de servicio"),"FUERA DE SERVICIO",IF(OR(TRIM($V8)="Taller",TRIM($V8)="En taller",TRIM($V8)="EN TALLER"),"EN TALLER",IF($AD8="PENDIENTE","POR RECIBIR",IF(AND($Z8<>"",$AA8=""),"EN PROCESO",IF(AND(ISNUMBER($X8),$X8<0),"ATRASADA",IF(AND(ISNUMBER($X8),$X8<=30),"PRÓXIMA","AL DÍA")))))) -> AL DÍA | X8: =IF(OR(NOT(ISNUMBER(R8)),NOT(ISNUMBER(J8)),NOT(ISNUMBER(O8))),"", (R8+J8)-O8) -> 417 | Y8: =IFERROR(IF(OR(tblMaestroEquipos[[#This Row],[Estado Operacional]]="FUERA DE SERVICIO",tblMaestroEquipos[[#This Row],[Ultima Fecha Lectura]]="",tblMaestroEquipos[[#This Row],[Dias a Proxima Mantencion]]=""),"",tblMaestroEquipos[[#This Row],[Ultima Fecha Lectura]]+tblMaestroEquipos[[#This Row],[Dias a Proxima Mantencion]]),"") -> 46559 | Z8: =IFERROR(IF(_xlfn.MINIFS(tblComprasPM[Fecha],tblComprasPM[Codigo],tblMaestroEquipos[[#This Row],[Codigo]])=0,"",_xlfn.MINIFS(tblComprasPM[Fecha],tblComprasPM[Codigo],tblMaestroEquipos[[#This Row],[Codigo]])),"") -> 46069.447 | AA8: =IFERROR(IF(_xlfn.MAXIFS(tblBodega[Fecha],tblBodega[Codigo],tblMaestroEquipos[[#This Row],[Codigo]])=0,"",_xlfn.MAXIFS(tblBodega[Fecha],tblBodega[Codigo],tblMaestroEquipos[[#This Row],[Codigo]])),"") -> 46105 | AB8: =IFERROR(IF(OR(tblMaestroEquipos[[#This Row],[Fecha Compra PM]]="",tblMaestroEquipos[[#This Row],[Fecha Compra PM]]=0),"",IF(OR(tblMaestroEquipos[[#This Row],[Ultima Fecha PM]]="",tblMaestroEquipos[[#This Row],[Ultima Fecha PM]]=0),MAX(0,INT(TODAY())-INT(tblMaestroEquipos[[#This Row],[Fecha Compra PM]])),MAX(0,INT(tblMaestroEquipos[[#This Row],[Ultima Fecha PM]])-INT(tblMaestroEquipos[[#This Row],[Fecha Compra PM]])))),"") -> 58 | AC8: =IFERROR(IF(OR(tblMaestroEquipos[[#This Row],[Fecha Salida Bodega]]="",tblMaestroEquipos[[#This Row],[Fecha Salida Bodega]]=0),"",IF(OR(tblMaestroEquipos[[#This Row],[Ultima Fecha PM]]="",tblMaestroEquipos[[#This Row],[Ultima Fecha PM]]=0),MAX(0,INT(TODAY())-INT(tblMaestroEquipos[[#This Row],[Fecha Salida Bodega]])),MAX(0,INT(tblMaestroEquipos[[#This Row],[Ultima Fecha PM]])-INT(tblMaestroEquipos[[#This Row],[Fecha Salida Bodega]])))),"") -> 22 | AD8: =IF(tblMaestroEquipos[[#This Row],[Fecha Salida Bodega]]="","SIN SALIDA BODEGA",IF(OR(tblMaestroEquipos[[#This Row],[Ultima Fecha PM]]="",tblMaestroEquipos[[#This Row],[Ultima Fecha PM]]<tblMaestroEquipos[[#This Row],[Fecha Salida Bodega]]),"PENDIENTE","CERRADO")) -> CERRADO | AE8: =IF(TRIM(V8)="Fuera de servicio","FUERA DE SERVICIO", IF(OR(TRIM(V8)="Taller",TRIM(V8)="En taller"),"EN TALLER", IF(W8="ATRASADO","ATRASADO", IF(W8="EN PROCESO","EN PROCESO", IF(W8="PRÓXIMO","PRÓXIMO", "OPERATIVO"))))) -> OPERATIVO | AF8: =IF($AE8="ATRASADA",IF($X8<=-15,"CRÍTICA","ALTA"),IF($AE8="PRÓXIMA","MEDIA",IF(OR($AE8="EN PROCESO",$AE8="POR RECIBIR"),"SEGUIMIENTO",IF($AE8="FUERA DE SERVICIO","NO APLICA","BAJA")))) -> BAJA | AG8: =IF($AE8="FUERA DE SERVICIO","No programar compra",IF($AE8="CERRADO","Cerrar ciclo y preparar siguiente PM",IF($AE8="EN PROCESO","Hacer seguimiento al taller y cerrar report",IF($AE8="POR RECIBIR","Acelerar recepción de repuestos",IF($AE8="ATRASADA","Comprar kit PM y coordinar ejecución",IF($AE8="PRÓXIMA","Planificar compra preventiva","Monitorear próximo vencimiento")))))) -> Monitorear próximo vencimiento | AH8: =IF(AND(OR($AE8="ATRASADA",$AE8="PRÓXIMA"),$Z8="",$AA8=""),1,0) -> 0 | AI8: =IF(OR($AH8=0,$Y8=""),"",SUMPRODUCT(($AH$4:$AH$242=1)*(($Y$4:$Y$242<$Y8)+(($Y$4:$Y$242=$Y8)*(ROW($Y$4:$Y$242)<=ROW()))))) | AJ8: =IF(W8="ATRASADA",1,IF(W8="EN PROCESO",2,IF(W8="POR RECIBIR",3,99))) -> 99
A9: CD-106 | B9: Camión Tolva | C9: Camiones de Ruta | D9: Man | E9: TGS 50480 | F9: 2019 | G9: =IFERROR(_xlfn.XLOOKUP($A9,tblEquipos[Codigo],tblEquipos[Ubicacion],""),"") -> Emergencias Curico | H9: Eugenio Hormazabal | I9: =IFERROR(VLOOKUP(A9, Equipos!A:J, 9, FALSE), "") -> HORAS | J9: =IFERROR(VLOOKUP(A9, Equipos!A:J, 10, FALSE), "") -> 500 | K9: =IFERROR(IF($I9="KM",ROUND((_xlfn.MAXIFS(tblLecturas[Kilometraje],tblLecturas[Codigo],$A9)-_xlfn.MINIFS(tblLecturas[Kilometraje],tblLecturas[Codigo],$A9))/(MAX(1,_xlfn.MAXIFS(tblLecturas[Fecha],tblLecturas[Codigo],$A9)-_xlfn.MINIFS(tblLecturas[Fecha],tblLecturas[Codigo],$A9))),1),ROUND((_xlfn.MAXIFS(tblLecturas[Horometro],tblLecturas[Codigo],$A9)-_xlfn.MINIFS(tblLecturas[Horometro],tblLecturas[Codigo],$A9))/(MAX(1,_xlfn.MAXIFS(tblLecturas[Fecha],tblLecturas[Codigo],$A9)-_xlfn.MINIFS(tblLecturas[Fecha],tblLecturas[Codigo],$A9))),1)),"") -> 2.2 | L9: =IFERROR(_xlfn.MAXIFS(tblLecturas[Fecha],tblLecturas[Codigo],$A9),"") -> 46105 | M9: =IFERROR(_xlfn.MAXIFS(Lecturas!$C:$C,Lecturas!$B:$B,$A9,Lecturas!$C:$C,">0"),"") -> 8345 | N9: =IFERROR(_xlfn.MAXIFS(tblLecturas[Kilometraje],tblLecturas[Codigo],$A9,tblLecturas[Kilometraje],">0"),"") -> 250115 | O9: {=IFERROR(IF($I9="KM",LOOKUP(2,1/(Lecturas!$B:$B=$A9)/(Lecturas!$D:$D>0),Lecturas!$D:$D),LOOKUP(2,1/(Lecturas!$B:$B=$A9)/(Lecturas!$C:$C>0),Lecturas!$C:$C)),"")} -> 8221 | P9: =IFERROR(_xlfn.MAXIFS(tblMantenciones[Fecha],tblMantenciones[Codigo],tblMaestroEquipos[[#This Row],[Codigo]],tblMantenciones[EsPM],"Sí"),"") -> 46044 | Q9: =IF(_xlfn.MAXIFS(Mantenciones!$D:$D,Mantenciones!$B:$B,A9)=0,"Sin datos de mantención registrado",_xlfn.MAXIFS(Mantenciones!$D:$D,Mantenciones!$B:$B,A9)) -> 8319 | R9: =IFERROR(IF(_xlfn.MAXIFS(Mantenciones!$D:$D,Mantenciones!$B:$B,$A9,Mantenciones!$E:$E,"Sí",Mantenciones!$D:$D,">0")=0,"Sin datos de mantención registrado",_xlfn.MAXIFS(Mantenciones!$D:$D,Mantenciones!$B:$B,$A9,Mantenciones!$E:$E,"Sí",Mantenciones!$D:$D,">0")),"Sin datos de mantención registrado") -> 8319 | S9: =IFERROR(SUMIFS(tblMantenciones[Costo Mantencion CLP],tblMantenciones[Codigo],A9),0) -> 0 | T9: =IFERROR(SUMIFS(tblComprasPM[Costo PM CLP],tblComprasPM[Codigo],tblMaestroEquipos[[#This Row],[Codigo]]),0) -> 49130.81 | U9: =IFERROR(tblMaestroEquipos[[#This Row],[Costo Mantenciones CLP]]+tblMaestroEquipos[[#This Row],[Costo Compras PM CLP]],0) -> 49130.81 | V9: =IFERROR(_xlfn.XLOOKUP(tblMaestroEquipos[[#This Row],[Codigo]],tblEquipos[Codigo],tblEquipos[Estado Base]),"") -> Operativo | W9: =IF(OR(TRIM($V9)="Fuera de Servicio",TRIM($V9)="Fuera de servicio"),"FUERA DE SERVICIO",IF(OR(TRIM($V9)="Taller",TRIM($V9)="En taller",TRIM($V9)="EN TALLER"),"EN TALLER",IF($AD9="PENDIENTE","POR RECIBIR",IF(AND($Z9<>"",$AA9=""),"EN PROCESO",IF(AND(ISNUMBER($X9),$X9<0),"ATRASADA",IF(AND(ISNUMBER($X9),$X9<=30),"PRÓXIMA","AL DÍA")))))) -> AL DÍA | X9: =IF(OR(NOT(ISNUMBER(R9)),NOT(ISNUMBER(J9)),NOT(ISNUMBER(O9))),"", (R9+J9)-O9) -> 598 | Y9: =IFERROR(IF(OR(tblMaestroEquipos[[#This Row],[Estado Operacional]]="FUERA DE SERVICIO",tblMaestroEquipos[[#This Row],[Ultima Fecha Lectura]]="",tblMaestroEquipos[[#This Row],[Dias a Proxima Mantencion]]=""),"",tblMaestroEquipos[[#This Row],[Ultima Fecha Lectura]]+tblMaestroEquipos[[#This Row],[Dias a Proxima Mantencion]]),"") -> 46703 | Z9: =IFERROR(IF(_xlfn.MINIFS(tblComprasPM[Fecha],tblComprasPM[Codigo],tblMaestroEquipos[[#This Row],[Codigo]])=0,"",_xlfn.MINIFS(tblComprasPM[Fecha],tblComprasPM[Codigo],tblMaestroEquipos[[#This Row],[Codigo]])),"") -> 46069.447 | AA9: =IFERROR(IF(_xlfn.MAXIFS(tblBodega[Fecha],tblBodega[Codigo],tblMaestroEquipos[[#This Row],[Codigo]])=0,"",_xlfn.MAXIFS(tblBodega[Fecha],tblBodega[Codigo],tblMaestroEquipos[[#This Row],[Codigo]])),"") -> 46044 | AB9: =IFERROR(IF(OR(tblMaestroEquipos[[#This Row],[Fecha Compra PM]]="",tblMaestroEquipos[[#This Row],[Fecha Compra PM]]=0),"",IF(OR(tblMaestroEquipos[[#This Row],[Ultima Fecha PM]]="",tblMaestroEquipos[[#This Row],[Ultima Fecha PM]]=0),MAX(0,INT(TODAY())-INT(tblMaestroEquipos[[#This Row],[Fecha Compra PM]])),MAX(0,INT(tblMaestroEquipos[[#This Row],[Ultima Fecha PM]])-INT(tblMaestroEquipos[[#This Row],[Fecha Compra PM]])))),"") -> 0 | AC9: =IFERROR(IF(OR(tblMaestroEquipos[[#This Row],[Fecha Salida Bodega]]="",tblMaestroEquipos[[#This Row],[Fecha Salida Bodega]]=0),"",IF(OR(tblMaestroEquipos[[#This Row],[Ultima Fecha PM]]="",tblMaestroEquipos[[#This Row],[Ultima Fecha PM]]=0),MAX(0,INT(TODAY())-INT(tblMaestroEquipos[[#This Row],[Fecha Salida Bodega]])),MAX(0,INT(tblMaestroEquipos[[#This Row],[Ultima Fecha PM]])-INT(tblMaestroEquipos[[#This Row],[Fecha Salida Bodega]])))),"") -> 0 | AD9: =IF(tblMaestroEquipos[[#This Row],[Fecha Salida Bodega]]="","SIN SALIDA BODEGA",IF(OR(tblMaestroEquipos[[#This Row],[Ultima Fecha PM]]="",tblMaestroEquipos[[#This Row],[Ultima Fecha PM]]<tblMaestroEquipos[[#This Row],[Fecha Salida Bodega]]),"PENDIENTE","CERRADO")) -> CERRADO | AE9: =IF(TRIM(V9)="Fuera de servicio","FUERA DE SERVICIO", IF(OR(TRIM(V9)="Taller",TRIM(V9)="En taller"),"EN TALLER", IF(W9="ATRASADO","ATRASADO", IF(W9="EN PROCESO","EN PROCESO", IF(W9="PRÓXIMO","PRÓXIMO", "OPERATIVO"))))) -> OPERATIVO | AF9: =IF($AE9="ATRASADA",IF($X9<=-15,"CRÍTICA","ALTA"),IF($AE9="PRÓXIMA","MEDIA",IF(OR($AE9="EN PROCESO",$AE9="POR RECIBIR"),"SEGUIMIENTO",IF($AE9="FUERA DE SERVICIO","NO APLICA","BAJA")))) -> BAJA | AG9: =IF($AE9="FUERA DE SERVICIO","No programar compra",IF($AE9="CERRADO","Cerrar ciclo y preparar siguiente PM",IF($AE9="EN PROCESO","Hacer seguimiento al taller y cerrar report",IF($AE9="POR RECIBIR","Acelerar recepción de repuestos",IF($AE9="ATRASADA","Comprar kit PM y coordinar ejecución",IF($AE9="PRÓXIMA","Planificar compra preventiva","Monitorear próximo vencimiento")))))) -> Monitorear próximo vencimiento | AH9: =IF(AND(OR($AE9="ATRASADA",$AE9="PRÓXIMA"),$Z9="",$AA9=""),1,0) -> 0 | AI9: =IF(OR($AH9=0,$Y9=""),"",SUMPRODUCT(($AH$4:$AH$242=1)*(($Y$4:$Y$242<$Y9)+(($Y$4:$Y$242=$Y9)*(ROW($Y$4:$Y$242)<=ROW()))))) | AJ9: =IF(W9="ATRASADA",1,IF(W9="EN PROCESO",2,IF(W9="POR RECIBIR",3,99))) -> 99
A10: CD-107 | B10: Camión Tolva | C10: Camiones de Ruta | D10: Man | E10: TGS 50480 | F10: 2019 | G10: =IFERROR(_xlfn.XLOOKUP($A10,tblEquipos[Codigo],tblEquipos[Ubicacion],""),"") -> Taller | H10: Cesar Vergara | I10: =IFERROR(VLOOKUP(A10, Equipos!A:J, 9, FALSE), "") -> HORAS | J10: =IFERROR(VLOOKUP(A10, Equipos!A:J, 10, FALSE), "") -> 500 | K10: =IFERROR(IF($I10="KM",ROUND((_xlfn.MAXIFS(tblLecturas[Kilometraje],tblLecturas[Codigo],$A10)-_xlfn.MINIFS(tblLecturas[Kilometraje],tblLecturas[Codigo],$A10))/(MAX(1,_xlfn.MAXIFS(tblLecturas[Fecha],tblLecturas[Codigo],$A10)-_xlfn.MINIFS(tblLecturas[Fecha],tblLecturas[Codigo],$A10))),1),ROUND((_xlfn.MAXIFS(tblLecturas[Horometro],tblLecturas[Codigo],$A10)-_xlfn.MINIFS(tblLecturas[Horometro],tblLecturas[Codigo],$A10))/(MAX(1,_xlfn.MAXIFS(tblLecturas[Fecha],tblLecturas[Codigo],$A10)-_xlfn.MINIFS(tblLecturas[Fecha],tblLecturas[Codigo],$A10))),1)),"") -> 3.8 | L10: =IFERROR(_xlfn.MAXIFS(tblLecturas[Fecha],tblLecturas[Codigo],$A10),"") -> 46092 | M10: =IFERROR(_xlfn.MAXIFS(Lecturas!$C:$C,Lecturas!$B:$B,$A10,Lecturas!$C:$C,">0"),"") -> 10923 | N10: =IFERROR(_xlfn.MAXIFS(tblLecturas[Kilometraje],tblLecturas[Codigo],$A10,tblLecturas[Kilometraje],">0"),"") -> 0 | O10: {=IFERROR(IF($I10="KM",LOOKUP(2,1/(Lecturas!$B:$B=$A10)/(Lecturas!$D:$D>0),Lecturas!$D:$D),LOOKUP(2,1/(Lecturas!$B:$B=$A10)/(Lecturas!$C:$C>0),Lecturas!$C:$C)),"")} -> 10863 | P10: =IFERROR(_xlfn.MAXIFS(tblMantenciones[Fecha],tblMantenciones[Codigo],tblMaestroEquipos[[#This Row],[Codigo]],tblMantenciones[EsPM],"Sí"),"") -> 46181 | Q10: =IF(_xlfn.MAXIFS(Mantenciones!$D:$D,Mantenciones!$B:$B,A10)=0,"Sin datos de mantención registrado",_xlfn.MAXIFS(Mantenciones!$D:$D,Mantenciones!$B:$B,A10)) -> 10974 | R10: =IFERROR(IF(_xlfn.MAXIFS(Mantenciones!$D:$D,Mantenciones!$B:$B,$A10,Mantenciones!$E:$E,"Sí",Mantenciones!$D:$D,">0")=0,"Sin datos de mantención registrado",_xlfn.MAXIFS(Mantenciones!$D:$D,Mantenciones!$B:$B,$A10,Mantenciones!$E:$E,"Sí",Mantenciones!$D:$D,">0")),"Sin datos de mantención registrado") -> 10974 | S10: =IFERROR(SUMIFS(tblMantenciones[Costo Mantencion CLP],tblMantenciones[Codigo],A10),0) -> 0 | T10: =IFERROR(SUMIFS(tblComprasPM[Costo PM CLP],tblComprasPM[Codigo],tblMaestroEquipos[[#This Row],[Codigo]]),0) -> 275874.6 | U10: =IFERROR(tblMaestroEquipos[[#This Row],[Costo Mantenciones CLP]]+tblMaestroEquipos[[#This Row],[Costo Compras PM CLP]],0) -> 275874.6 | V10: =IFERROR(_xlfn.XLOOKUP(tblMaestroEquipos[[#This Row],[Codigo]],tblEquipos[Codigo],tblEquipos[Estado Base]),"") -> Operativo | W10: =IF(OR(TRIM($V10)="Fuera de Servicio",TRIM($V10)="Fuera de servicio"),"FUERA DE SERVICIO",IF(OR(TRIM($V10)="Taller",TRIM($V10)="En taller",TRIM($V10)="EN TALLER"),"EN TALLER",IF($AD10="PENDIENTE","POR RECIBIR",IF(AND($Z10<>"",$AA10=""),"EN PROCESO",IF(AND(ISNUMBER($X10),$X10<0),"ATRASADA",IF(AND(ISNUMBER($X10),$X10<=30),"PRÓXIMA","AL DÍA")))))) -> AL DÍA | X10: =IF(OR(NOT(ISNUMBER(R10)),NOT(ISNUMBER(J10)),NOT(ISNUMBER(O10))),"", (R10+J10)-O10) -> 611 | Y10: =IFERROR(IF(OR(tblMaestroEquipos[[#This Row],[Estado Operacional]]="FUERA DE SERVICIO",tblMaestroEquipos[[#This Row],[Ultima Fecha Lectura]]="",tblMaestroEquipos[[#This Row],[Dias a Proxima Mantencion]]=""),"",tblMaestroEquipos[[#This Row],[Ultima Fecha Lectura]]+tblMaestroEquipos[[#This Row],[Dias a Proxima Mantencion]]),"") -> 46703 | Z10: =IFERROR(IF(_xlfn.MINIFS(tblComprasPM[Fecha],tblComprasPM[Codigo],tblMaestroEquipos[[#This Row],[Codigo]])=0,"",_xlfn.MINIFS(tblComprasPM[Fecha],tblComprasPM[Codigo],tblMaestroEquipos[[#This Row],[Codigo]])),"") -> 46069.447 | AA10: =IFERROR(IF(_xlfn.MAXIFS(tblBodega[Fecha],tblBodega[Codigo],tblMaestroEquipos[[#This Row],[Codigo]])=0,"",_xlfn.MAXIFS(tblBodega[Fecha],tblBodega[Codigo],tblMaestroEquipos[[#This Row],[Codigo]])),"") -> 46179 | AB10: =IFERROR(IF(OR(tblMaestroEquipos[[#This Row],[Fecha Compra PM]]="",tblMaestroEquipos[[#This Row],[Fecha Compra PM]]=0),"",IF(OR(tblMaestroEquipos[[#This Row],[Ultima Fecha PM]]="",tblMaestroEquipos[[#This Row],[Ultima Fecha PM]]=0),MAX(0,INT(TODAY())-INT(tblMaestroEquipos[[#This Row],[Fecha Compra PM]])),MAX(0,INT(tblMaestroEquipos[[#This Row],[Ultima Fecha PM]])-INT(tblMaestroEquipos[[#This Row],[Fecha Compra PM]])))),"") -> 112 | AC10: =IFERROR(IF(OR(tblMaestroEquipos[[#This Row],[Fecha Salida Bodega]]="",tblMaestroEquipos[[#This Row],[Fecha Salida Bodega]]=0),"",IF(OR(tblMaestroEquipos[[#This Row],[Ultima Fecha PM]]="",tblMaestroEquipos[[#This Row],[Ultima Fecha PM]]=0),MAX(0,INT(TODAY())-INT(tblMaestroEquipos[[#This Row],[Fecha Salida Bodega]])),MAX(0,INT(tblMaestroEquipos[[#This Row],[Ultima Fecha PM]])-INT(tblMaestroEquipos[[#This Row],[Fecha Salida Bodega]])))),"") -> 2 | AD10: =IF(tblMaestroEquipos[[#This Row],[Fecha Salida Bodega]]="","SIN SALIDA BODEGA",IF(OR(tblMaestroEquipos[[#This Row],[Ultima Fecha PM]]="",tblMaestroEquipos[[#This Row],[Ultima Fecha PM]]<tblMaestroEquipos[[#This Row],[Fecha Salida Bodega]]),"PENDIENTE","CERRADO")) -> CERRADO | AE10: =IF(TRIM(V10)="Fuera de servicio","FUERA DE SERVICIO", IF(OR(TRIM(V10)="Taller",TRIM(V10)="En taller"),"EN TALLER", IF(W10="ATRASADO","ATRASADO", IF(W10="EN PROCESO","EN PROCESO", IF(W10="PRÓXIMO","PRÓXIMO", "OPERATIVO"))))) -> OPERATIVO | AF10: =IF($AE10="ATRASADA",IF($X10<=-15,"CRÍTICA","ALTA"),IF($AE10="PRÓXIMA","MEDIA",IF(OR($AE10="EN PROCESO",$AE10="POR RECIBIR"),"SEGUIMIENTO",IF($AE10="FUERA DE SERVICIO","NO APLICA","BAJA")))) -> BAJA | AG10: =IF($AE10="FUERA DE SERVICIO","No programar compra",IF($AE10="CERRADO","Cerrar ciclo y preparar siguiente PM",IF($AE10="EN PROCESO","Hacer seguimiento al taller y cerrar report",IF($AE10="POR RECIBIR","Acelerar recepción de repuestos",IF($AE10="ATRASADA","Comprar kit PM y coordinar ejecución",IF($AE10="PRÓXIMA","Planificar compra preventiva","Monitorear próximo vencimiento")))))) -> Monitorear próximo vencimiento | AH10: =IF(AND(OR($AE10="ATRASADA",$AE10="PRÓXIMA"),$Z10="",$AA10=""),1,0) -> 0 | AI10: =IF(OR($AH10=0,$Y10=""),"",SUMPRODUCT(($AH$4:$AH$242=1)*(($Y$4:$Y$242<$Y10)+(($Y$4:$Y$242=$Y10)*(ROW($Y$4:$Y$242)<=ROW()))))) | AJ10: =IF(W10="ATRASADA",1,IF(W10="EN PROCESO",2,IF(W10="POR RECIBIR",3,99))) -> 99
A11: CD-108 | B11: Camión Slurry | C11: Camiones de Ruta | D11: International | E11: 7600 | F11: 2008 | G11: =IFERROR(_xlfn.XLOOKUP($A11,tblEquipos[Codigo],tblEquipos[Ubicacion],""),"") -> Palmucho | H11: Ivo Garrido | I11: =IFERROR(VLOOKUP(A11, Equipos!A:J, 9, FALSE), "") -> HORAS | J11: =IFERROR(VLOOKUP(A11, Equipos!A:J, 10, FALSE), "") -> 250 | K11: =IFERROR(IF($I11="KM",ROUND((_xlfn.MAXIFS(tblLecturas[Kilometraje],tblLecturas[Codigo],$A11)-_xlfn.MINIFS(tblLecturas[Kilometraje],tblLecturas[Codigo],$A11))/(MAX(1,_xlfn.MAXIFS(tblLecturas[Fecha],tblLecturas[Codigo],$A11)-_xlfn.MINIFS(tblLecturas[Fecha],tblLecturas[Codigo],$A11))),1),ROUND((_xlfn.MAXIFS(tblLecturas[Horometro],tblLecturas[Codigo],$A11)-_xlfn.MINIFS(tblLecturas[Horometro],tblLecturas[Codigo],$A11))/(MAX(1,_xlfn.MAXIFS(tblLecturas[Fecha],tblLecturas[Codigo],$A11)-_xlfn.MINIFS(tblLecturas[Fecha],tblLecturas[Codigo],$A11))),1)),"") -> 137.2 | L11: =IFERROR(_xlfn.MAXIFS(tblLecturas[Fecha],tblLecturas[Codigo],$A11),"") -> 46133 | M11: =IFERROR(_xlfn.MAXIFS(Lecturas!$C:$C,Lecturas!$B:$B,$A11,Lecturas!$C:$C,">0"),"") -> 9884 | N11: =IFERROR(_xlfn.MAXIFS(tblLecturas[Kilometraje],tblLecturas[Codigo],$A11,tblLecturas[Kilometraje],">0"),"") -> 98639 | O11: {=IFERROR(IF($I11="KM",LOOKUP(2,1/(Lecturas!$B:$B=$A11)/(Lecturas!$D:$D>0),Lecturas!$D:$D),LOOKUP(2,1/(Lecturas!$B:$B=$A11)/(Lecturas!$C:$C>0),Lecturas!$C:$C)),"")} -> 145 | P11: =IFERROR(_xlfn.MAXIFS(tblMantenciones[Fecha],tblMantenciones[Codigo],tblMaestroEquipos[[#This Row],[Codigo]],tblMantenciones[EsPM],"Sí"),"") -> 45015 | Q11: =IF(_xlfn.MAXIFS(Mantenciones!$D:$D,Mantenciones!$B:$B,A11)=0,"Sin datos de mantención registrado",_xlfn.MAXIFS(Mantenciones!$D:$D,Mantenciones!$B:$B,A11)) -> Sin datos de mantención registrado | R11: =IFERROR(IF(_xlfn.MAXIFS(Mantenciones!$D:$D,Mantenciones!$B:$B,$A11,Mantenciones!$E:$E,"Sí",Mantenciones!$D:$D,">0")=0,"Sin datos de mantención registrado",_xlfn.MAXIFS(Mantenciones!$D:$D,Mantenciones!$B:$B,$A11,Mantenciones!$E:$E,"Sí",Mantenciones!$D:$D,">0")),"Sin datos de mantención registrado") -> Sin datos de mantención registrado | S11: =IFERROR(SUMIFS(tblMantenciones[Costo Mantencion CLP],tblMantenciones[Codigo],A11),0) -> 0 | T11: =IFERROR(SUMIFS(tblComprasPM[Costo PM CLP],tblComprasPM[Codigo],tblMaestroEquipos[[#This Row],[Codigo]]),0) -> 251368.46 | U11: =IFERROR(tblMaestroEquipos[[#This Row],[Costo Mantenciones CLP]]+tblMaestroEquipos[[#This Row],[Costo Compras PM CLP]],0) -> 251368.46 | V11: =IFERROR(_xlfn.XLOOKUP(tblMaestroEquipos[[#This Row],[Codigo]],tblEquipos[Codigo],tblEquipos[Estado Base]),"") -> Operativo | W11: =IF(OR(TRIM($V11)="Fuera de Servicio",TRIM($V11)="Fuera de servicio"),"FUERA DE SERVICIO",IF(OR(TRIM($V11)="Taller",TRIM($V11)="En taller",TRIM($V11)="EN TALLER"),"EN TALLER",IF($AD11="PENDIENTE","POR RECIBIR",IF(AND($Z11<>"",$AA11=""),"EN PROCESO",IF(AND(ISNUMBER($X11),$X11<0),"ATRASADA",IF(AND(ISNUMBER($X11),$X11<=30),"PRÓXIMA","AL DÍA")))))) -> EN PROCESO | X11: =IF(OR(NOT(ISNUMBER(R11)),NOT(ISNUMBER(J11)),NOT(ISNUMBER(O11))),"", (R11+J11)-O11) | Y11: =IFERROR(IF(OR(tblMaestroEquipos[[#This Row],[Estado Operacional]]="FUERA DE SERVICIO",tblMaestroEquipos[[#This Row],[Ultima Fecha Lectura]]="",tblMaestroEquipos[[#This Row],[Dias a Proxima Mantencion]]=""),"",tblMaestroEquipos[[#This Row],[Ultima Fecha Lectura]]+tblMaestroEquipos[[#This Row],[Dias a Proxima Mantencion]]),"") | Z11: =IFERROR(IF(_xlfn.MINIFS(tblComprasPM[Fecha],tblComprasPM[Codigo],tblMaestroEquipos[[#This Row],[Codigo]])=0,"",_xlfn.MINIFS(tblComprasPM[Fecha],tblComprasPM[Codigo],tblMaestroEquipos[[#This Row],[Codigo]])),"") -> 46128.371 | AA11: =IFERROR(IF(_xlfn.MAXIFS(tblBodega[Fecha],tblBodega[Codigo],tblMaestroEquipos[[#This Row],[Codigo]])=0,"",_xlfn.MAXIFS(tblBodega[Fecha],tblBodega[Codigo],tblMaestroEquipos[[#This Row],[Codigo]])),"") | AB11: =IFERROR(IF(OR(tblMaestroEquipos[[#This Row],[Fecha Compra PM]]="",tblMaestroEquipos[[#This Row],[Fecha Compra PM]]=0),"",IF(OR(tblMaestroEquipos[[#This Row],[Ultima Fecha PM]]="",tblMaestroEquipos[[#This Row],[Ultima Fecha PM]]=0),MAX(0,INT(TODAY())-INT(tblMaestroEquipos[[#This Row],[Fecha Compra PM]])),MAX(0,INT(tblMaestroEquipos[[#This Row],[Ultima Fecha PM]])-INT(tblMaestroEquipos[[#This Row],[Fecha Compra PM]])))),"") -> 0 | AC11: =IFERROR(IF(OR(tblMaestroEquipos[[#This Row],[Fecha Salida Bodega]]="",tblMaestroEquipos[[#This Row],[Fecha Salida Bodega]]=0),"",IF(OR(tblMaestroEquipos[[#This Row],[Ultima Fecha PM]]="",tblMaestroEquipos[[#This Row],[Ultima Fecha PM]]=0),MAX(0,INT(TODAY())-INT(tblMaestroEquipos[[#This Row],[Fecha Salida Bodega]])),MAX(0,INT(tblMaestroEquipos[[#This Row],[Ultima Fecha PM]])-INT(tblMaestroEquipos[[#This Row],[Fecha Salida Bodega]])))),"") | AD11: =IF(tblMaestroEquipos[[#This Row],[Fecha Salida Bodega]]="","SIN SALIDA BODEGA",IF(OR(tblMaestroEquipos[[#This Row],[Ultima Fecha PM]]="",tblMaestroEquipos[[#This Row],[Ultima Fecha PM]]<tblMaestroEquipos[[#This Row],[Fecha Salida Bodega]]),"PENDIENTE","CERRADO")) -> SIN SALIDA BODEGA | AE11: =IF(TRIM(V11)="Fuera de servicio","FUERA DE SERVICIO", IF(OR(TRIM(V11)="Taller",TRIM(V11)="En taller"),"EN TALLER", IF(W11="ATRASADO","ATRASADO", IF(W11="EN PROCESO","EN PROCESO", IF(W11="PRÓXIMO","PRÓXIMO", "OPERATIVO"))))) -> EN PROCESO | AF11: =IF($AE11="ATRASADA",IF($X11<=-15,"CRÍTICA","ALTA"),IF($AE11="PRÓXIMA","MEDIA",IF(OR($AE11="EN PROCESO",$AE11="POR RECIBIR"),"SEGUIMIENTO",IF($AE11="FUERA DE SERVICIO","NO APLICA","BAJA")))) -> SEGUIMIENTO | AG11: =IF($AE11="FUERA DE SERVICIO","No programar compra",IF($AE11="CERRADO","Cerrar ciclo y preparar siguiente PM",IF($AE11="EN PROCESO","Hacer seguimiento al taller y cerrar report",IF($AE11="POR RECIBIR","Acelerar recepción de repuestos",IF($AE11="ATRASADA","Comprar kit PM y coordinar ejecución",IF($AE11="PRÓXIMA","Planificar compra preventiva","Monitorear próximo vencimiento")))))) -> Hacer seguimiento al taller y cerrar report | AH11: =IF(AND(OR($AE11="ATRASADA",$AE11="PRÓXIMA"),$Z11="",$AA11=""),1,0) -> 0 | AI11: =IF(OR($AH11=0,$Y11=""),"",SUMPRODUCT(($AH$4:$AH$242=1)*(($Y$4:$Y$242<$Y11)+(($Y$4:$Y$242=$Y11)*(ROW($Y$4:$Y$242)<=ROW()))))) | AJ11: =IF(W11="ATRASADA",1,IF(W11="EN PROCESO",2,IF(W11="POR RECIBIR",3,99))) -> 2
A12: CD-109 | B12: Camión Plano | C12: Camiones de Ruta | D12: Hino | E12: XZU 6.5 DCAB | F12: 2012 | G12: =IFERROR(_xlfn.XLOOKUP($A12,tblEquipos[Codigo],tblEquipos[Ubicacion],""),"") -> Palmucho | H12: Washinton Sanzana | I12: =IFERROR(VLOOKUP(A12, Equipos!A:J, 9, FALSE), "") -> KM | J12: =IFERROR(VLOOKUP(A12, Equipos!A:J, 10, FALSE), "") -> 10000 | K12: =IFERROR(IF($I12="KM",ROUND((_xlfn.MAXIFS(tblLecturas[Kilometraje],tblLecturas[Codigo],$A12)-_xlfn.MINIFS(tblLecturas[Kilometraje],tblLecturas[Codigo],$A12))/(MAX(1,_xlfn.MAXIFS(tblLecturas[Fecha],tblLecturas[Codigo],$A12)-_xlfn.MINIFS(tblLecturas[Fecha],tblLecturas[Codigo],$A12))),1),ROUND((_xlfn.MAXIFS(tblLecturas[Horometro],tblLecturas[Codigo],$A12)-_xlfn.MINIFS(tblLecturas[Horometro],tblLecturas[Codigo],$A12))/(MAX(1,_xlfn.MAXIFS(tblLecturas[Fecha],tblLecturas[Codigo],$A12)-_xlfn.MINIFS(tblLecturas[Fecha],tblLecturas[Codigo],$A12))),1)),"") -> 40.4 | L12: =IFERROR(_xlfn.MAXIFS(tblLecturas[Fecha],tblLecturas[Codigo],$A12),"") -> 46189 | M12: =IFERROR(_xlfn.MAXIFS(Lecturas!$C:$C,Lecturas!$B:$B,$A12,Lecturas!$C:$C,">0"),"") -> 0 | N12: =IFERROR(_xlfn.MAXIFS(tblLecturas[Kilometraje],tblLecturas[Codigo],$A12,tblLecturas[Kilometraje],">0"),"") -> 193745 | O12: {=IFERROR(IF($I12="KM",LOOKUP(2,1/(Lecturas!$B:$B=$A12)/(Lecturas!$D:$D>0),Lecturas!$D:$D),LOOKUP(2,1/(Lecturas!$B:$B=$A12)/(Lecturas!$C:$C>0),Lecturas!$C:$C)),"")} -> 193745 | P12: =IFERROR(_xlfn.MAXIFS(tblMantenciones[Fecha],tblMantenciones[Codigo],tblMaestroEquipos[[#This Row],[Codigo]],tblMantenciones[EsPM],"Sí"),"") -> 46093 | Q12: =IF(_xlfn.MAXIFS(Mantenciones!$D:$D,Mantenciones!$B:$B,A12)=0,"Sin datos de mantención registrado",_xlfn.MAXIFS(Mantenciones!$D:$D,Mantenciones!$B:$B,A12)) -> 189849 | R12: =IFERROR(IF(_xlfn.MAXIFS(Mantenciones!$D:$D,Mantenciones!$B:$B,$A12,Mantenciones!$E:$E,"Sí",Mantenciones!$D:$D,">0")=0,"Sin datos de mantención registrado",_xlfn.MAXIFS(Mantenciones!$D:$D,Mantenciones!$B:$B,$A12,Mantenciones!$E:$E,"Sí",Mantenciones!$D:$D,">0")),"Sin datos de mantención registrado") -> 189849 | S12: =IFERROR(SUMIFS(tblMantenciones[Costo Mantencion CLP],tblMantenciones[Codigo],A12),0) -> 0 | T12: =IFERROR(SUMIFS(tblComprasPM[Costo PM CLP],tblComprasPM[Codigo],tblMaestroEquipos[[#This Row],[Codigo]]),0) -> 186232.99 | U12: =IFERROR(tblMaestroEquipos[[#This Row],[Costo Mantenciones CLP]]+tblMaestroEquipos[[#This Row],[Costo Compras PM CLP]],0) -> 186232.99 | V12: =IFERROR(_xlfn.XLOOKUP(tblMaestroEquipos[[#This Row],[Codigo]],tblEquipos[Codigo],tblEquipos[Estado Base]),"") -> Operativo | W12: =IF(OR(TRIM($V12)="Fuera de Servicio",TRIM($V12)="Fuera de servicio"),"FUERA DE SERVICIO",IF(OR(TRIM($V12)="Taller",TRIM($V12)="En taller",TRIM($V12)="EN TALLER"),"EN TALLER",IF($AD12="PENDIENTE","POR RECIBIR",IF(AND($Z12<>"",$AA12=""),"EN PROCESO",IF(AND(ISNUMBER($X12),$X12<0),"ATRASADA",IF(AND(ISNUMBER($X12),$X12<=30),"PRÓXIMA","AL DÍA")))))) -> AL DÍA | X12: =IF(OR(NOT(ISNUMBER(R12)),NOT(ISNUMBER(J12)),NOT(ISNUMBER(O12))),"", (R12+J12)-O12) -> 6104 | Y12: =IFERROR(IF(OR(tblMaestroEquipos[[#This Row],[Estado Operacional]]="FUERA DE SERVICIO",tblMaestroEquipos[[#This Row],[Ultima Fecha Lectura]]="",tblMaestroEquipos[[#This Row],[Dias a Proxima Mantencion]]=""),"",tblMaestroEquipos[[#This Row],[Ultima Fecha Lectura]]+tblMaestroEquipos[[#This Row],[Dias a Proxima Mantencion]]),"") -> 52293 | Z12: =IFERROR(IF(_xlfn.MINIFS(tblComprasPM[Fecha],tblComprasPM[Codigo],tblMaestroEquipos[[#This Row],[Codigo]])=0,"",_xlfn.MINIFS(tblComprasPM[Fecha],tblComprasPM[Codigo],tblMaestroEquipos[[#This Row],[Codigo]])),"") -> 46093.486 | AA12: =IFERROR(IF(_xlfn.MAXIFS(tblBodega[Fecha],tblBodega[Codigo],tblMaestroEquipos[[#This Row],[Codigo]])=0,"",_xlfn.MAXIFS(tblBodega[Fecha],tblBodega[Codigo],tblMaestroEquipos[[#This Row],[Codigo]])),"") -> 46091 | AB12: =IFERROR(IF(OR(tblMaestroEquipos[[#This Row],[Fecha Compra PM]]="",tblMaestroEquipos[[#This Row],[Fecha Compra PM]]=0),"",IF(OR(tblMaestroEquipos[[#This Row],[Ultima Fecha PM]]="",tblMaestroEquipos[[#This Row],[Ultima Fecha PM]]=0),MAX(0,INT(TODAY())-INT(tblMaestroEquipos[[#This Row],[Fecha Compra PM]])),MAX(0,INT(tblMaestroEquipos[[#This Row],[Ultima Fecha PM]])-INT(tblMaestroEquipos[[#This Row],[Fecha Compra PM]])))),"") -> 0 | AC12: =IFERROR(IF(OR(tblMaestroEquipos[[#This Row],[Fecha Salida Bodega]]="",tblMaestroEquipos[[#This Row],[Fecha Salida Bodega]]=0),"",IF(OR(tblMaestroEquipos[[#This Row],[Ultima Fecha PM]]="",tblMaestroEquipos[[#This Row],[Ultima Fecha PM]]=0),MAX(0,INT(TODAY())-INT(tblMaestroEquipos[[#This Row],[Fecha Salida Bodega]])),MAX(0,INT(tblMaestroEquipos[[#This Row],[Ultima Fecha PM]])-INT(tblMaestroEquipos[[#This Row],[Fecha Salida Bodega]])))),"") -> 2 | AD12: =IF(tblMaestroEquipos[[#This Row],[Fecha Salida Bodega]]="","SIN SALIDA BODEGA",IF(OR(tblMaestroEquipos[[#This Row],[Ultima Fecha PM]]="",tblMaestroEquipos[[#This Row],[Ultima Fecha PM]]<tblMaestroEquipos[[#This Row],[Fecha Salida Bodega]]),"PENDIENTE","CERRADO")) -> CERRADO | AE12: =IF(TRIM(V12)="Fuera de servicio","FUERA DE SERVICIO", IF(OR(TRIM(V12)="Taller",TRIM(V12)="En taller"),"EN TALLER", IF(W12="ATRASADO","ATRASADO", IF(W12="EN PROCESO","EN PROCESO", IF(W12="PRÓXIMO","PRÓXIMO", "OPERATIVO"))))) -> OPERATIVO | AF12: =IF($AE12="ATRASADA",IF($X12<=-15,"CRÍTICA","ALTA"),IF($AE12="PRÓXIMA","MEDIA",IF(OR($AE12="EN PROCESO",$AE12="POR RECIBIR"),"SEGUIMIENTO",IF($AE12="FUERA DE SERVICIO","NO APLICA","BAJA")))) -> BAJA | AG12: =IF($AE12="FUERA DE SERVICIO","No programar compra",IF($AE12="CERRADO","Cerrar ciclo y preparar siguiente PM",IF($AE12="EN PROCESO","Hacer seguimiento al taller y cerrar report",IF($AE12="POR RECIBIR","Acelerar recepción de repuestos",IF($AE12="ATRASADA","Comprar kit PM y coordinar ejecución",IF($AE12="PRÓXIMA","Planificar compra preventiva","Monitorear próximo vencimiento")))))) -> Monitorear próximo vencimiento | AH12: =IF(AND(OR($AE12="ATRASADA",$AE12="PRÓXIMA"),$Z12="",$AA12=""),1,0) -> 0 | AI12: =IF(OR($AH12=0,$Y12=""),"",SUMPRODUCT(($AH$4:$AH$242=1)*(($Y$4:$Y$242<$Y12)+(($Y$4:$Y$242=$Y12)*(ROW($Y$4:$Y$242)<=ROW()))))) | AJ12: =IF(W12="ATRASADA",1,IF(W12="EN PROCESO",2,IF(W12="POR RECIBIR",3,99))) -> 99
A13: CD-110 | B13: Camión Plano | C13: Camiones de Ruta | D13: Jac | E13: Urban HFC1050K | F13: 2015 | G13: =IFERROR(_xlfn.XLOOKUP($A13,tblEquipos[Codigo],tblEquipos[Ubicacion],""),"") -> Cobquecura | H13: No identificado | I13: =IFERROR(VLOOKUP(A13, Equipos!A:J, 9, FALSE), "") -> HORAS | J13: =IFERROR(VLOOKUP(A13, Equipos!A:J, 10, FALSE), "") -> 250 | K13: =IFERROR(IF($I13="KM",ROUND((_xlfn.MAXIFS(tblLecturas[Kilometraje],tblLecturas[Codigo],$A13)-_xlfn.MINIFS(tblLecturas[Kilometraje],tblLecturas[Codigo],$A13))/(MAX(1,_xlfn.MAXIFS(tblLecturas[Fecha],tblLecturas[Codigo],$A13)-_xlfn.MINIFS(tblLecturas[Fecha],tblLecturas[Codigo],$A13))),1),ROUND((_xlfn.MAXIFS(tblLecturas[Horometro],tblLecturas[Codigo],$A13)-_xlfn.MINIFS(tblLecturas[Horometro],tblLecturas[Codigo],$A13))/(MAX(1,_xlfn.MAXIFS(tblLecturas[Fecha],tblLecturas[Codigo],$A13)-_xlfn.MINIFS(tblLecturas[Fecha],tblLecturas[Codigo],$A13))),1)),"") -> 0 | L13: =IFERROR(_xlfn.MAXIFS(tblLecturas[Fecha],tblLecturas[Codigo],$A13),"") -> 46111 | M13: =IFERROR(_xlfn.MAXIFS(Lecturas!$C:$C,Lecturas!$B:$B,$A13,Lecturas!$C:$C,">0"),"") -> 0 | N13: =IFERROR(_xlfn.MAXIFS(tblLecturas[Kilometraje],tblLecturas[Codigo],$A13,tblLecturas[Kilometraje],">0"),"") -> 275886 | O13: {=IFERROR(IF($I13="KM",LOOKUP(2,1/(Lecturas!$B:$B=$A13)/(Lecturas!$D:$D>0),Lecturas!$D:$D),LOOKUP(2,1/(Lecturas!$B:$B=$A13)/(Lecturas!$C:$C>0),Lecturas!$C:$C)),"")} | P13: =IFERROR(_xlfn.MAXIFS(tblMantenciones[Fecha],tblMantenciones[Codigo],tblMaestroEquipos[[#This Row],[Codigo]],tblMantenciones[EsPM],"Sí"),"") -> 46105 | Q13: =IF(_xlfn.MAXIFS(Mantenciones!$D:$D,Mantenciones!$B:$B,A13)=0,"Sin datos de mantención registrado",_xlfn.MAXIFS(Mantenciones!$D:$D,Mantenciones!$B:$B,A13)) -> 275548 | R13: =IFERROR(IF(_xlfn.MAXIFS(Mantenciones!$D:$D,Mantenciones!$B:$B,$A13,Mantenciones!$E:$E,"Sí",Mantenciones!$D:$D,">0")=0,"Sin datos de mantención registrado",_xlfn.MAXIFS(Mantenciones!$D:$D,Mantenciones!$B:$B,$A13,Mantenciones!$E:$E,"Sí",Mantenciones!$D:$D,">0")),"Sin datos de mantención registrado") -> 275548 | S13: =IFERROR(SUMIFS(tblMantenciones[Costo Mantencion CLP],tblMantenciones[Codigo],A13),0) -> 0 | T13: =IFERROR(SUMIFS(tblComprasPM[Costo PM CLP],tblComprasPM[Codigo],tblMaestroEquipos[[#This Row],[Codigo]]),0) -> 21301 | U13: =IFERROR(tblMaestroEquipos[[#This Row],[Costo Mantenciones CLP]]+tblMaestroEquipos[[#This Row],[Costo Compras PM CLP]],0) -> 21301 | V13: =IFERROR(_xlfn.XLOOKUP(tblMaestroEquipos[[#This Row],[Codigo]],tblEquipos[Codigo],tblEquipos[Estado Base]),"") -> Operativo | W13: =IF(OR(TRIM($V13)="Fuera de Servicio",TRIM($V13)="Fuera de servicio"),"FUERA DE SERVICIO",IF(OR(TRIM($V13)="Taller",TRIM($V13)="En taller",TRIM($V13)="EN TALLER"),"EN TALLER",IF($AD13="PENDIENTE","POR RECIBIR",IF(AND($Z13<>"",$AA13=""),"EN PROCESO",IF(AND(ISNUMBER($X13),$X13<0),"ATRASADA",IF(AND(ISNUMBER($X13),$X13<=30),"PRÓXIMA","AL DÍA")))))) -> AL DÍA | X13: =IF(OR(NOT(ISNUMBER(R13)),NOT(ISNUMBER(J13)),NOT(ISNUMBER(O13))),"", (R13+J13)-O13) | Y13: =IFERROR(IF(OR(tblMaestroEquipos[[#This Row],[Estado Operacional]]="FUERA DE SERVICIO",tblMaestroEquipos[[#This Row],[Ultima Fecha Lectura]]="",tblMaestroEquipos[[#This Row],[Dias a Proxima Mantencion]]=""),"",tblMaestroEquipos[[#This Row],[Ultima Fecha Lectura]]+tblMaestroEquipos[[#This Row],[Dias a Proxima Mantencion]]),"") | Z13: =IFERROR(IF(_xlfn.MINIFS(tblComprasPM[Fecha],tblComprasPM[Codigo],tblMaestroEquipos[[#This Row],[Codigo]])=0,"",_xlfn.MINIFS(tblComprasPM[Fecha],tblComprasPM[Codigo],tblMaestroEquipos[[#This Row],[Codigo]])),"") -> 46076.364 | AA13: =IFERROR(IF(_xlfn.MAXIFS(tblBodega[Fecha],tblBodega[Codigo],tblMaestroEquipos[[#This Row],[Codigo]])=0,"",_xlfn.MAXIFS(tblBodega[Fecha],tblBodega[Codigo],tblMaestroEquipos[[#This Row],[Codigo]])),"") -> 46101 | AB13: =IFERROR(IF(OR(tblMaestroEquipos[[#This Row],[Fecha Compra PM]]="",tblMaestroEquipos[[#This Row],[Fecha Compra PM]]=0),"",IF(OR(tblMaestroEquipos[[#This Row],[Ultima Fecha PM]]="",tblMaestroEquipos[[#This Row],[Ultima Fecha PM]]=0),MAX(0,INT(TODAY())-INT(tblMaestroEquipos[[#This Row],[Fecha Compra PM]])),MAX(0,INT(tblMaestroEquipos[[#This Row],[Ultima Fecha PM]])-INT(tblMaestroEquipos[[#This Row],[Fecha Compra PM]])))),"") -> 29 | AC13: =IFERROR(IF(OR(tblMaestroEquipos[[#This Row],[Fecha Salida Bodega]]="",tblMaestroEquipos[[#This Row],[Fecha Salida Bodega]]=0),"",IF(OR(tblMaestroEquipos[[#This Row],[Ultima Fecha PM]]="",tblMaestroEquipos[[#This Row],[Ultima Fecha PM]]=0),MAX(0,INT(TODAY())-INT(tblMaestroEquipos[[#This Row],[Fecha Salida Bodega]])),MAX(0,INT(tblMaestroEquipos[[#This Row],[Ultima Fecha PM]])-INT(tblMaestroEquipos[[#This Row],[Fecha Salida Bodega]])))),"") -> 4 | AD13: =IF(tblMaestroEquipos[[#This Row],[Fecha Salida Bodega]]="","SIN SALIDA BODEGA",IF(OR(tblMaestroEquipos[[#This Row],[Ultima Fecha PM]]="",tblMaestroEquipos[[#This Row],[Ultima Fecha PM]]<tblMaestroEquipos[[#This Row],[Fecha Salida Bodega]]),"PENDIENTE","CERRADO")) -> CERRADO | AE13: =IF(TRIM(V13)="Fuera de servicio","FUERA DE SERVICIO", IF(OR(TRIM(V13)="Taller",TRIM(V13)="En taller"),"EN TALLER", IF(W13="ATRASADO","ATRASADO", IF(W13="EN PROCESO","EN PROCESO", IF(W13="PRÓXIMO","PRÓXIMO", "OPERATIVO"))))) -> OPERATIVO | AF13: =IF($AE13="ATRASADA",IF($X13<=-15,"CRÍTICA","ALTA"),IF($AE13="PRÓXIMA","MEDIA",IF(OR($AE13="EN PROCESO",$AE13="POR RECIBIR"),"SEGUIMIENTO",IF($AE13="FUERA DE SERVICIO","NO APLICA","BAJA")))) -> BAJA | AG13: =IF($AE13="FUERA DE SERVICIO","No programar compra",IF($AE13="CERRADO","Cerrar ciclo y preparar siguiente PM",IF($AE13="EN PROCESO","Hacer seguimiento al taller y cerrar report",IF($AE13="POR RECIBIR","Acelerar recepción de repuestos",IF($AE13="ATRASADA","Comprar kit PM y coordinar ejecución",IF($AE13="PRÓXIMA","Planificar compra preventiva","Monitorear próximo vencimiento")))))) -> Monitorear próximo vencimiento | AH13: =IF(AND(OR($AE13="ATRASADA",$AE13="PRÓXIMA"),$Z13="",$AA13=""),1,0) -> 0 | AI13: =IF(OR($AH13=0,$Y13=""),"",SUMPRODUCT(($AH$4:$AH$242=1)*(($Y$4:$Y$242<$Y13)+(($Y$4:$Y$242=$Y13)*(ROW($Y$4:$Y$242)<=ROW()))))) | AJ13: =IF(W13="ATRASADA",1,IF(W13="EN PROCESO",2,IF(W13="POR RECIBIR",3,99))) -> 99
A14: CD-111 | B14: Camión Plano | C14: Camiones de Ruta | D14: Mercedes Benz | E14: Atego 1315 48 | F14: 2007 | G14: =IFERROR(_xlfn.XLOOKUP($A14,tblEquipos[Codigo],tblEquipos[Ubicacion],""),"") -> TALLER | H14: Sin asignar | I14: =IFERROR(VLOOKUP(A14, Equipos!A:J, 9, FALSE), "") -> HORAS | J14: =IFERROR(VLOOKUP(A14, Equipos!A:J, 10, FALSE), "") -> 250 | K14: =IFERROR(IF($I14="KM",ROUND((_xlfn.MAXIFS(tblLecturas[Kilometraje],tblLecturas[Codigo],$A14)-_xlfn.MINIFS(tblLecturas[Kilometraje],tblLecturas[Codigo],$A14))/(MAX(1,_xlfn.MAXIFS(tblLecturas[Fecha],tblLecturas[Codigo],$A14)-_xlfn.MINIFS(tblLecturas[Fecha],tblLecturas[Codigo],$A14))),1),ROUND((_xlfn.MAXIFS(tblLecturas[Horometro],tblLecturas[Codigo],$A14)-_xlfn.MINIFS(tblLecturas[Horometro],tblLecturas[Codigo],$A14))/(MAX(1,_xlfn.MAXIFS(tblLecturas[Fecha],tblLecturas[Codigo],$A14)-_xlfn.MINIFS(tblLecturas[Fecha],tblLecturas[Codigo],$A14))),1)),"") -> 0 | L14: =IFERROR(_xlfn.MAXIFS(tblLecturas[Fecha],tblLecturas[Codigo],$A14),"") -> 0 | M14: =IFERROR(_xlfn.MAXIFS(Lecturas!$C:$C,Lecturas!$B:$B,$A14,Lecturas!$C:$C,">0"),"") -> 0 | N14: =IFERROR(_xlfn.MAXIFS(tblLecturas[Kilometraje],tblLecturas[Codigo],$A14,tblLecturas[Kilometraje],">0"),"") -> 0 | O14: {=IFERROR(IF($I14="KM",LOOKUP(2,1/(Lecturas!$B:$B=$A14)/(Lecturas!$D:$D>0),Lecturas!$D:$D),LOOKUP(2,1/(Lecturas!$B:$B=$A14)/(Lecturas!$C:$C>0),Lecturas!$C:$C)),"")} | P14: =IFERROR(_xlfn.MAXIFS(tblMantenciones[Fecha],tblMantenciones[Codigo],tblMaestroEquipos[[#This Row],[Codigo]],tblMantenciones[EsPM],"Sí"),"") -> 0 | Q14: =IF(_xlfn.MAXIFS(Mantenciones!$D:$D,Mantenciones!$B:$B,A14)=0,"Sin datos de mantención registrado",_xlfn.MAXIFS(Mantenciones!$D:$D,Mantenciones!$B:$B,A14)) -> Sin datos de mantención registrado | R14: =IFERROR(IF(_xlfn.MAXIFS(Mantenciones!$D:$D,Mantenciones!$B:$B,$A14,Mantenciones!$E:$E,"Sí",Mantenciones!$D:$D,">0")=0,"Sin datos de mantención registrado",_xlfn.MAXIFS(Mantenciones!$D:$D,Mantenciones!$B:$B,$A14,Mantenciones!$E:$E,"Sí",Mantenciones!$D:$D,">0")),"Sin datos de mantención registrado") -> Sin datos de mantención registrado | S14: =IFERROR(SUMIFS(tblMantenciones[Costo Mantencion CLP],tblMantenciones[Codigo],A14),0) -> 0 | T14: =IFERROR(SUMIFS(tblComprasPM[Costo PM CLP],tblComprasPM[Codigo],tblMaestroEquipos[[#This Row],[Codigo]]),0) -> 0 | U14: =IFERROR(tblMaestroEquipos[[#This Row],[Costo Mantenciones CLP]]+tblMaestroEquipos[[#This Row],[Costo Compras PM CLP]],0) -> 0 | V14: =IFERROR(_xlfn.XLOOKUP(tblMaestroEquipos[[#This Row],[Codigo]],tblEquipos[Codigo],tblEquipos[Estado Base]),"") -> Fuera de Servicio | W14: =IF(OR(TRIM($V14)="Fuera de Servicio",TRIM($V14)="Fuera de servicio"),"FUERA DE SERVICIO",IF(OR(TRIM($V14)="Taller",TRIM($V14)="En taller",TRIM($V14)="EN TALLER"),"EN TALLER",IF($AD14="PENDIENTE","POR RECIBIR",IF(AND($Z14<>"",$AA14=""),"EN PROCESO",IF(AND(ISNUMBER($X14),$X14<0),"ATRASADA",IF(AND(ISNUMBER($X14),$X14<=30),"PRÓXIMA","AL DÍA")))))) -> FUERA DE SERVICIO | X14: =IF(OR(NOT(ISNUMBER(R14)),NOT(ISNUMBER(J14)),NOT(ISNUMBER(O14))),"", (R14+J14)-O14) | Y14: =IFERROR(IF(OR(tblMaestroEquipos[[#This Row],[Estado Operacional]]="FUERA DE SERVICIO",tblMaestroEquipos[[#This Row],[Ultima Fecha Lectura]]="",tblMaestroEquipos[[#This Row],[Dias a Proxima Mantencion]]=""),"",tblMaestroEquipos[[#This Row],[Ultima Fecha Lectura]]+tblMaestroEquipos[[#This Row],[Dias a Proxima Mantencion]]),"") | Z14: =IFERROR(IF(_xlfn.MINIFS(tblComprasPM[Fecha],tblComprasPM[Codigo],tblMaestroEquipos[[#This Row],[Codigo]])=0,"",_xlfn.MINIFS(tblComprasPM[Fecha],tblComprasPM[Codigo],tblMaestroEquipos[[#This Row],[Codigo]])),"") | AA14: =IFERROR(IF(_xlfn.MAXIFS(tblBodega[Fecha],tblBodega[Codigo],tblMaestroEquipos[[#This Row],[Codigo]])=0,"",_xlfn.MAXIFS(tblBodega[Fecha],tblBodega[Codigo],tblMaestroEquipos[[#This Row],[Codigo]])),"") | AB14: =IFERROR(IF(OR(tblMaestroEquipos[[#This Row],[Fecha Compra PM]]="",tblMaestroEquipos[[#This Row],[Fecha Compra PM]]=0),"",IF(OR(tblMaestroEquipos[[#This Row],[Ultima Fecha PM]]="",tblMaestroEquipos[[#This Row],[Ultima Fecha PM]]=0),MAX(0,INT(TODAY())-INT(tblMaestroEquipos[[#This Row],[Fecha Compra PM]])),MAX(0,INT(tblMaestroEquipos[[#This Row],[Ultima Fecha PM]])-INT(tblMaestroEquipos[[#This Row],[Fecha Compra PM]])))),"") | AC14: =IFERROR(IF(OR(tblMaestroEquipos[[#This Row],[Fecha Salida Bodega]]="",tblMaestroEquipos[[#This Row],[Fecha Salida Bodega]]=0),"",IF(OR(tblMaestroEquipos[[#This Row],[Ultima Fecha PM]]="",tblMaestroEquipos[[#This Row],[Ultima Fecha PM]]=0),MAX(0,INT(TODAY())-INT(tblMaestroEquipos[[#This Row],[Fecha Salida Bodega]])),MAX(0,INT(tblMaestroEquipos[[#This Row],[Ultima Fecha PM]])-INT(tblMaestroEquipos[[#This Row],[Fecha Salida Bodega]])))),"") | AD14: =IF(tblMaestroEquipos[[#This Row],[Fecha Salida Bodega]]="","SIN SALIDA BODEGA",IF(OR(tblMaestroEquipos[[#This Row],[Ultima Fecha PM]]="",tblMaestroEquipos[[#This Row],[Ultima Fecha PM]]<tblMaestroEquipos[[#This Row],[Fecha Salida Bodega]]),"PENDIENTE","CERRADO")) -> SIN SALIDA BODEGA | AE14: =IF(TRIM(V14)="Fuera de servicio","FUERA DE SERVICIO", IF(OR(TRIM(V14)="Taller",TRIM(V14)="En taller"),"EN TALLER", IF(W14="ATRASADO","ATRASADO", IF(W14="EN PROCESO","EN PROCESO", IF(W14="PRÓXIMO","PRÓXIMO", "OPERATIVO"))))) -> FUERA DE SERVICIO | AF14: =IF($AE14="ATRASADA",IF($X14<=-15,"CRÍTICA","ALTA"),IF($AE14="PRÓXIMA","MEDIA",IF(OR($AE14="EN PROCESO",$AE14="POR RECIBIR"),"SEGUIMIENTO",IF($AE14="FUERA DE SERVICIO","NO APLICA","BAJA")))) -> NO APLICA | AG14: =IF($AE14="FUERA DE SERVICIO","No programar compra",IF($AE14="CERRADO","Cerrar ciclo y preparar siguiente PM",IF($AE14="EN PROCESO","Hacer seguimiento al taller y cerrar report",IF($AE14="POR RECIBIR","Acelerar recepción de repuestos",IF($AE14="ATRASADA","Comprar kit PM y coordinar ejecución",IF($AE14="PRÓXIMA","Planificar compra preventiva","Monitorear próximo vencimiento")))))) -> No programar compra | AH14: =IF(AND(OR($AE14="ATRASADA",$AE14="PRÓXIMA"),$Z14="",$AA14=""),1,0) -> 0 | AI14: =IF(OR($AH14=0,$Y14=""),"",SUMPRODUCT(($AH$4:$AH$242=1)*(($Y$4:$Y$242<$Y14)+(($Y$4:$Y$242=$Y14)*(ROW($Y$4:$Y$242)<=ROW()))))) | AJ14: =IF(W14="ATRASADA",1,IF(W14="EN PROCESO",2,IF(W14="POR RECIBIR",3,99))) -> 99
A15: CD-112 | B15: Camión Pintura | C15: Camiones de Ruta | D15: No hay info | E15: No hay info | F15: No hay info | G15: =IFERROR(_xlfn.XLOOKUP($A15,tblEquipos[Codigo],tblEquipos[Ubicacion],""),"") -> TALLER | H15: Sin asignar | I15: =IFERROR(VLOOKUP(A15, Equipos!A:J, 9, FALSE), "") -> HORAS | J15: =IFERROR(VLOOKUP(A15, Equipos!A:J, 10, FALSE), "") -> 250 | K15: =IFERROR(IF($I15="KM",ROUND((_xlfn.MAXIFS(tblLecturas[Kilometraje],tblLecturas[Codigo],$A15)-_xlfn.MINIFS(tblLecturas[Kilometraje],tblLecturas[Codigo],$A15))/(MAX(1,_xlfn.MAXIFS(tblLecturas[Fecha],tblLecturas[Codigo],$A15)-_xlfn.MINIFS(tblLecturas[Fecha],tblLecturas[Codigo],$A15))),1),ROUND((_xlfn.MAXIFS(tblLecturas[Horometro],tblLecturas[Codigo],$A15)-_xlfn.MINIFS(tblLecturas[Horometro],tblLecturas[Codigo],$A15))/(MAX(1,_xlfn.MAXIFS(tblLecturas[Fecha],tblLecturas[Codigo],$A15)-_xlfn.MINIFS(tblLecturas[Fecha],tblLecturas[Codigo],$A15))),1)),"") -> 0 | L15: =IFERROR(_xlfn.MAXIFS(tblLecturas[Fecha],tblLecturas[Codigo],$A15),"") -> 0 | M15: =IFERROR(_xlfn.MAXIFS(Lecturas!$C:$C,Lecturas!$B:$B,$A15,Lecturas!$C:$C,">0"),"") -> 0 | N15: =IFERROR(_xlfn.MAXIFS(tblLecturas[Kilometraje],tblLecturas[Codigo],$A15,tblLecturas[Kilometraje],">0"),"") -> 0 | O15: {=IFERROR(IF($I15="KM",LOOKUP(2,1/(Lecturas!$B:$B=$A15)/(Lecturas!$D:$D>0),Lecturas!$D:$D),LOOKUP(2,1/(Lecturas!$B:$B=$A15)/(Lecturas!$C:$C>0),Lecturas!$C:$C)),"")} | P15: =IFERROR(_xlfn.MAXIFS(tblMantenciones[Fecha],tblMantenciones[Codigo],tblMaestroEquipos[[#This Row],[Codigo]],tblMantenciones[EsPM],"Sí"),"") -> 44455 | Q15: =IF(_xlfn.MAXIFS(Mantenciones!$D:$D,Mantenciones!$B:$B,A15)=0,"Sin datos de mantención registrado",_xlfn.MAXIFS(Mantenciones!$D:$D,Mantenciones!$B:$B,A15)) -> Sin datos de mantención registrado | R15: =IFERROR(IF(_xlfn.MAXIFS(Mantenciones!$D:$D,Mantenciones!$B:$B,$A15,Mantenciones!$E:$E,"Sí",Mantenciones!$D:$D,">0")=0,"Sin datos de mantención registrado",_xlfn.MAXIFS(Mantenciones!$D:$D,Mantenciones!$B:$B,$A15,Mantenciones!$E:$E,"Sí",Mantenciones!$D:$D,">0")),"Sin datos de mantención registrado") -> Sin datos de mantención registrado | S15: =IFERROR(SUMIFS(tblMantenciones[Costo Mantencion CLP],tblMantenciones[Codigo],A15),0) -> 0 | T15: =IFERROR(SUMIFS(tblComprasPM[Costo PM CLP],tblComprasPM[Codigo],tblMaestroEquipos[[#This Row],[Codigo]]),0) -> 0 | U15: =IFERROR(tblMaestroEquipos[[#This Row],[Costo Mantenciones CLP]]+tblMaestroEquipos[[#This Row],[Costo Compras PM CLP]],0) -> 0 | V15: =IFERROR(_xlfn.XLOOKUP(tblMaestroEquipos[[#This Row],[Codigo]],tblEquipos[Codigo],tblEquipos[Estado Base]),"") -> Fuera de Servicio | W15: =IF(OR(TRIM($V15)="Fuera de Servicio",TRIM($V15)="Fuera de servicio"),"FUERA DE SERVICIO",IF(OR(TRIM($V15)="Taller",TRIM($V15)="En taller",TRIM($V15)="EN TALLER"),"EN TALLER",IF($AD15="PENDIENTE","POR RECIBIR",IF(AND($Z15<>"",$AA15=""),"EN PROCESO",IF(AND(ISNUMBER($X15),$X15<0),"ATRASADA",IF(AND(ISNUMBER($X15),$X15<=30),"PRÓXIMA","AL DÍA")))))) -> FUERA DE SERVICIO | X15: =IF(OR(NOT(ISNUMBER(R15)),NOT(ISNUMBER(J15)),NOT(ISNUMBER(O15))),"", (R15+J15)-O15) | Y15: =IFERROR(IF(OR(tblMaestroEquipos[[#This Row],[Estado Operacional]]="FUERA DE SERVICIO",tblMaestroEquipos[[#This Row],[Ultima Fecha Lectura]]="",tblMaestroEquipos[[#This Row],[Dias a Proxima Mantencion]]=""),"",tblMaestroEquipos[[#This Row],[Ultima Fecha Lectura]]+tblMaestroEquipos[[#This Row],[Dias a Proxima Mantencion]]),"") | Z15: =IFERROR(IF(_xlfn.MINIFS(tblComprasPM[Fecha],tblComprasPM[Codigo],tblMaestroEquipos[[#This Row],[Codigo]])=0,"",_xlfn.MINIFS(tblComprasPM[Fecha],tblComprasPM[Codigo],tblMaestroEquipos[[#This Row],[Codigo]])),"") | AA15: =IFERROR(IF(_xlfn.MAXIFS(tblBodega[Fecha],tblBodega[Codigo],tblMaestroEquipos[[#This Row],[Codigo]])=0,"",_xlfn.MAXIFS(tblBodega[Fecha],tblBodega[Codigo],tblMaestroEquipos[[#This Row],[Codigo]])),"") | AB15: =IFERROR(IF(OR(tblMaestroEquipos[[#This Row],[Fecha Compra PM]]="",tblMaestroEquipos[[#This Row],[Fecha Compra PM]]=0),"",IF(OR(tblMaestroEquipos[[#This Row],[Ultima Fecha PM]]="",tblMaestroEquipos[[#This Row],[Ultima Fecha PM]]=0),MAX(0,INT(TODAY())-INT(tblMaestroEquipos[[#This Row],[Fecha Compra PM]])),MAX(0,INT(tblMaestroEquipos[[#This Row],[Ultima Fecha PM]])-INT(tblMaestroEquipos[[#This Row],[Fecha Compra PM]])))),"") | AC15: =IFERROR(IF(OR(tblMaestroEquipos[[#This Row],[Fecha Salida Bodega]]="",tblMaestroEquipos[[#This Row],[Fecha Salida Bodega]]=0),"",IF(OR(tblMaestroEquipos[[#This Row],[Ultima Fecha PM]]="",tblMaestroEquipos[[#This Row],[Ultima Fecha PM]]=0),MAX(0,INT(TODAY())-INT(tblMaestroEquipos[[#This Row],[Fecha Salida Bodega]])),MAX(0,INT(tblMaestroEquipos[[#This Row],[Ultima Fecha PM]])-INT(tblMaestroEquipos[[#This Row],[Fecha Salida Bodega]])))),"") | AD15: =IF(tblMaestroEquipos[[#This Row],[Fecha Salida Bodega]]="","SIN SALIDA BODEGA",IF(OR(tblMaestroEquipos[[#This Row],[Ultima Fecha PM]]="",tblMaestroEquipos[[#This Row],[Ultima Fecha PM]]<tblMaestroEquipos[[#This Row],[Fecha Salida Bodega]]),"PENDIENTE","CERRADO")) -> SIN SALIDA BODEGA | AE15: =IF(TRIM(V15)="Fuera de servicio","FUERA DE SERVICIO", IF(OR(TRIM(V15)="Taller",TRIM(V15)="En taller"),"EN TALLER", IF(W15="ATRASADO","ATRASADO", IF(W15="EN PROCESO","EN PROCESO", IF(W15="PRÓXIMO","PRÓXIMO", "OPERATIVO"))))) -> FUERA DE SERVICIO | AF15: =IF($AE15="ATRASADA",IF($X15<=-15,"CRÍTICA","ALTA"),IF($AE15="PRÓXIMA","MEDIA",IF(OR($AE15="EN PROCESO",$AE15="POR RECIBIR"),"SEGUIMIENTO",IF($AE15="FUERA DE SERVICIO","NO APLICA","BAJA")))) -> NO APLICA | AG15: =IF($AE15="FUERA DE SERVICIO","No programar compra",IF($AE15="CERRADO","Cerrar ciclo y preparar siguiente PM",IF($AE15="EN PROCESO","Hacer seguimiento al taller y cerrar report",IF($AE15="POR RECIBIR","Acelerar recepción de repuestos",IF($AE15="ATRASADA","Comprar kit PM y coordinar ejecución",IF($AE15="PRÓXIMA","Planificar compra preventiva","Monitorear próximo vencimiento")))))) -> No programar compra | AH15: =IF(AND(OR($AE15="ATRASADA",$AE15="PRÓXIMA"),$Z15="",$AA15=""),1,0) -> 0 | AI15: =IF(OR($AH15=0,$Y15=""),"",SUMPRODUCT(($AH$4:$AH$242=1)*(($Y$4:$Y$242<$Y15)+(($Y$4:$Y$242=$Y15)*(ROW($Y$4:$Y$242)<=ROW()))))) | AJ15: =IF(W15="ATRASADA",1,IF(W15="EN PROCESO",2,IF(W15="POR RECIBIR",3,99))) -> 99
A16: CD-113 | B16: Camión Imprimador | C16: Camiones de Ruta | D16: Volkswagen | E16: 17180M | F16: 2011 | G16: =IFERROR(_xlfn.XLOOKUP($A16,tblEquipos[Codigo],tblEquipos[Ubicacion],""),"") -> Quirihue | H16: Nector Muñoz | I16: =IFERROR(VLOOKUP(A16, Equipos!A:J, 9, FALSE), "") -> HORAS | J16: =IFERROR(VLOOKUP(A16, Equipos!A:J, 10, FALSE), "") -> 250 | K16: =IFERROR(IF($I16="KM",ROUND((_xlfn.MAXIFS(tblLecturas[Kilometraje],tblLecturas[Codigo],$A16)-_xlfn.MINIFS(tblLecturas[Kilometraje],tblLecturas[Codigo],$A16))/(MAX(1,_xlfn.MAXIFS(tblLecturas[Fecha],tblLecturas[Codigo],$A16)-_xlfn.MINIFS(tblLecturas[Fecha],tblLecturas[Codigo],$A16))),1),ROUND((_xlfn.MAXIFS(tblLecturas[Horometro],tblLecturas[Codigo],$A16)-_xlfn.MINIFS(tblLecturas[Horometro],tblLecturas[Codigo],$A16))/(MAX(1,_xlfn.MAXIFS(tblLecturas[Fecha],tblLecturas[Codigo],$A16)-_xlfn.MINIFS(tblLecturas[Fecha],tblLecturas[Codigo],$A16))),1)),"") -> 0 | L16: =IFERROR(_xlfn.MAXIFS(tblLecturas[Fecha],tblLecturas[Codigo],$A16),"") -> 46050 | M16: =IFERROR(_xlfn.MAXIFS(Lecturas!$C:$C,Lecturas!$B:$B,$A16,Lecturas!$C:$C,">0"),"") -> 0 | N16: =IFERROR(_xlfn.MAXIFS(tblLecturas[Kilometraje],tblLecturas[Codigo],$A16,tblLecturas[Kilometraje],">0"),"") -> 802920 | O16: {=IFERROR(IF($I16="KM",LOOKUP(2,1/(Lecturas!$B:$B=$A16)/(Lecturas!$D:$D>0),Lecturas!$D:$D),LOOKUP(2,1/(Lecturas!$B:$B=$A16)/(Lecturas!$C:$C>0),Lecturas!$C:$C)),"")} | P16: =IFERROR(_xlfn.MAXIFS(tblMantenciones[Fecha],tblMantenciones[Codigo],tblMaestroEquipos[[#This Row],[Codigo]],tblMantenciones[EsPM],"Sí"),"") -> 46167 | Q16: =IF(_xlfn.MAXIFS(Mantenciones!$D:$D,Mantenciones!$B:$B,A16)=0,"Sin datos de mantención registrado",_xlfn.MAXIFS(Mantenciones!$D:$D,Mantenciones!$B:$B,A16)) -> 802920 | R16: =IFERROR(IF(_xlfn.MAXIFS(Mantenciones!$D:$D,Mantenciones!$B:$B,$A16,Mantenciones!$E:$E,"Sí",Mantenciones!$D:$D,">0")=0,"Sin datos de mantención registrado",_xlfn.MAXIFS(Mantenciones!$D:$D,Mantenciones!$B:$B,$A16,Mantenciones!$E:$E,"Sí",Mantenciones!$D:$D,">0")),"Sin datos de mantención registrado") -> 802920 | S16: =IFERROR(SUMIFS(tblMantenciones[Costo Mantencion CLP],tblMantenciones[Codigo],A16),0) -> 0 | T16: =IFERROR(SUMIFS(tblComprasPM[Costo PM CLP],tblComprasPM[Codigo],tblMaestroEquipos[[#This Row],[Codigo]]),0) -> 209900.82 | U16: =IFERROR(tblMaestroEquipos[[#This Row],[Costo Mantenciones CLP]]+tblMaestroEquipos[[#This Row],[Costo Compras PM CLP]],0) -> 209900.82 | V16: =IFERROR(_xlfn.XLOOKUP(tblMaestroEquipos[[#This Row],[Codigo]],tblEquipos[Codigo],tblEquipos[Estado Base]),"") -> Operativo | W16: =IF(OR(TRIM($V16)="Fuera de Servicio",TRIM($V16)="Fuera de servicio"),"FUERA DE SERVICIO",IF(OR(TRIM($V16)="Taller",TRIM($V16)="En taller",TRIM($V16)="EN TALLER"),"EN TALLER",IF($AD16="PENDIENTE","POR RECIBIR",IF(AND($Z16<>"",$AA16=""),"EN PROCESO",IF(AND(ISNUMBER($X16),$X16<0),"ATRASADA",IF(AND(ISNUMBER($X16),$X16<=30),"PRÓXIMA","AL DÍA")))))) -> AL DÍA | X16: =IF(OR(NOT(ISNUMBER(R16)),NOT(ISNUMBER(J16)),NOT(ISNUMBER(O16))),"", (R16+J16)-O16) | Y16: =IFERROR(IF(OR(tblMaestroEquipos[[#This Row],[Estado Operacional]]="FUERA DE SERVICIO",tblMaestroEquipos[[#This Row],[Ultima Fecha Lectura]]="",tblMaestroEquipos[[#This Row],[Dias a Proxima Mantencion]]=""),"",tblMaestroEquipos[[#This Row],[Ultima Fecha Lectura]]+tblMaestroEquipos[[#This Row],[Dias a Proxima Mantencion]]),"") | Z16: =IFERROR(IF(_xlfn.MINIFS(tblComprasPM[Fecha],tblComprasPM[Codigo],tblMaestroEquipos[[#This Row],[Codigo]])=0,"",_xlfn.MINIFS(tblComprasPM[Fecha],tblComprasPM[Codigo],tblMaestroEquipos[[#This Row],[Codigo]])),"") -> 46079.691 | AA16: =IFERROR(IF(_xlfn.MAXIFS(tblBodega[Fecha],tblBodega[Codigo],tblMaestroEquipos[[#This Row],[Codigo]])=0,"",_xlfn.MAXIFS(tblBodega[Fecha],tblBodega[Codigo],tblMaestroEquipos[[#This Row],[Codigo]])),"") -> 46167 | AB16: =IFERROR(IF(OR(tblMaestroEquipos[[#This Row],[Fecha Compra PM]]="",tblMaestroEquipos[[#This Row],[Fecha Compra PM]]=0),"",IF(OR(tblMaestroEquipos[[#This Row],[Ultima Fecha PM]]="",tblMaestroEquipos[[#This Row],[Ultima Fecha PM]]=0),MAX(0,INT(TODAY())-INT(tblMaestroEquipos[[#This Row],[Fecha Compra PM]])),MAX(0,INT(tblMaestroEquipos[[#This Row],[Ultima Fecha PM]])-INT(tblMaestroEquipos[[#This Row],[Fecha Compra PM]])))),"") -> 88 | AC16: =IFERROR(IF(OR(tblMaestroEquipos[[#This Row],[Fecha Salida Bodega]]="",tblMaestroEquipos[[#This Row],[Fecha Salida Bodega]]=0),"",IF(OR(tblMaestroEquipos[[#This Row],[Ultima Fecha PM]]="",tblMaestroEquipos[[#This Row],[Ultima Fecha PM]]=0),MAX(0,INT(TODAY())-INT(tblMaestroEquipos[[#This Row],[Fecha Salida Bodega]])),MAX(0,INT(tblMaestroEquipos[[#This Row],[Ultima Fecha PM]])-INT(tblMaestroEquipos[[#This Row],[Fecha Salida Bodega]])))),"") -> 0 | AD16: =IF(tblMaestroEquipos[[#This Row],[Fecha Salida Bodega]]="","SIN SALIDA BODEGA",IF(OR(tblMaestroEquipos[[#This Row],[Ultima Fecha PM]]="",tblMaestroEquipos[[#This Row],[Ultima Fecha PM]]<tblMaestroEquipos[[#This Row],[Fecha Salida Bodega]]),"PENDIENTE","CERRADO")) -> CERRADO | AE16: =IF(TRIM(V16)="Fuera de servicio","FUERA DE SERVICIO", IF(OR(TRIM(V16)="Taller",TRIM(V16)="En taller"),"EN TALLER", IF(W16="ATRASADO","ATRASADO", IF(W16="EN PROCESO","EN PROCESO", IF(W16="PRÓXIMO","PRÓXIMO", "OPERATIVO"))))) -> OPERATIVO | AF16: =IF($AE16="ATRASADA",IF($X16<=-15,"CRÍTICA","ALTA"),IF($AE16="PRÓXIMA","MEDIA",IF(OR($AE16="EN PROCESO",$AE16="POR RECIBIR"),"SEGUIMIENTO",IF($AE16="FUERA DE SERVICIO","NO APLICA","BAJA")))) -> BAJA | AG16: =IF($AE16="FUERA DE SERVICIO","No programar compra",IF($AE16="CERRADO","Cerrar ciclo y preparar siguiente PM",IF($AE16="EN PROCESO","Hacer seguimiento al taller y cerrar report",IF($AE16="POR RECIBIR","Acelerar recepción de repuestos",IF($AE16="ATRASADA","Comprar kit PM y coordinar ejecución",IF($AE16="PRÓXIMA","Planificar compra preventiva","Monitorear próximo vencimiento")))))) -> Monitorear próximo vencimiento | AH16: =IF(AND(OR($AE16="ATRASADA",$AE16="PRÓXIMA"),$Z16="",$AA16=""),1,0) -> 0 | AI16: =IF(OR($AH16=0,$Y16=""),"",SUMPRODUCT(($AH$4:$AH$242=1)*(($Y$4:$Y$242<$Y16)+(($Y$4:$Y$242=$Y16)*(ROW($Y$4:$Y$242)<=ROW()))))) | AJ16: =IF(W16="ATRASADA",1,IF(W16="EN PROCESO",2,IF(W16="POR RECIBIR",3,99))) -> 99
A17: CD-114 | B17: Camión Imprimador | C17: Camiones de Ruta | D17: Freightliner | E17: M2 112 | F17: 1998 | G17: =IFERROR(_xlfn.XLOOKUP($A17,tblEquipos[Codigo],tblEquipos[Ubicacion],""),"") -> Palmucho | H17: Sin asignar | I17: =IFERROR(VLOOKUP(A17, Equipos!A:J, 9, FALSE), "") -> HORAS | J17: =IFERROR(VLOOKUP(A17, Equipos!A:J, 10, FALSE), "") -> 250 | K17: =IFERROR(IF($I17="KM",ROUND((_xlfn.MAXIFS(tblLecturas[Kilometraje],tblLecturas[Codigo],$A17)-_xlfn.MINIFS(tblLecturas[Kilometraje],tblLecturas[Codigo],$A17))/(MAX(1,_xlfn.MAXIFS(tblLecturas[Fecha],tblLecturas[Codigo],$A17)-_xlfn.MINIFS(tblLecturas[Fecha],tblLecturas[Codigo],$A17))),1),ROUND((_xlfn.MAXIFS(tblLecturas[Horometro],tblLecturas[Codigo],$A17)-_xlfn.MINIFS(tblLecturas[Horometro],tblLecturas[Codigo],$A17))/(MAX(1,_xlfn.MAXIFS(tblLecturas[Fecha],tblLecturas[Codigo],$A17)-_xlfn.MINIFS(tblLecturas[Fecha],tblLecturas[Codigo],$A17))),1)),"") -> 6.3 | L17: =IFERROR(_xlfn.MAXIFS(tblLecturas[Fecha],tblLecturas[Codigo],$A17),"") -> 46150 | M17: =IFERROR(_xlfn.MAXIFS(Lecturas!$C:$C,Lecturas!$B:$B,$A17,Lecturas!$C:$C,">0"),"") -> 4017 | N17: =IFERROR(_xlfn.MAXIFS(tblLecturas[Kilometraje],tblLecturas[Codigo],$A17,tblLecturas[Kilometraje],">0"),"") -> 0 | O17: {=IFERROR(IF($I17="KM",LOOKUP(2,1/(Lecturas!$B:$B=$A17)/(Lecturas!$D:$D>0),Lecturas!$D:$D),LOOKUP(2,1/(Lecturas!$B:$B=$A17)/(Lecturas!$C:$C>0),Lecturas!$C:$C)),"")} -> 4017 | P17: =IFERROR(_xlfn.MAXIFS(tblMantenciones[Fecha],tblMantenciones[Codigo],tblMaestroEquipos[[#This Row],[Codigo]],tblMantenciones[EsPM],"Sí"),"") -> 46147 | Q17: =IF(_xlfn.MAXIFS(Mantenciones!$D:$D,Mantenciones!$B:$B,A17)=0,"Sin datos de mantención registrado",_xlfn.MAXIFS(Mantenciones!$D:$D,Mantenciones!$B:$B,A17)) -> 4010 | R17: =IFERROR(IF(_xlfn.MAXIFS(Mantenciones!$D:$D,Mantenciones!$B:$B,$A17,Mantenciones!$E:$E,"Sí",Mantenciones!$D:$D,">0")=0,"Sin datos de mantención registrado",_xlfn.MAXIFS(Mantenciones!$D:$D,Mantenciones!$B:$B,$A17,Mantenciones!$E:$E,"Sí",Mantenciones!$D:$D,">0")),"Sin datos de mantención registrado") -> 4010 | S17: =IFERROR(SUMIFS(tblMantenciones[Costo Mantencion CLP],tblMantenciones[Codigo],A17),0) -> 0 | T17: =IFERROR(SUMIFS(tblComprasPM[Costo PM CLP],tblComprasPM[Codigo],tblMaestroEquipos[[#This Row],[Codigo]]),0) -> 341629.96 | U17: =IFERROR(tblMaestroEquipos[[#This Row],[Costo Mantenciones CLP]]+tblMaestroEquipos[[#This Row],[Costo Compras PM CLP]],0) -> 341629.96 | V17: =IFERROR(_xlfn.XLOOKUP(tblMaestroEquipos[[#This Row],[Codigo]],tblEquipos[Codigo],tblEquipos[Estado Base]),"") -> Operativo | W17: =IF(OR(TRIM($V17)="Fuera de Servicio",TRIM($V17)="Fuera de servicio"),"FUERA DE SERVICIO",IF(OR(TRIM($V17)="Taller",TRIM($V17)="En taller",TRIM($V17)="EN TALLER"),"EN TALLER",IF($AD17="PENDIENTE","POR RECIBIR",IF(AND($Z17<>"",$AA17=""),"EN PROCESO",IF(AND(ISNUMBER($X17),$X17<0),"ATRASADA",IF(AND(ISNUMBER($X17),$X17<=30),"PRÓXIMA","AL DÍA")))))) -> AL DÍA | X17: =IF(OR(NOT(ISNUMBER(R17)),NOT(ISNUMBER(J17)),NOT(ISNUMBER(O17))),"", (R17+J17)-O17) -> 243 | Y17: =IFERROR(IF(OR(tblMaestroEquipos[[#This Row],[Estado Operacional]]="FUERA DE SERVICIO",tblMaestroEquipos[[#This Row],[Ultima Fecha Lectura]]="",tblMaestroEquipos[[#This Row],[Dias a Proxima Mantencion]]=""),"",tblMaestroEquipos[[#This Row],[Ultima Fecha Lectura]]+tblMaestroEquipos[[#This Row],[Dias a Proxima Mantencion]]),"") -> 46393 | Z17: =IFERROR(IF(_xlfn.MINIFS(tblComprasPM[Fecha],tblComprasPM[Codigo],tblMaestroEquipos[[#This Row],[Codigo]])=0,"",_xlfn.MINIFS(tblComprasPM[Fecha],tblComprasPM[Codigo],tblMaestroEquipos[[#This Row],[Codigo]])),"") -> 46119.35 | AA17: =IFERROR(IF(_xlfn.MAXIFS(tblBodega[Fecha],tblBodega[Codigo],tblMaestroEquipos[[#This Row],[Codigo]])=0,"",_xlfn.MAXIFS(tblBodega[Fecha],tblBodega[Codigo],tblMaestroEquipos[[#This Row],[Codigo]])),"") -> 46134 | AB17: =IFERROR(IF(OR(tblMaestroEquipos[[#This Row],[Fecha Compra PM]]="",tblMaestroEquipos[[#This Row],[Fecha Compra PM]]=0),"",IF(OR(tblMaestroEquipos[[#This Row],[Ultima Fecha PM]]="",tblMaestroEquipos[[#This Row],[Ultima Fecha PM]]=0),MAX(0,INT(TODAY())-INT(tblMaestroEquipos[[#This Row],[Fecha Compra PM]])),MAX(0,INT(tblMaestroEquipos[[#This Row],[Ultima Fecha PM]])-INT(tblMaestroEquipos[[#This Row],[Fecha Compra PM]])))),"") -> 28 | AC17: =IFERROR(IF(OR(tblMaestroEquipos[[#This Row],[Fecha Salida Bodega]]="",tblMaestroEquipos[[#This Row],[Fecha Salida Bodega]]=0),"",IF(OR(tblMaestroEquipos[[#This Row],[Ultima Fecha PM]]="",tblMaestroEquipos[[#This Row],[Ultima Fecha PM]]=0),MAX(0,INT(TODAY())-INT(tblMaestroEquipos[[#This Row],[Fecha Salida Bodega]])),MAX(0,INT(tblMaestroEquipos[[#This Row],[Ultima Fecha PM]])-INT(tblMaestroEquipos[[#This Row],[Fecha Salida Bodega]])))),"") -> 13 | AD17: =IF(tblMaestroEquipos[[#This Row],[Fecha Salida Bodega]]="","SIN SALIDA BODEGA",IF(OR(tblMaestroEquipos[[#This Row],[Ultima Fecha PM]]="",tblMaestroEquipos[[#This Row],[Ultima Fecha PM]]<tblMaestroEquipos[[#This Row],[Fecha Salida Bodega]]),"PENDIENTE","CERRADO")) -> CERRADO | AE17: =IF(TRIM(V17)="Fuera de servicio","FUERA DE SERVICIO", IF(OR(TRIM(V17)="Taller",TRIM(V17)="En taller"),"EN TALLER", IF(W17="ATRASADO","ATRASADO", IF(W17="EN PROCESO","EN PROCESO", IF(W17="PRÓXIMO","PRÓXIMO", "OPERATIVO"))))) -> OPERATIVO | AF17: =IF($AE17="ATRASADA",IF($X17<=-15,"CRÍTICA","ALTA"),IF($AE17="PRÓXIMA","MEDIA",IF(OR($AE17="EN PROCESO",$AE17="POR RECIBIR"),"SEGUIMIENTO",IF($AE17="FUERA DE SERVICIO","NO APLICA","BAJA")))) -> BAJA | AG17: =IF($AE17="FUERA DE SERVICIO","No programar compra",IF($AE17="CERRADO","Cerrar ciclo y preparar siguiente PM",IF($AE17="EN PROCESO","Hacer seguimiento al taller y cerrar report",IF($AE17="POR RECIBIR","Acelerar recepción de repuestos",IF($AE17="ATRASADA","Comprar kit PM y coordinar ejecución",IF($AE17="PRÓXIMA","Planificar compra preventiva","Monitorear próximo vencimiento")))))) -> Monitorear próximo vencimiento | AH17: =IF(AND(OR($AE17="ATRASADA",$AE17="PRÓXIMA"),$Z17="",$AA17=""),1,0) -> 0 | AI17: =IF(OR($AH17=0,$Y17=""),"",SUMPRODUCT(($AH$4:$AH$242=1)*(($Y$4:$Y$242<$Y17)+(($Y$4:$Y$242=$Y17)*(ROW($Y$4:$Y$242)<=ROW()))))) | AJ17: =IF(W17="ATRASADA",1,IF(W17="EN PROCESO",2,IF(W17="POR RECIBIR",3,99))) -> 99
A18: CD-115 | B18: Tracto Camión | C18: Camiones de Ruta | D18: Mercedes Benz | E18: LS 1634 45 | F18: 2011 | G18: =IFERROR(_xlfn.XLOOKUP($A18,tblEquipos[Codigo],tblEquipos[Ubicacion],""),"") -> Taller ext | H18: Manuel Pacheco | I18: =IFERROR(VLOOKUP(A18, Equipos!A:J, 9, FALSE), "") -> KM | J18: =IFERROR(VLOOKUP(A18, Equipos!A:J, 10, FALSE), "") -> 10000 | K18: =IFERROR(IF($I18="KM",ROUND((_xlfn.MAXIFS(tblLecturas[Kilometraje],tblLecturas[Codigo],$A18)-_xlfn.MINIFS(tblLecturas[Kilometraje],tblLecturas[Codigo],$A18))/(MAX(1,_xlfn.MAXIFS(tblLecturas[Fecha],tblLecturas[Codigo],$A18)-_xlfn.MINIFS(tblLecturas[Fecha],tblLecturas[Codigo],$A18))),1),ROUND((_xlfn.MAXIFS(tblLecturas[Horometro],tblLecturas[Codigo],$A18)-_xlfn.MINIFS(tblLecturas[Horometro],tblLecturas[Codigo],$A18))/(MAX(1,_xlfn.MAXIFS(tblLecturas[Fecha],tblLecturas[Codigo],$A18)-_xlfn.MINIFS(tblLecturas[Fecha],tblLecturas[Codigo],$A18))),1)),"") -> 225.3 | L18: =IFERROR(_xlfn.MAXIFS(tblLecturas[Fecha],tblLecturas[Codigo],$A18),"") -> 46064 | M18: =IFERROR(_xlfn.MAXIFS(Lecturas!$C:$C,Lecturas!$B:$B,$A18,Lecturas!$C:$C,">0"),"") -> 0 | N18: =IFERROR(_xlfn.MAXIFS(tblLecturas[Kilometraje],tblLecturas[Codigo],$A18,tblLecturas[Kilometraje],">0"),"") -> 333912 | O18: {=IFERROR(IF($I18="KM",LOOKUP(2,1/(Lecturas!$B:$B=$A18)/(Lecturas!$D:$D>0),Lecturas!$D:$D),LOOKUP(2,1/(Lecturas!$B:$B=$A18)/(Lecturas!$C:$C>0),Lecturas!$C:$C)),"")} -> 329180 | P18: =IFERROR(_xlfn.MAXIFS(tblMantenciones[Fecha],tblMantenciones[Codigo],tblMaestroEquipos[[#This Row],[Codigo]],tblMantenciones[EsPM],"Sí"),"") -> 44937 | Q18: =IF(_xlfn.MAXIFS(Mantenciones!$D:$D,Mantenciones!$B:$B,A18)=0,"Sin datos de mantención registrado",_xlfn.MAXIFS(Mantenciones!$D:$D,Mantenciones!$B:$B,A18)) -> 328000 | R18: =IFERROR(IF(_xlfn.MAXIFS(Mantenciones!$D:$D,Mantenciones!$B:$B,$A18,Mantenciones!$E:$E,"Sí",Mantenciones!$D:$D,">0")=0,"Sin datos de mantención registrado",_xlfn.MAXIFS(Mantenciones!$D:$D,Mantenciones!$B:$B,$A18,Mantenciones!$E:$E,"Sí",Mantenciones!$D:$D,">0")),"Sin datos de mantención registrado") -> 328000 | S18: =IFERROR(SUMIFS(tblMantenciones[Costo Mantencion CLP],tblMantenciones[Codigo],A18),0) -> 0 | T18: =IFERROR(SUMIFS(tblComprasPM[Costo PM CLP],tblComprasPM[Codigo],tblMaestroEquipos[[#This Row],[Codigo]]),0) -> 121145.57 | U18: =IFERROR(tblMaestroEquipos[[#This Row],[Costo Mantenciones CLP]]+tblMaestroEquipos[[#This Row],[Costo Compras PM CLP]],0) -> 121145.57 | V18: =IFERROR(_xlfn.XLOOKUP(tblMaestroEquipos[[#This Row],[Codigo]],tblEquipos[Codigo],tblEquipos[Estado Base]),"") -> Taller | W18: =IF(OR(TRIM($V18)="Fuera de Servicio",TRIM($V18)="Fuera de servicio"),"FUERA DE SERVICIO",IF(OR(TRIM($V18)="Taller",TRIM($V18)="En taller",TRIM($V18)="EN TALLER"),"EN TALLER",IF($AD18="PENDIENTE","POR RECIBIR",IF(AND($Z18<>"",$AA18=""),"EN PROCESO",IF(AND(ISNUMBER($X18),$X18<0),"ATRASADA",IF(AND(ISNUMBER($X18),$X18<=30),"PRÓXIMA","AL DÍA")))))) -> EN TALLER | X18: =IF(OR(NOT(ISNUMBER(R18)),NOT(ISNUMBER(J18)),NOT(ISNUMBER(O18))),"", (R18+J18)-O18) -> 8820 | Y18: =IFERROR(IF(OR(tblMaestroEquipos[[#This Row],[Estado Operacional]]="FUERA DE SERVICIO",tblMaestroEquipos[[#This Row],[Ultima Fecha Lectura]]="",tblMaestroEquipos[[#This Row],[Dias a Proxima Mantencion]]=""),"",tblMaestroEquipos[[#This Row],[Ultima Fecha Lectura]]+tblMaestroEquipos[[#This Row],[Dias a Proxima Mantencion]]),"") -> 54884 | Z18: =IFERROR(IF(_xlfn.MINIFS(tblComprasPM[Fecha],tblComprasPM[Codigo],tblMaestroEquipos[[#This Row],[Codigo]])=0,"",_xlfn.MINIFS(tblComprasPM[Fecha],tblComprasPM[Codigo],tblMaestroEquipos[[#This Row],[Codigo]])),"") -> 46100 | AA18: =IFERROR(IF(_xlfn.MAXIFS(tblBodega[Fecha],tblBodega[Codigo],tblMaestroEquipos[[#This Row],[Codigo]])=0,"",_xlfn.MAXIFS(tblBodega[Fecha],tblBodega[Codigo],tblMaestroEquipos[[#This Row],[Codigo]])),"") -> 46062 | AB18: =IFERROR(IF(OR(tblMaestroEquipos[[#This Row],[Fecha Compra PM]]="",tblMaestroEquipos[[#This Row],[Fecha Compra PM]]=0),"",IF(OR(tblMaestroEquipos[[#This Row],[Ultima Fecha PM]]="",tblMaestroEquipos[[#This Row],[Ultima Fecha PM]]=0),MAX(0,INT(TODAY())-INT(tblMaestroEquipos[[#This Row],[Fecha Compra PM]])),MAX(0,INT(tblMaestroEquipos[[#This Row],[Ultima Fecha PM]])-INT(tblMaestroEquipos[[#This Row],[Fecha Compra PM]])))),"") -> 0 | AC18: =IFERROR(IF(OR(tblMaestroEquipos[[#This Row],[Fecha Salida Bodega]]="",tblMaestroEquipos[[#This Row],[Fecha Salida Bodega]]=0),"",IF(OR(tblMaestroEquipos[[#This Row],[Ultima Fecha PM]]="",tblMaestroEquipos[[#This Row],[Ultima Fecha PM]]=0),MAX(0,INT(TODAY())-INT(tblMaestroEquipos[[#This Row],[Fecha Salida Bodega]])),MAX(0,INT(tblMaestroEquipos[[#This Row],[Ultima Fecha PM]])-INT(tblMaestroEquipos[[#This Row],[Fecha Salida Bodega]])))),"") -> 0 | AD18: =IF(tblMaestroEquipos[[#This Row],[Fecha Salida Bodega]]="","SIN SALIDA BODEGA",IF(OR(tblMaestroEquipos[[#This Row],[Ultima Fecha PM]]="",tblMaestroEquipos[[#This Row],[Ultima Fecha PM]]<tblMaestroEquipos[[#This Row],[Fecha Salida Bodega]]),"PENDIENTE","CERRADO")) -> PENDIENTE | AE18: =IF(TRIM(V18)="Fuera de servicio","FUERA DE SERVICIO", IF(OR(TRIM(V18)="Taller",TRIM(V18)="En taller"),"EN TALLER", IF(W18="ATRASADO","ATRASADO", IF(W18="EN PROCESO","EN PROCESO", IF(W18="PRÓXIMO","PRÓXIMO", "OPERATIVO"))))) -> EN TALLER | AF18: =IF($AE18="ATRASADA",IF($X18<=-15,"CRÍTICA","ALTA"),IF($AE18="PRÓXIMA","MEDIA",IF(OR($AE18="EN PROCESO",$AE18="POR RECIBIR"),"SEGUIMIENTO",IF($AE18="FUERA DE SERVICIO","NO APLICA","BAJA")))) -> BAJA | AG18: =IF($AE18="FUERA DE SERVICIO","No programar compra",IF($AE18="CERRADO","Cerrar ciclo y preparar siguiente PM",IF($AE18="EN PROCESO","Hacer seguimiento al taller y cerrar report",IF($AE18="POR RECIBIR","Acelerar recepción de repuestos",IF($AE18="ATRASADA","Comprar kit PM y coordinar ejecución",IF($AE18="PRÓXIMA","Planificar compra preventiva","Monitorear próximo vencimiento")))))) -> Monitorear próximo vencimiento | AH18: =IF(AND(OR($AE18="ATRASADA",$AE18="PRÓXIMA"),$Z18="",$AA18=""),1,0) -> 0 | AI18: =IF(OR($AH18=0,$Y18=""),"",SUMPRODUCT(($AH$4:$AH$242=1)*(($Y$4:$Y$242<$Y18)+(($Y$4:$Y$242=$Y18)*(ROW($Y$4:$Y$242)<=ROW()))))) | AJ18: =IF(W18="ATRASADA",1,IF(W18="EN PROCESO",2,IF(W18="POR RECIBIR",3,99))) -> 99
A19: CD-116 | B19: Camión Plano | C19: Camiones de Ruta | D19: Wolkswagen | E19: 9150E | F19: 2012 | G19: =IFERROR(_xlfn.XLOOKUP($A19,tblEquipos[Codigo],tblEquipos[Ubicacion],""),"") -> Taller | H19: No identificado | I19: =IFERROR(VLOOKUP(A19, Equipos!A:J, 9, FALSE), "") -> HORAS | J19: =IFERROR(VLOOKUP(A19, Equipos!A:J, 10, FALSE), "") -> 250 | K19: =IFERROR(IF($I19="KM",ROUND((_xlfn.MAXIFS(tblLecturas[Kilometraje],tblLecturas[Codigo],$A19)-_xlfn.MINIFS(tblLecturas[Kilometraje],tblLecturas[Codigo],$A19))/(MAX(1,_xlfn.MAXIFS(tblLecturas[Fecha],tblLecturas[Codigo],$A19)-_xlfn.MINIFS(tblLecturas[Fecha],tblLecturas[Codigo],$A19))),1),ROUND((_xlfn.MAXIFS(tblLecturas[Horometro],tblLecturas[Codigo],$A19)-_xlfn.MINIFS(tblLecturas[Horometro],tblLecturas[Codigo],$A19))/(MAX(1,_xlfn.MAXIFS(tblLecturas[Fecha],tblLecturas[Codigo],$A19)-_xlfn.MINIFS(tblLecturas[Fecha],tblLecturas[Codigo],$A19))),1)),"") -> 0 | L19: =IFERROR(_xlfn.MAXIFS(tblLecturas[Fecha],tblLecturas[Codigo],$A19),"") -> 46100 | M19: =IFERROR(_xlfn.MAXIFS(Lecturas!$C:$C,Lecturas!$B:$B,$A19,Lecturas!$C:$C,">0"),"") -> 0 | N19: =IFERROR(_xlfn.MAXIFS(tblLecturas[Kilometraje],tblLecturas[Codigo],$A19,tblLecturas[Kilometraje],">0"),"") -> 329583 | O19: {=IFERROR(IF($I19="KM",LOOKUP(2,1/(Lecturas!$B:$B=$A19)/(Lecturas!$D:$D>0),Lecturas!$D:$D),LOOKUP(2,1/(Lecturas!$B:$B=$A19)/(Lecturas!$C:$C>0),Lecturas!$C:$C)),"")} | P19: =IFERROR(_xlfn.MAXIFS(tblMantenciones[Fecha],tblMantenciones[Codigo],tblMaestroEquipos[[#This Row],[Codigo]],tblMantenciones[EsPM],"Sí"),"") -> 46133 | Q19: =IF(_xlfn.MAXIFS(Mantenciones!$D:$D,Mantenciones!$B:$B,A19)=0,"Sin datos de mantención registrado",_xlfn.MAXIFS(Mantenciones!$D:$D,Mantenciones!$B:$B,A19)) -> 395318 | R19: =IFERROR(IF(_xlfn.MAXIFS(Mantenciones!$D:$D,Mantenciones!$B:$B,$A19,Mantenciones!$E:$E,"Sí",Mantenciones!$D:$D,">0")=0,"Sin datos de mantención registrado",_xlfn.MAXIFS(Mantenciones!$D:$D,Mantenciones!$B:$B,$A19,Mantenciones!$E:$E,"Sí",Mantenciones!$D:$D,">0")),"Sin datos de mantención registrado") -> 395318 | S19: =IFERROR(SUMIFS(tblMantenciones[Costo Mantencion CLP],tblMantenciones[Codigo],A19),0) -> 0 | T19: =IFERROR(SUMIFS(tblComprasPM[Costo PM CLP],tblComprasPM[Codigo],tblMaestroEquipos[[#This Row],[Codigo]]),0) -> 94000.004 | U19: =IFERROR(tblMaestroEquipos[[#This Row],[Costo Mantenciones CLP]]+tblMaestroEquipos[[#This Row],[Costo Compras PM CLP]],0) -> 94000.004 | V19: =IFERROR(_xlfn.XLOOKUP(tblMaestroEquipos[[#This Row],[Codigo]],tblEquipos[Codigo],tblEquipos[Estado Base]),"") -> Operativo | W19: =IF(OR(TRIM($V19)="Fuera de Servicio",TRIM($V19)="Fuera de servicio"),"FUERA DE SERVICIO",IF(OR(TRIM($V19)="Taller",TRIM($V19)="En taller",TRIM($V19)="EN TALLER"),"EN TALLER",IF($AD19="PENDIENTE","POR RECIBIR",IF(AND($Z19<>"",$AA19=""),"EN PROCESO",IF(AND(ISNUMBER($X19),$X19<0),"ATRASADA",IF(AND(ISNUMBER($X19),$X19<=30),"PRÓXIMA","AL DÍA")))))) -> EN PROCESO | X19: =IF(OR(NOT(ISNUMBER(R19)),NOT(ISNUMBER(J19)),NOT(ISNUMBER(O19))),"", (R19+J19)-O19) | Y19: =IFERROR(IF(OR(tblMaestroEquipos[[#This Row],[Estado Operacional]]="FUERA DE SERVICIO",tblMaestroEquipos[[#This Row],[Ultima Fecha Lectura]]="",tblMaestroEquipos[[#This Row],[Dias a Proxima Mantencion]]=""),"",tblMaestroEquipos[[#This Row],[Ultima Fecha Lectura]]+tblMaestroEquipos[[#This Row],[Dias a Proxima Mantencion]]),"") | Z19: =IFERROR(IF(_xlfn.MINIFS(tblComprasPM[Fecha],tblComprasPM[Codigo],tblMaestroEquipos[[#This Row],[Codigo]])=0,"",_xlfn.MINIFS(tblComprasPM[Fecha],tblComprasPM[Codigo],tblMaestroEquipos[[#This Row],[Codigo]])),"") -> 46078.358 | AA19: =IFERROR(IF(_xlfn.MAXIFS(tblBodega[Fecha],tblBodega[Codigo],tblMaestroEquipos[[#This Row],[Codigo]])=0,"",_xlfn.MAXIFS(tblBodega[Fecha],tblBodega[Codigo],tblMaestroEquipos[[#This Row],[Codigo]])),"") | AB19: =IFERROR(IF(OR(tblMaestroEquipos[[#This Row],[Fecha Compra PM]]="",tblMaestroEquipos[[#This Row],[Fecha Compra PM]]=0),"",IF(OR(tblMaestroEquipos[[#This Row],[Ultima Fecha PM]]="",tblMaestroEquipos[[#This Row],[Ultima Fecha PM]]=0),MAX(0,INT(TODAY())-INT(tblMaestroEquipos[[#This Row],[Fecha Compra PM]])),MAX(0,INT(tblMaestroEquipos[[#This Row],[Ultima Fecha PM]])-INT(tblMaestroEquipos[[#This Row],[Fecha Compra PM]])))),"") -> 55 | AC19: =IFERROR(IF(OR(tblMaestroEquipos[[#This Row],[Fecha Salida Bodega]]="",tblMaestroEquipos[[#This Row],[Fecha Salida Bodega]]=0),"",IF(OR(tblMaestroEquipos[[#This Row],[Ultima Fecha PM]]="",tblMaestroEquipos[[#This Row],[Ultima Fecha PM]]=0),MAX(0,INT(TODAY())-INT(tblMaestroEquipos[[#This Row],[Fecha Salida Bodega]])),MAX(0,INT(tblMaestroEquipos[[#This Row],[Ultima Fecha PM]])-INT(tblMaestroEquipos[[#This Row],[Fecha Salida Bodega]])))),"") | AD19: =IF(tblMaestroEquipos[[#This Row],[Fecha Salida Bodega]]="","SIN SALIDA BODEGA",IF(OR(tblMaestroEquipos[[#This Row],[Ultima Fecha PM]]="",tblMaestroEquipos[[#This Row],[Ultima Fecha PM]]<tblMaestroEquipos[[#This Row],[Fecha Salida Bodega]]),"PENDIENTE","CERRADO")) -> SIN SALIDA BODEGA | AE19: =IF(TRIM(V19)="Fuera de servicio","FUERA DE SERVICIO", IF(OR(TRIM(V19)="Taller",TRIM(V19)="En taller"),"EN TALLER", IF(W19="ATRASADO","ATRASADO", IF(W19="EN PROCESO","EN PROCESO", IF(W19="PRÓXIMO","PRÓXIMO", "OPERATIVO"))))) -> EN PROCESO | AF19: =IF($AE19="ATRASADA",IF($X19<=-15,"CRÍTICA","ALTA"),IF($AE19="PRÓXIMA","MEDIA",IF(OR($AE19="EN PROCESO",$AE19="POR RECIBIR"),"SEGUIMIENTO",IF($AE19="FUERA DE SERVICIO","NO APLICA","BAJA")))) -> SEGUIMIENTO | AG19: =IF($AE19="FUERA DE SERVICIO","No programar compra",IF($AE19="CERRADO","Cerrar ciclo y preparar siguiente PM",IF($AE19="EN PROCESO","Hacer seguimiento al taller y cerrar report",IF($AE19="POR RECIBIR","Acelerar recepción de repuestos",IF($AE19="ATRASADA","Comprar kit PM y coordinar ejecución",IF($AE19="PRÓXIMA","Planificar compra preventiva","Monitorear próximo vencimiento")))))) -> Hacer seguimiento al taller y cerrar report | AH19: =IF(AND(OR($AE19="ATRASADA",$AE19="PRÓXIMA"),$Z19="",$AA19=""),1,0) -> 0 | AI19: =IF(OR($AH19=0,$Y19=""),"",SUMPRODUCT(($AH$4:$AH$242=1)*(($Y$4:$Y$242<$Y19)+(($Y$4:$Y$242=$Y19)*(ROW($Y$4:$Y$242)<=ROW()))))) | AJ19: =IF(W19="ATRASADA",1,IF(W19="EN PROCESO",2,IF(W19="POR RECIBIR",3,99))) -> 2
A20: CD-117 | B20: Camión Slurry | C20: Camiones de Ruta | D20: No hay info | E20: No hay info | F20: No hay info | G20: =IFERROR(_xlfn.XLOOKUP($A20,tblEquipos[Codigo],tblEquipos[Ubicacion],""),"") -> Taller | H20: Sin asignar | I20: =IFERROR(VLOOKUP(A20, Equipos!A:J, 9, FALSE), "") -> HORAS | J20: =IFERROR(VLOOKUP(A20, Equipos!A:J, 10, FALSE), "") -> 250 | K20: =IFERROR(IF($I20="KM",ROUND((_xlfn.MAXIFS(tblLecturas[Kilometraje],tblLecturas[Codigo],$A20)-_xlfn.MINIFS(tblLecturas[Kilometraje],tblLecturas[Codigo],$A20))/(MAX(1,_xlfn.MAXIFS(tblLecturas[Fecha],tblLecturas[Codigo],$A20)-_xlfn.MINIFS(tblLecturas[Fecha],tblLecturas[Codigo],$A20))),1),ROUND((_xlfn.MAXIFS(tblLecturas[Horometro],tblLecturas[Codigo],$A20)-_xlfn.MINIFS(tblLecturas[Horometro],tblLecturas[Codigo],$A20))/(MAX(1,_xlfn.MAXIFS(tblLecturas[Fecha],tblLecturas[Codigo],$A20)-_xlfn.MINIFS(tblLecturas[Fecha],tblLecturas[Codigo],$A20))),1)),"") -> 0 | L20: =IFERROR(_xlfn.MAXIFS(tblLecturas[Fecha],tblLecturas[Codigo],$A20),"") -> 46034 | M20: =IFERROR(_xlfn.MAXIFS(Lecturas!$C:$C,Lecturas!$B:$B,$A20,Lecturas!$C:$C,">0"),"") -> 0 | N20: =IFERROR(_xlfn.MAXIFS(tblLecturas[Kilometraje],tblLecturas[Codigo],$A20,tblLecturas[Kilometraje],">0"),"") -> 114148 | O20: {=IFERROR(IF($I20="KM",LOOKUP(2,1/(Lecturas!$B:$B=$A20)/(Lecturas!$D:$D>0),Lecturas!$D:$D),LOOKUP(2,1/(Lecturas!$B:$B=$A20)/(Lecturas!$C:$C>0),Lecturas!$C:$C)),"")} | P20: =IFERROR(_xlfn.MAXIFS(tblMantenciones[Fecha],tblMantenciones[Codigo],tblMaestroEquipos[[#This Row],[Codigo]],tblMantenciones[EsPM],"Sí"),"") -> 0 | Q20: =IF(_xlfn.MAXIFS(Mantenciones!$D:$D,Mantenciones!$B:$B,A20)=0,"Sin datos de mantención registrado",_xlfn.MAXIFS(Mantenciones!$D:$D,Mantenciones!$B:$B,A20)) -> Sin datos de mantención registrado | R20: =IFERROR(IF(_xlfn.MAXIFS(Mantenciones!$D:$D,Mantenciones!$B:$B,$A20,Mantenciones!$E:$E,"Sí",Mantenciones!$D:$D,">0")=0,"Sin datos de mantención registrado",_xlfn.MAXIFS(Mantenciones!$D:$D,Mantenciones!$B:$B,$A20,Mantenciones!$E:$E,"Sí",Mantenciones!$D:$D,">0")),"Sin datos de mantención registrado") -> Sin datos de mantención registrado | S20: =IFERROR(SUMIFS(tblMantenciones[Costo Mantencion CLP],tblMantenciones[Codigo],A20),0) -> 0 | T20: =IFERROR(SUMIFS(tblComprasPM[Costo PM CLP],tblComprasPM[Codigo],tblMaestroEquipos[[#This Row],[Codigo]]),0) -> 0 | U20: =IFERROR(tblMaestroEquipos[[#This Row],[Costo Mantenciones CLP]]+tblMaestroEquipos[[#This Row],[Costo Compras PM CLP]],0) -> 0 | V20: =IFERROR(_xlfn.XLOOKUP(tblMaestroEquipos[[#This Row],[Codigo]],tblEquipos[Codigo],tblEquipos[Estado Base]),"") -> Fuera de Servicio | W20: =IF(OR(TRIM($V20)="Fuera de Servicio",TRIM($V20)="Fuera de servicio"),"FUERA DE SERVICIO",IF(OR(TRIM($V20)="Taller",TRIM($V20)="En taller",TRIM($V20)="EN TALLER"),"EN TALLER",IF($AD20="PENDIENTE","POR RECIBIR",IF(AND($Z20<>"",$AA20=""),"EN PROCESO",IF(AND(ISNUMBER($X20),$X20<0),"ATRASADA",IF(AND(ISNUMBER($X20),$X20<=30),"PRÓXIMA","AL DÍA")))))) -> FUERA DE SERVICIO | X20: =IF(OR(NOT(ISNUMBER(R20)),NOT(ISNUMBER(J20)),NOT(ISNUMBER(O20))),"", (R20+J20)-O20) | Y20: =IFERROR(IF(OR(tblMaestroEquipos[[#This Row],[Estado Operacional]]="FUERA DE SERVICIO",tblMaestroEquipos[[#This Row],[Ultima Fecha Lectura]]="",tblMaestroEquipos[[#This Row],[Dias a Proxima Mantencion]]=""),"",tblMaestroEquipos[[#This Row],[Ultima Fecha Lectura]]+tblMaestroEquipos[[#This Row],[Dias a Proxima Mantencion]]),"") | Z20: =IFERROR(IF(_xlfn.MINIFS(tblComprasPM[Fecha],tblComprasPM[Codigo],tblMaestroEquipos[[#This Row],[Codigo]])=0,"",_xlfn.MINIFS(tblComprasPM[Fecha],tblComprasPM[Codigo],tblMaestroEquipos[[#This Row],[Codigo]])),"") | AA20: =IFERROR(IF(_xlfn.MAXIFS(tblBodega[Fecha],tblBodega[Codigo],tblMaestroEquipos[[#This Row],[Codigo]])=0,"",_xlfn.MAXIFS(tblBodega[Fecha],tblBodega[Codigo],tblMaestroEquipos[[#This Row],[Codigo]])),"") | AB20: =IFERROR(IF(OR(tblMaestroEquipos[[#This Row],[Fecha Compra PM]]="",tblMaestroEquipos[[#This Row],[Fecha Compra PM]]=0),"",IF(OR(tblMaestroEquipos[[#This Row],[Ultima Fecha PM]]="",tblMaestroEquipos[[#This Row],[Ultima Fecha PM]]=0),MAX(0,INT(TODAY())-INT(tblMaestroEquipos[[#This Row],[Fecha Compra PM]])),MAX(0,INT(tblMaestroEquipos[[#This Row],[Ultima Fecha PM]])-INT(tblMaestroEquipos[[#This Row],[Fecha Compra PM]])))),"") | AC20: =IFERROR(IF(OR(tblMaestroEquipos[[#This Row],[Fecha Salida Bodega]]="",tblMaestroEquipos[[#This Row],[Fecha Salida Bodega]]=0),"",IF(OR(tblMaestroEquipos[[#This Row],[Ultima Fecha PM]]="",tblMaestroEquipos[[#This Row],[Ultima Fecha PM]]=0),MAX(0,INT(TODAY())-INT(tblMaestroEquipos[[#This Row],[Fecha Salida Bodega]])),MAX(0,INT(tblMaestroEquipos[[#This Row],[Ultima Fecha PM]])-INT(tblMaestroEquipos[[#This Row],[Fecha Salida Bodega]])))),"") | AD20: =IF(tblMaestroEquipos[[#This Row],[Fecha Salida Bodega]]="","SIN SALIDA BODEGA",IF(OR(tblMaestroEquipos[[#This Row],[Ultima Fecha PM]]="",tblMaestroEquipos[[#This Row],[Ultima Fecha PM]]<tblMaestroEquipos[[#This Row],[Fecha Salida Bodega]]),"PENDIENTE","CERRADO")) -> SIN SALIDA BODEGA | AE20: =IF(TRIM(V20)="Fuera de servicio","FUERA DE SERVICIO", IF(OR(TRIM(V20)="Taller",TRIM(V20)="En taller"),"EN TALLER", IF(W20="ATRASADO","ATRASADO", IF(W20="EN PROCESO","EN PROCESO", IF(W20="PRÓXIMO","PRÓXIMO", "OPERATIVO"))))) -> FUERA DE SERVICIO | AF20: =IF($AE20="ATRASADA",IF($X20<=-15,"CRÍTICA","ALTA"),IF($AE20="PRÓXIMA","MEDIA",IF(OR($AE20="EN PROCESO",$AE20="POR RECIBIR"),"SEGUIMIENTO",IF($AE20="FUERA DE SERVICIO","NO APLICA","BAJA")))) -> NO APLICA | AG20: =IF($AE20="FUERA DE SERVICIO","No programar compra",IF($AE20="CERRADO","Cerrar ciclo y preparar siguiente PM",IF($AE20="EN PROCESO","Hacer seguimiento al taller y cerrar report",IF($AE20="POR RECIBIR","Acelerar recepción de repuestos",IF($AE20="ATRASADA","Comprar kit PM y coordinar ejecución",IF($AE20="PRÓXIMA","Planificar compra preventiva","Monitorear próximo vencimiento")))))) -> No programar compra | AH20: =IF(AND(OR($AE20="ATRASADA",$AE20="PRÓXIMA"),$Z20="",$AA20=""),1,0) -> 0 | AI20: =IF(OR($AH20=0,$Y20=""),"",SUMPRODUCT(($AH$4:$AH$242=1)*(($Y$4:$Y$242<$Y20)+(($Y$4:$Y$242=$Y20)*(ROW($Y$4:$Y$242)<=ROW()))))) | AJ20: =IF(W20="ATRASADA",1,IF(W20="EN PROCESO",2,IF(W20="POR RECIBIR",3,99))) -> 99
A21: CD-118 | B21: Camión Plano | C21: Camiones de Ruta | D21: Freightliner | E21: M2 106 | F21: 2010 | G21: =IFERROR(_xlfn.XLOOKUP($A21,tblEquipos[Codigo],tblEquipos[Ubicacion],""),"") -> Taller | H21: Carlos Vasquez | I21: =IFERROR(VLOOKUP(A21, Equipos!A:J, 9, FALSE), "") -> HORAS | J21: =IFERROR(VLOOKUP(A21, Equipos!A:J, 10, FALSE), "") -> 250 | K21: =IFERROR(IF($I21="KM",ROUND((_xlfn.MAXIFS(tblLecturas[Kilometraje],tblLecturas[Codigo],$A21)-_xlfn.MINIFS(tblLecturas[Kilometraje],tblLecturas[Codigo],$A21))/(MAX(1,_xlfn.MAXIFS(tblLecturas[Fecha],tblLecturas[Codigo],$A21)-_xlfn.MINIFS(tblLecturas[Fecha],tblLecturas[Codigo],$A21))),1),ROUND((_xlfn.MAXIFS(tblLecturas[Horometro],tblLecturas[Codigo],$A21)-_xlfn.MINIFS(tblLecturas[Horometro],tblLecturas[Codigo],$A21))/(MAX(1,_xlfn.MAXIFS(tblLecturas[Fecha],tblLecturas[Codigo],$A21)-_xlfn.MINIFS(tblLecturas[Fecha],tblLecturas[Codigo],$A21))),1)),"") -> 0 | L21: =IFERROR(_xlfn.MAXIFS(tblLecturas[Fecha],tblLecturas[Codigo],$A21),"") -> 46150 | M21: =IFERROR(_xlfn.MAXIFS(Lecturas!$C:$C,Lecturas!$B:$B,$A21,Lecturas!$C:$C,">0"),"") -> 0 | N21: =IFERROR(_xlfn.MAXIFS(tblLecturas[Kilometraje],tblLecturas[Codigo],$A21,tblLecturas[Kilometraje],">0"),"") -> 917261 | O21: {=IFERROR(IF($I21="KM",LOOKUP(2,1/(Lecturas!$B:$B=$A21)/(Lecturas!$D:$D>0),Lecturas!$D:$D),LOOKUP(2,1/(Lecturas!$B:$B=$A21)/(Lecturas!$C:$C>0),Lecturas!$C:$C)),"")} | P21: =IFERROR(_xlfn.MAXIFS(tblMantenciones[Fecha],tblMantenciones[Codigo],tblMaestroEquipos[[#This Row],[Codigo]],tblMantenciones[EsPM],"Sí"),"") -> 0 | Q21: =IF(_xlfn.MAXIFS(Mantenciones!$D:$D,Mantenciones!$B:$B,A21)=0,"Sin datos de mantención registrado",_xlfn.MAXIFS(Mantenciones!$D:$D,Mantenciones!$B:$B,A21)) -> Sin datos de mantención registrado | R21: =IFERROR(IF(_xlfn.MAXIFS(Mantenciones!$D:$D,Mantenciones!$B:$B,$A21,Mantenciones!$E:$E,"Sí",Mantenciones!$D:$D,">0")=0,"Sin datos de mantención registrado",_xlfn.MAXIFS(Mantenciones!$D:$D,Mantenciones!$B:$B,$A21,Mantenciones!$E:$E,"Sí",Mantenciones!$D:$D,">0")),"Sin datos de mantención registrado") -> Sin datos de mantención registrado | S21: =IFERROR(SUMIFS(tblMantenciones[Costo Mantencion CLP],tblMantenciones[Codigo],A21),0) -> 0 | T21: =IFERROR(SUMIFS(tblComprasPM[Costo PM CLP],tblComprasPM[Codigo],tblMaestroEquipos[[#This Row],[Codigo]]),0) -> 382151.35 | U21: =IFERROR(tblMaestroEquipos[[#This Row],[Costo Mantenciones CLP]]+tblMaestroEquipos[[#This Row],[Costo Compras PM CLP]],0) -> 382151.35 | V21: =IFERROR(_xlfn.XLOOKUP(tblMaestroEquipos[[#This Row],[Codigo]],tblEquipos[Codigo],tblEquipos[Estado Base]),"") -> Operativo | W21: =IF(OR(TRIM($V21)="Fuera de Servicio",TRIM($V21)="Fuera de servicio"),"FUERA DE SERVICIO",IF(OR(TRIM($V21)="Taller",TRIM($V21)="En taller",TRIM($V21)="EN TALLER"),"EN TALLER",IF($AD21="PENDIENTE","POR RECIBIR",IF(AND($Z21<>"",$AA21=""),"EN PROCESO",IF(AND(ISNUMBER($X21),$X21<0),"ATRASADA",IF(AND(ISNUMBER($X21),$X21<=30),"PRÓXIMA","AL DÍA")))))) -> POR RECIBIR | X21: =IF(OR(NOT(ISNUMBER(R21)),NOT(ISNUMBER(J21)),NOT(ISNUMBER(O21))),"", (R21+J21)-O21) | Y21: =IFERROR(IF($X21="","",TODAY()+$X21),"") | Z21: =IFERROR(IF(_xlfn.MINIFS(tblComprasPM[Fecha],tblComprasPM[Codigo],tblMaestroEquipos[[#This Row],[Codigo]])=0,"",_xlfn.MINIFS(tblComprasPM[Fecha],tblComprasPM[Codigo],tblMaestroEquipos[[#This Row],[Codigo]])),"") -> 46139.565 | AA21: =IFERROR(IF(_xlfn.MAXIFS(tblBodega[Fecha],tblBodega[Codigo],tblMaestroEquipos[[#This Row],[Codigo]])=0,"",_xlfn.MAXIFS(tblBodega[Fecha],tblBodega[Codigo],tblMaestroEquipos[[#This Row],[Codigo]])),"") -> 46161 | AB21: =IFERROR(IF(OR(tblMaestroEquipos[[#This Row],[Fecha Compra PM]]="",tblMaestroEquipos[[#This Row],[Fecha Compra PM]]=0),"",IF(OR(tblMaestroEquipos[[#This Row],[Ultima Fecha PM]]="",tblMaestroEquipos[[#This Row],[Ultima Fecha PM]]=0),MAX(0,INT(TODAY())-INT(tblMaestroEquipos[[#This Row],[Fecha Compra PM]])),MAX(0,INT(tblMaestroEquipos[[#This Row],[Ultima Fecha PM]])-INT(tblMaestroEquipos[[#This Row],[Fecha Compra PM]])))),"") -> 101 | AC21: =IFERROR(IF(OR(tblMaestroEquipos[[#This Row],[Fecha Salida Bodega]]="",tblMaestroEquipos[[#This Row],[Fecha Salida Bodega]]=0),"",IF(OR(tblMaestroEquipos[[#This Row],[Ultima Fecha PM]]="",tblMaestroEquipos[[#This Row],[Ultima Fecha PM]]=0),MAX(0,INT(TODAY())-INT(tblMaestroEquipos[[#This Row],[Fecha Salida Bodega]])),MAX(0,INT(tblMaestroEquipos[[#This Row],[Ultima Fecha PM]])-INT(tblMaestroEquipos[[#This Row],[Fecha Salida Bodega]])))),"") -> 79 | AD21: =IF(tblMaestroEquipos[[#This Row],[Fecha Salida Bodega]]="","SIN SALIDA BODEGA",IF(OR(tblMaestroEquipos[[#This Row],[Ultima Fecha PM]]="",tblMaestroEquipos[[#This Row],[Ultima Fecha PM]]<tblMaestroEquipos[[#This Row],[Fecha Salida Bodega]]),"PENDIENTE","CERRADO")) -> PENDIENTE | AE21: =IF(TRIM(V21)="Fuera de servicio","FUERA DE SERVICIO", IF(OR(TRIM(V21)="Taller",TRIM(V21)="En taller"),"EN TALLER", IF(W21="ATRASADO","ATRASADO", IF(W21="EN PROCESO","EN PROCESO", IF(W21="PRÓXIMO","PRÓXIMO", "OPERATIVO"))))) -> OPERATIVO | AF21: =IF($AE21="ATRASADA",IF($X21<=-15,"CRÍTICA","ALTA"),IF($AE21="PRÓXIMA","MEDIA",IF(OR($AE21="EN PROCESO",$AE21="POR RECIBIR"),"SEGUIMIENTO",IF($AE21="FUERA DE SERVICIO","NO APLICA","BAJA")))) -> BAJA | AG21: =IF($AE21="FUERA DE SERVICIO","No programar compra",IF($AE21="CERRADO","Cerrar ciclo y preparar siguiente PM",IF($AE21="EN PROCESO","Hacer seguimiento al taller y cerrar report",IF($AE21="POR RECIBIR","Acelerar recepción de repuestos",IF($AE21="ATRASADA","Comprar kit PM y coordinar ejecución",IF($AE21="PRÓXIMA","Planificar compra preventiva","Monitorear próximo vencimiento")))))) -> Monitorear próximo vencimiento | AH21: =IF(AND(OR($AE21="ATRASADA",$AE21="PRÓXIMA"),$Z21="",$AA21=""),1,0) -> 0 | AI21: =IF(OR($AH21=0,$Y21=""),"",SUMPRODUCT(($AH$4:$AH$242=1)*(($Y$4:$Y$242<$Y21)+(($Y$4:$Y$242=$Y21)*(ROW($Y$4:$Y$242)<=ROW()))))) | AJ21: =IF(W21="ATRASADA",1,IF(W21="EN PROCESO",2,IF(W21="POR RECIBIR",3,99))) -> 3
A22: CD-119 | B22: Camión Combustible | C22: Camiones de Ruta | D22: Hino | E22: GH8JMTA | F22: 2013 | G22: =IFERROR(_xlfn.XLOOKUP($A22,tblEquipos[Codigo],tblEquipos[Ubicacion],""),"") -> San Nicolas | H22: Francisco Hidalgo | I22: =IFERROR(VLOOKUP(A22, Equipos!A:J, 9, FALSE), "") -> HORAS | J22: =IFERROR(VLOOKUP(A22, Equipos!A:J, 10, FALSE), "") -> 250 | K22: =IFERROR(IF($I22="KM",ROUND((_xlfn.MAXIFS(tblLecturas[Kilometraje],tblLecturas[Codigo],$A22)-_xlfn.MINIFS(tblLecturas[Kilometraje],tblLecturas[Codigo],$A22))/(MAX(1,_xlfn.MAXIFS(tblLecturas[Fecha],tblLecturas[Codigo],$A22)-_xlfn.MINIFS(tblLecturas[Fecha],tblLecturas[Codigo],$A22))),1),ROUND((_xlfn.MAXIFS(tblLecturas[Horometro],tblLecturas[Codigo],$A22)-_xlfn.MINIFS(tblLecturas[Horometro],tblLecturas[Codigo],$A22))/(MAX(1,_xlfn.MAXIFS(tblLecturas[Fecha],tblLecturas[Codigo],$A22)-_xlfn.MINIFS(tblLecturas[Fecha],tblLecturas[Codigo],$A22))),1)),"") -> 0.6 | L22: =IFERROR(_xlfn.MAXIFS(tblLecturas[Fecha],tblLecturas[Codigo],$A22),"") -> 46115 | M22: =IFERROR(_xlfn.MAXIFS(Lecturas!$C:$C,Lecturas!$B:$B,$A22,Lecturas!$C:$C,">0"),"") -> 2841 | N22: =IFERROR(_xlfn.MAXIFS(tblLecturas[Kilometraje],tblLecturas[Codigo],$A22,tblLecturas[Kilometraje],">0"),"") -> 195800 | O22: {=IFERROR(IF($I22="KM",LOOKUP(2,1/(Lecturas!$B:$B=$A22)/(Lecturas!$D:$D>0),Lecturas!$D:$D),LOOKUP(2,1/(Lecturas!$B:$B=$A22)/(Lecturas!$C:$C>0),Lecturas!$C:$C)),"")} -> 2832 | P22: =IFERROR(_xlfn.MAXIFS(tblMantenciones[Fecha],tblMantenciones[Codigo],tblMaestroEquipos[[#This Row],[Codigo]],tblMantenciones[EsPM],"Sí"),"") -> 46099 | Q22: =IF(_xlfn.MAXIFS(Mantenciones!$D:$D,Mantenciones!$B:$B,A22)=0,"Sin datos de mantención registrado",_xlfn.MAXIFS(Mantenciones!$D:$D,Mantenciones!$B:$B,A22)) -> 195600 | R22: =IFERROR(IF(_xlfn.MAXIFS(Mantenciones!$D:$D,Mantenciones!$B:$B,$A22,Mantenciones!$E:$E,"Sí",Mantenciones!$D:$D,">0")=0,"Sin datos de mantención registrado",_xlfn.MAXIFS(Mantenciones!$D:$D,Mantenciones!$B:$B,$A22,Mantenciones!$E:$E,"Sí",Mantenciones!$D:$D,">0")),"Sin datos de mantención registrado") -> 195600 | S22: =IFERROR(SUMIFS(tblMantenciones[Costo Mantencion CLP],tblMantenciones[Codigo],A22),0) -> 313653.99 | T22: =IFERROR(SUMIFS(tblComprasPM[Costo PM CLP],tblComprasPM[Codigo],tblMaestroEquipos[[#This Row],[Codigo]]),0) -> 372096.34 | U22: =IFERROR(tblMaestroEquipos[[#This Row],[Costo Mantenciones CLP]]+tblMaestroEquipos[[#This Row],[Costo Compras PM CLP]],0) -> 685750.33 | V22: =IFERROR(_xlfn.XLOOKUP(tblMaestroEquipos[[#This Row],[Codigo]],tblEquipos[Codigo],tblEquipos[Estado Base]),"") -> Operativo | W22: =IF(OR(TRIM($V22)="Fuera de Servicio",TRIM($V22)="Fuera de servicio"),"FUERA DE SERVICIO",IF(OR(TRIM($V22)="Taller",TRIM($V22)="En taller",TRIM($V22)="EN TALLER"),"EN TALLER",IF($AD22="PENDIENTE","POR RECIBIR",IF(AND($Z22<>"",$AA22=""),"EN PROCESO",IF(AND(ISNUMBER($X22),$X22<0),"ATRASADA",IF(AND(ISNUMBER($X22),$X22<=30),"PRÓXIMA","AL DÍA")))))) -> AL DÍA | X22: =IF(OR(NOT(ISNUMBER(R22)),NOT(ISNUMBER(J22)),NOT(ISNUMBER(O22))),"", (R22+J22)-O22) -> 193018 | Y22: =IFERROR(IF(OR(tblMaestroEquipos[[#This Row],[Estado Operacional]]="FUERA DE SERVICIO",tblMaestroEquipos[[#This Row],[Ultima Fecha Lectura]]="",tblMaestroEquipos[[#This Row],[Dias a Proxima Mantencion]]=""),"",tblMaestroEquipos[[#This Row],[Ultima Fecha Lectura]]+tblMaestroEquipos[[#This Row],[Dias a Proxima Mantencion]]),"") -> 239133 | Z22: =IFERROR(IF(_xlfn.MINIFS(tblComprasPM[Fecha],tblComprasPM[Codigo],tblMaestroEquipos[[#This Row],[Codigo]])=0,"",_xlfn.MINIFS(tblComprasPM[Fecha],tblComprasPM[Codigo],tblMaestroEquipos[[#This Row],[Codigo]])),"") -> 46071.627 | AA22: =IFERROR(IF(_xlfn.MAXIFS(tblBodega[Fecha],tblBodega[Codigo],tblMaestroEquipos[[#This Row],[Codigo]])=0,"",_xlfn.MAXIFS(tblBodega[Fecha],tblBodega[Codigo],tblMaestroEquipos[[#This Row],[Codigo]])),"") -> 46099 | AB22: =IFERROR(IF(OR(tblMaestroEquipos[[#This Row],[Fecha Compra PM]]="",tblMaestroEquipos[[#This Row],[Fecha Compra PM]]=0),"",IF(OR(tblMaestroEquipos[[#This Row],[Ultima Fecha PM]]="",tblMaestroEquipos[[#This Row],[Ultima Fecha PM]]=0),MAX(0,INT(TODAY())-INT(tblMaestroEquipos[[#This Row],[Fecha Compra PM]])),MAX(0,INT(tblMaestroEquipos[[#This Row],[Ultima Fecha PM]])-INT(tblMaestroEquipos[[#This Row],[Fecha Compra PM]])))),"") -> 28 | AC22: =IFERROR(IF(OR(tblMaestroEquipos[[#This Row],[Fecha Salida Bodega]]="",tblMaestroEquipos[[#This Row],[Fecha Salida Bodega]]=0),"",IF(OR(tblMaestroEquipos[[#This Row],[Ultima Fecha PM]]="",tblMaestroEquipos[[#This Row],[Ultima Fecha PM]]=0),MAX(0,INT(TODAY())-INT(tblMaestroEquipos[[#This Row],[Fecha Salida Bodega]])),MAX(0,INT(tblMaestroEquipos[[#This Row],[Ultima Fecha PM]])-INT(tblMaestroEquipos[[#This Row],[Fecha Salida Bodega]])))),"") -> 0 | AD22: =IF(tblMaestroEquipos[[#This Row],[Fecha Salida Bodega]]="","SIN SALIDA BODEGA",IF(OR(tblMaestroEquipos[[#This Row],[Ultima Fecha PM]]="",tblMaestroEquipos[[#This Row],[Ultima Fecha PM]]<tblMaestroEquipos[[#This Row],[Fecha Salida Bodega]]),"PENDIENTE","CERRADO")) -> CERRADO | AE22: =IF(TRIM(V22)="Fuera de servicio","FUERA DE SERVICIO", IF(OR(TRIM(V22)="Taller",TRIM(V22)="En taller"),"EN TALLER", IF(W22="ATRASADO","ATRASADO", IF(W22="EN PROCESO","EN PROCESO", IF(W22="PRÓXIMO","PRÓXIMO", "OPERATIVO"))))) -> OPERATIVO | AF22: =IF($AE22="ATRASADA",IF($X22<=-15,"CRÍTICA","ALTA"),IF($AE22="PRÓXIMA","MEDIA",IF(OR($AE22="EN PROCESO",$AE22="POR RECIBIR"),"SEGUIMIENTO",IF($AE22="FUERA DE SERVICIO","NO APLICA","BAJA")))) -> BAJA | AG22: =IF($AE22="FUERA DE SERVICIO","No programar compra",IF($AE22="CERRADO","Cerrar ciclo y preparar siguiente PM",IF($AE22="EN PROCESO","Hacer seguimiento al taller y cerrar report",IF($AE22="POR RECIBIR","Acelerar recepción de repuestos",IF($AE22="ATRASADA","Comprar kit PM y coordinar ejecución",IF($AE22="PRÓXIMA","Planificar compra preventiva","Monitorear próximo vencimiento")))))) -> Monitorear próximo vencimiento | AH22: =IF(AND(OR($AE22="ATRASADA",$AE22="PRÓXIMA"),$Z22="",$AA22=""),1,0) -> 0 | AI22: =IF(OR($AH22=0,$Y22=""),"",SUMPRODUCT(($AH$4:$AH$242=1)*(($Y$4:$Y$242<$Y22)+(($Y$4:$Y$242=$Y22)*(ROW($Y$4:$Y$242)<=ROW()))))) | AJ22: =IF(W22="ATRASADA",1,IF(W22="EN PROCESO",2,IF(W22="POR RECIBIR",3,99))) -> 99
A23: CD-120 | B23: Camión Tolva | C23: Camiones de Ruta | D23: Man | E23: TGS 40400 BB | F23: 2024 | G23: =IFERROR(_xlfn.XLOOKUP($A23,tblEquipos[Codigo],tblEquipos[Ubicacion],""),"") -> Cobquecura | H23: Pablo Torres | I23: =IFERROR(VLOOKUP(A23, Equipos!A:J, 9, FALSE), "") -> HORAS | J23: =IFERROR(VLOOKUP(A23, Equipos!A:J, 10, FALSE), "") -> 500 | K23: =IFERROR(IF($I23="KM",ROUND((_xlfn.MAXIFS(tblLecturas[Kilometraje],tblLecturas[Codigo],$A23)-_xlfn.MINIFS(tblLecturas[Kilometraje],tblLecturas[Codigo],$A23))/(MAX(1,_xlfn.MAXIFS(tblLecturas[Fecha],tblLecturas[Codigo],$A23)-_xlfn.MINIFS(tblLecturas[Fecha],tblLecturas[Codigo],$A23))),1),ROUND((_xlfn.MAXIFS(tblLecturas[Horometro],tblLecturas[Codigo],$A23)-_xlfn.MINIFS(tblLecturas[Horometro],tblLecturas[Codigo],$A23))/(MAX(1,_xlfn.MAXIFS(tblLecturas[Fecha],tblLecturas[Codigo],$A23)-_xlfn.MINIFS(tblLecturas[Fecha],tblLecturas[Codigo],$A23))),1)),"") -> 2.7 | L23: =IFERROR(_xlfn.MAXIFS(tblLecturas[Fecha],tblLecturas[Codigo],$A23),"") -> 46086 | M23: =IFERROR(_xlfn.MAXIFS(Lecturas!$C:$C,Lecturas!$B:$B,$A23,Lecturas!$C:$C,">0"),"") -> 3406 | N23: =IFERROR(_xlfn.MAXIFS(tblLecturas[Kilometraje],tblLecturas[Codigo],$A23,tblLecturas[Kilometraje],">0"),"") -> 0 | O23: {=IFERROR(IF($I23="KM",LOOKUP(2,1/(Lecturas!$B:$B=$A23)/(Lecturas!$D:$D>0),Lecturas!$D:$D),LOOKUP(2,1/(Lecturas!$B:$B=$A23)/(Lecturas!$C:$C>0),Lecturas!$C:$C)),"")} -> 3406 | P23: =IFERROR(_xlfn.MAXIFS(tblMantenciones[Fecha],tblMantenciones[Codigo],tblMaestroEquipos[[#This Row],[Codigo]],tblMantenciones[EsPM],"Sí"),"") -> 46188 | Q23: =IF(_xlfn.MAXIFS(Mantenciones!$D:$D,Mantenciones!$B:$B,A23)=0,"Sin datos de mantención registrado",_xlfn.MAXIFS(Mantenciones!$D:$D,Mantenciones!$B:$B,A23)) -> 3699 | R23: =IFERROR(IF(_xlfn.MAXIFS(Mantenciones!$D:$D,Mantenciones!$B:$B,$A23,Mantenciones!$E:$E,"Sí",Mantenciones!$D:$D,">0")=0,"Sin datos de mantención registrado",_xlfn.MAXIFS(Mantenciones!$D:$D,Mantenciones!$B:$B,$A23,Mantenciones!$E:$E,"Sí",Mantenciones!$D:$D,">0")),"Sin datos de mantención registrado") -> 3699 | S23: =IFERROR(SUMIFS(tblMantenciones[Costo Mantencion CLP],tblMantenciones[Codigo],A23),0) -> 0 | T23: =IFERROR(SUMIFS(tblComprasPM[Costo PM CLP],tblComprasPM[Codigo],tblMaestroEquipos[[#This Row],[Codigo]]),0) -> 327374.59 | U23: =IFERROR(tblMaestroEquipos[[#This Row],[Costo Mantenciones CLP]]+tblMaestroEquipos[[#This Row],[Costo Compras PM CLP]],0) -> 327374.59 | V23: =IFERROR(_xlfn.XLOOKUP(tblMaestroEquipos[[#This Row],[Codigo]],tblEquipos[Codigo],tblEquipos[Estado Base]),"") -> Operativo | W23: =IF(OR(TRIM($V23)="Fuera de Servicio",TRIM($V23)="Fuera de servicio"),"FUERA DE SERVICIO",IF(OR(TRIM($V23)="Taller",TRIM($V23)="En taller",TRIM($V23)="EN TALLER"),"EN TALLER",IF($AD23="PENDIENTE","POR RECIBIR",IF(AND($Z23<>"",$AA23=""),"EN PROCESO",IF(AND(ISNUMBER($X23),$X23<0),"ATRASADA",IF(AND(ISNUMBER($X23),$X23<=30),"PRÓXIMA","AL DÍA")))))) -> AL DÍA | X23: =IF(OR(NOT(ISNUMBER(R23)),NOT(ISNUMBER(J23)),NOT(ISNUMBER(O23))),"", (R23+J23)-O23) -> 793 | Y23: =IFERROR(IF(OR(tblMaestroEquipos[[#This Row],[Estado Operacional]]="FUERA DE SERVICIO",tblMaestroEquipos[[#This Row],[Ultima Fecha Lectura]]="",tblMaestroEquipos[[#This Row],[Dias a Proxima Mantencion]]=""),"",tblMaestroEquipos[[#This Row],[Ultima Fecha Lectura]]+tblMaestroEquipos[[#This Row],[Dias a Proxima Mantencion]]),"") -> 46879 | Z23: =IFERROR(IF(_xlfn.MINIFS(tblComprasPM[Fecha],tblComprasPM[Codigo],tblMaestroEquipos[[#This Row],[Codigo]])=0,"",_xlfn.MINIFS(tblComprasPM[Fecha],tblComprasPM[Codigo],tblMaestroEquipos[[#This Row],[Codigo]])),"") -> 46069.447 | AA23: =IFERROR(IF(_xlfn.MAXIFS(tblBodega[Fecha],tblBodega[Codigo],tblMaestroEquipos[[#This Row],[Codigo]])=0,"",_xlfn.MAXIFS(tblBodega[Fecha],tblBodega[Codigo],tblMaestroEquipos[[#This Row],[Codigo]])),"") -> 46080 | AB23: =IFERROR(IF(OR(tblMaestroEquipos[[#This Row],[Fecha Compra PM]]="",tblMaestroEquipos[[#This Row],[Fecha Compra PM]]=0),"",IF(OR(tblMaestroEquipos[[#This Row],[Ultima Fecha PM]]="",tblMaestroEquipos[[#This Row],[Ultima Fecha PM]]=0),MAX(0,INT(TODAY())-INT(tblMaestroEquipos[[#This Row],[Fecha Compra PM]])),MAX(0,INT(tblMaestroEquipos[[#This Row],[Ultima Fecha PM]])-INT(tblMaestroEquipos[[#This Row],[Fecha Compra PM]])))),"") -> 119 | AC23: =IFERROR(IF(OR(tblMaestroEquipos[[#This Row],[Fecha Salida Bodega]]="",tblMaestroEquipos[[#This Row],[Fecha Salida Bodega]]=0),"",IF(OR(tblMaestroEquipos[[#This Row],[Ultima Fecha PM]]="",tblMaestroEquipos[[#This Row],[Ultima Fecha PM]]=0),MAX(0,INT(TODAY())-INT(tblMaestroEquipos[[#This Row],[Fecha Salida Bodega]])),MAX(0,INT(tblMaestroEquipos[[#This Row],[Ultima Fecha PM]])-INT(tblMaestroEquipos[[#This Row],[Fecha Salida Bodega]])))),"") -> 108 | AD23: =IF(tblMaestroEquipos[[#This Row],[Fecha Salida Bodega]]="","SIN SALIDA BODEGA",IF(OR(tblMaestroEquipos[[#This Row],[Ultima Fecha PM]]="",tblMaestroEquipos[[#This Row],[Ultima Fecha PM]]<tblMaestroEquipos[[#This Row],[Fecha Salida Bodega]]),"PENDIENTE","CERRADO")) -> CERRADO | AE23: =IF(TRIM(V23)="Fuera de servicio","FUERA DE SERVICIO", IF(OR(TRIM(V23)="Taller",TRIM(V23)="En taller"),"EN TALLER", IF(W23="ATRASADO","ATRASADO", IF(W23="EN PROCESO","EN PROCESO", IF(W23="PRÓXIMO","PRÓXIMO", "OPERATIVO"))))) -> OPERATIVO | AF23: =IF($AE23="ATRASADA",IF($X23<=-15,"CRÍTICA","ALTA"),IF($AE23="PRÓXIMA","MEDIA",IF(OR($AE23="EN PROCESO",$AE23="POR RECIBIR"),"SEGUIMIENTO",IF($AE23="FUERA DE SERVICIO","NO APLICA","BAJA")))) -> BAJA | AG23: =IF($AE23="FUERA DE SERVICIO","No programar compra",IF($AE23="CERRADO","Cerrar ciclo y preparar siguiente PM",IF($AE23="EN PROCESO","Hacer seguimiento al taller y cerrar report",IF($AE23="POR RECIBIR","Acelerar recepción de repuestos",IF($AE23="ATRASADA","Comprar kit PM y coordinar ejecución",IF($AE23="PRÓXIMA","Planificar compra preventiva","Monitorear próximo vencimiento")))))) -> Monitorear próximo vencimiento | AH23: =IF(AND(OR($AE23="ATRASADA",$AE23="PRÓXIMA"),$Z23="",$AA23=""),1,0) -> 0 | AI23: =IF(OR($AH23=0,$Y23=""),"",SUMPRODUCT(($AH$4:$AH$242=1)*(($Y$4:$Y$242<$Y23)+(($Y$4:$Y$242=$Y23)*(ROW($Y$4:$Y$242)<=ROW()))))) | AJ23: =IF(W23="ATRASADA",1,IF(W23="EN PROCESO",2,IF(W23="POR RECIBIR",3,99))) -> 99
A24: CD-121 | B24: Camión Tolva | C24: Camiones de Ruta | D24: Man | E24: TGS 40400 BB | F24: 2024 | G24: =IFERROR(_xlfn.XLOOKUP($A24,tblEquipos[Codigo],tblEquipos[Ubicacion],""),"") -> Cobquecura | H24: Chandor Ruiz | I24: =IFERROR(VLOOKUP(A24, Equipos!A:J, 9, FALSE), "") -> HORAS | J24: =IFERROR(VLOOKUP(A24, Equipos!A:J, 10, FALSE), "") -> 500 | K24: =IFERROR(IF($I24="KM",ROUND((_xlfn.MAXIFS(tblLecturas[Kilometraje],tblLecturas[Codigo],$A24)-_xlfn.MINIFS(tblLecturas[Kilometraje],tblLecturas[Codigo],$A24))/(MAX(1,_xlfn.MAXIFS(tblLecturas[Fecha],tblLecturas[Codigo],$A24)-_xlfn.MINIFS(tblLecturas[Fecha],tblLecturas[Codigo],$A24))),1),ROUND((_xlfn.MAXIFS(tblLecturas[Horometro],tblLecturas[Codigo],$A24)-_xlfn.MINIFS(tblLecturas[Horometro],tblLecturas[Codigo],$A24))/(MAX(1,_xlfn.MAXIFS(tblLecturas[Fecha],tblLecturas[Codigo],$A24)-_xlfn.MINIFS(tblLecturas[Fecha],tblLecturas[Codigo],$A24))),1)),"") -> 3.1 | L24: =IFERROR(_xlfn.MAXIFS(tblLecturas[Fecha],tblLecturas[Codigo],$A24),"") -> 46111 | M24: =IFERROR(_xlfn.MAXIFS(Lecturas!$C:$C,Lecturas!$B:$B,$A24,Lecturas!$C:$C,">0"),"") -> 3552 | N24: =IFERROR(_xlfn.MAXIFS(tblLecturas[Kilometraje],tblLecturas[Codigo],$A24,tblLecturas[Kilometraje],">0"),"") -> 89291 | O24: {=IFERROR(IF($I24="KM",LOOKUP(2,1/(Lecturas!$B:$B=$A24)/(Lecturas!$D:$D>0),Lecturas!$D:$D),LOOKUP(2,1/(Lecturas!$B:$B=$A24)/(Lecturas!$C:$C>0),Lecturas!$C:$C)),"")} -> 3431 | P24: =IFERROR(_xlfn.MAXIFS(tblMantenciones[Fecha],tblMantenciones[Codigo],tblMaestroEquipos[[#This Row],[Codigo]],tblMantenciones[EsPM],"Sí"),"") -> 46085 | Q24: =IF(_xlfn.MAXIFS(Mantenciones!$D:$D,Mantenciones!$B:$B,A24)=0,"Sin datos de mantención registrado",_xlfn.MAXIFS(Mantenciones!$D:$D,Mantenciones!$B:$B,A24)) -> 3468 | R24: =IFERROR(IF(_xlfn.MAXIFS(Mantenciones!$D:$D,Mantenciones!$B:$B,$A24,Mantenciones!$E:$E,"Sí",Mantenciones!$D:$D,">0")=0,"Sin datos de mantención registrado",_xlfn.MAXIFS(Mantenciones!$D:$D,Mantenciones!$B:$B,$A24,Mantenciones!$E:$E,"Sí",Mantenciones!$D:$D,">0")),"Sin datos de mantención registrado") -> 3468 | S24: =IFERROR(SUMIFS(tblMantenciones[Costo Mantencion CLP],tblMantenciones[Codigo],A24),0) -> 0 | T24: =IFERROR(SUMIFS(tblComprasPM[Costo PM CLP],tblComprasPM[Codigo],tblMaestroEquipos[[#This Row],[Codigo]]),0) -> 274198.13 | U24: =IFERROR(tblMaestroEquipos[[#This Row],[Costo Mantenciones CLP]]+tblMaestroEquipos[[#This Row],[Costo Compras PM CLP]],0) -> 274198.13 | V24: =IFERROR(_xlfn.XLOOKUP(tblMaestroEquipos[[#This Row],[Codigo]],tblEquipos[Codigo],tblEquipos[Estado Base]),"") -> Operativo | W24: =IF(OR(TRIM($V24)="Fuera de Servicio",TRIM($V24)="Fuera de servicio"),"FUERA DE SERVICIO",IF(OR(TRIM($V24)="Taller",TRIM($V24)="En taller",TRIM($V24)="EN TALLER"),"EN TALLER",IF($AD24="PENDIENTE","POR RECIBIR",IF(AND($Z24<>"",$AA24=""),"EN PROCESO",IF(AND(ISNUMBER($X24),$X24<0),"ATRASADA",IF(AND(ISNUMBER($X24),$X24<=30),"PRÓXIMA","AL DÍA")))))) -> AL DÍA | X24: =IF(OR(NOT(ISNUMBER(R24)),NOT(ISNUMBER(J24)),NOT(ISNUMBER(O24))),"", (R24+J24)-O24) -> 537 | Y24: =IFERROR(IF(OR(tblMaestroEquipos[[#This Row],[Estado Operacional]]="FUERA DE SERVICIO",tblMaestroEquipos[[#This Row],[Ultima Fecha Lectura]]="",tblMaestroEquipos[[#This Row],[Dias a Proxima Mantencion]]=""),"",tblMaestroEquipos[[#This Row],[Ultima Fecha Lectura]]+tblMaestroEquipos[[#This Row],[Dias a Proxima Mantencion]]),"") -> 46648 | Z24: =IFERROR(IF(_xlfn.MINIFS(tblComprasPM[Fecha],tblComprasPM[Codigo],tblMaestroEquipos[[#This Row],[Codigo]])=0,"",_xlfn.MINIFS(tblComprasPM[Fecha],tblComprasPM[Codigo],tblMaestroEquipos[[#This Row],[Codigo]])),"") -> 46069.447 | AA24: =IFERROR(IF(_xlfn.MAXIFS(tblBodega[Fecha],tblBodega[Codigo],tblMaestroEquipos[[#This Row],[Codigo]])=0,"",_xlfn.MAXIFS(tblBodega[Fecha],tblBodega[Codigo],tblMaestroEquipos[[#This Row],[Codigo]])),"") -> 46080 | AB24: =IFERROR(IF(OR(tblMaestroEquipos[[#This Row],[Fecha Compra PM]]="",tblMaestroEquipos[[#This Row],[Fecha Compra PM]]=0),"",IF(OR(tblMaestroEquipos[[#This Row],[Ultima Fecha PM]]="",tblMaestroEquipos[[#This Row],[Ultima Fecha PM]]=0),MAX(0,INT(TODAY())-INT(tblMaestroEquipos[[#This Row],[Fecha Compra PM]])),MAX(0,INT(tblMaestroEquipos[[#This Row],[Ultima Fecha PM]])-INT(tblMaestroEquipos[[#This Row],[Fecha Compra PM]])))),"") -> 16 | AC24: =IFERROR(IF(OR(tblMaestroEquipos[[#This Row],[Fecha Salida Bodega]]="",tblMaestroEquipos[[#This Row],[Fecha Salida Bodega]]=0),"",IF(OR(tblMaestroEquipos[[#This Row],[Ultima Fecha PM]]="",tblMaestroEquipos[[#This Row],[Ultima Fecha PM]]=0),MAX(0,INT(TODAY())-INT(tblMaestroEquipos[[#This Row],[Fecha Salida Bodega]])),MAX(0,INT(tblMaestroEquipos[[#This Row],[Ultima Fecha PM]])-INT(tblMaestroEquipos[[#This Row],[Fecha Salida Bodega]])))),"") -> 5 | AD24: =IF(tblMaestroEquipos[[#This Row],[Fecha Salida Bodega]]="","SIN SALIDA BODEGA",IF(OR(tblMaestroEquipos[[#This Row],[Ultima Fecha PM]]="",tblMaestroEquipos[[#This Row],[Ultima Fecha PM]]<tblMaestroEquipos[[#This Row],[Fecha Salida Bodega]]),"PENDIENTE","CERRADO")) -> CERRADO | AE24: =IF(TRIM(V24)="Fuera de servicio","FUERA DE SERVICIO", IF(OR(TRIM(V24)="Taller",TRIM(V24)="En taller"),"EN TALLER", IF(W24="ATRASADO","ATRASADO", IF(W24="EN PROCESO","EN PROCESO", IF(W24="PRÓXIMO","PRÓXIMO", "OPERATIVO"))))) -> OPERATIVO | AF24: =IF($AE24="ATRASADA",IF($X24<=-15,"CRÍTICA","ALTA"),IF($AE24="PRÓXIMA","MEDIA",IF(OR($AE24="EN PROCESO",$AE24="POR RECIBIR"),"SEGUIMIENTO",IF($AE24="FUERA DE SERVICIO","NO APLICA","BAJA")))) -> BAJA | AG24: =IF($AE24="FUERA DE SERVICIO","No programar compra",IF($AE24="CERRADO","Cerrar ciclo y preparar siguiente PM",IF($AE24="EN PROCESO","Hacer seguimiento al taller y cerrar report",IF($AE24="POR RECIBIR","Acelerar recepción de repuestos",IF($AE24="ATRASADA","Comprar kit PM y coordinar ejecución",IF($AE24="PRÓXIMA","Planificar compra preventiva","Monitorear próximo vencimiento")))))) -> Monitorear próximo vencimiento | AH24: =IF(AND(OR($AE24="ATRASADA",$AE24="PRÓXIMA"),$Z24="",$AA24=""),1,0) -> 0 | AI24: =IF(OR($AH24=0,$Y24=""),"",SUMPRODUCT(($AH$4:$AH$242=1)*(($Y$4:$Y$242<$Y24)+(($Y$4:$Y$242=$Y24)*(ROW($Y$4:$Y$242)<=ROW()))))) | AJ24: =IF(W24="ATRASADA",1,IF(W24="EN PROCESO",2,IF(W24="POR RECIBIR",3,99))) -> 99
